Workbook
Name Users: Categories!$B$2:$B$15

Sheet Company lists
T1: =SUM(Table3[Column1]) -> 0 | U1: =SUM(Table3[Industry Essentials]) -> 1179 | V1: =SUM(Table3[Energy Supply Market Intelligence]) -> 244 | W1: =SUM(Table3[Energy Supply RTM Analysis]) -> 272 | X1: =SUM(Table3[Energy Supply Forecasts]) -> 244 | Y1: =SUM(Table3[Energy Supply Regulation]) -> 140 | Z1: =SUM(Table3[Renewables Market Intelligence]) -> 553 | AA1: =SUM(Table3[Renewables RTM Analysis]) -> 429 | AB1: =SUM(Table3[Renewables Forecasts]) -> 553 | AC1: =SUM(Table3[Renewables Regulation]) -> 382 | AD1: =SUM(Table3[Flexibility Market Intelligence]) -> 527 | AE1: =SUM(Table3[Flexibility RTM Analysis]) -> 268 | AF1: =SUM(Table3[Flexibility Forecasts]) -> 461 | AG1: =SUM(Table3[Flexibility Regulation]) -> 228 | AH1: =SUM(Table3[Business Energy Essentials]) -> 522 | AI1: =SUM(Table3[Energy User RTM Analysis]) -> 587 | AJ1: =SUM(Table3[Energy User Forecasts]) -> 531
A2: Company name | B2: CI subs customer? (existing and past 2 years) | C2: Consulting client? (past 2 years) | D2: Date added | E2: Scale | F2: Column19 | G2: Strategic priority segment | H2: Product fit | I2: Brand reach | J2: Competitive advantage | K2: Propensity to buy/ buyer readiness | L2: Overall scoring priority | M2: CI Segment | N2: Primary theme/sector | O2: Secondary theme/sector (1) | P2: Secondary theme/sector (2) | Q2: Secondary theme/sector (3) | R2: Secondary theme/sector (4) | S2: Secondary theme/sector (5) | T2: Column1 | U2: Industry Essentials | V2: Energy Supply Market Intelligence | W2: Energy Supply RTM Analysis | X2: Energy Supply Forecasts | Y2: Energy Supply Regulation | Z2: Renewables Market Intelligence | AA2: Renewables RTM Analysis | AB2: Renewables Forecasts | AC2: Renewables Regulation | AD2: Flexibility Market Intelligence | AE2: Flexibility RTM Analysis | AF2: Flexibility Forecasts | AG2: Flexibility Regulation | AH2: Business Energy Essentials | AI2: Energy User RTM Analysis | AJ2: Energy User Forecasts | AK2: Energy User Regulation | AL2: Column2 | AM2: Column3 | AN2: Column4 | AO2: Column5 | AP2: Column6 | AQ2: Column7 | AR2: Column8 | AS2: Column9 | AT2: Column10 | AU2: Column11 | AV2: Column12 | AW2: Column13 | AX2: Column14 | AY2: Column15 | AZ2: Column16 | BA2: Column17 | BB2: Column18 | BC2: Total Spend | BD2: Multiplier
A3: British Gas Trading Ltd | B3: Yes | D3: 45566 | E3: Large | F3: =INDEX(Definitions!$G$13:$G$17,MATCH(Table3[[#This Row],[Propensity to buy/ buyer readiness]],Definitions!$A$13:$A$17,0)) -> 250000 | G3: 5 | H3: 5 | I3: 5 | J3: 5 | K3: 5 | L3: =SUM(Table3[[#This Row],[Strategic priority segment]:[Propensity to buy/ buyer readiness]]) -> 25 | M3: Energy Supply | N3: Energy supplier | O3: Renewables generator/developer | P3: Flexibility generator/developer | Q3: Energy traders | U3: 1 | V3: 1 | W3: 1 | X3: 1 | Y3: 1 | Z3: 1 | AA3: 1 | AB3: 1 | AC3: 1 | AD3: 1 | AE3: 1 | AF3: 1 | AG3: 1 | AH3: 0 | AI3: 0 | AJ3: 0 | AK3: 0 | AL3: {=_xlfn.IFS(AND(Table3[[#This Row],[Scale]:[Scale]]="Large",Table3[[#This Row],[Industry Essentials]]=1),INDEX(Definitions!$C$21:$C$37,MATCH(Table3[[#Headers],[Industry Essentials]],Definitions!$A$21:$A$37,0)),AND(Table3[[#This Row],[Scale]:[Scale]]="Small",Table3[[#This Row],[Industry Essentials]]=1),INDEX(Definitions!$B$21:$B$37,MATCH(Table3[[#Headers],[Industry Essentials]],Definitions!$A$21:$A$37,0)),Table3[[#This Row],[Industry Essentials]]=0,0)} -> 10800 | AM3: {=_xlfn.IFS(AND(Table3[[#This Row],[Scale]:[Scale]]="Large",Table3[[#This Row],[Energy Supply Market Intelligence]]=1),INDEX(Definitions!$C$21:$C$37,MATCH(Table3[[#Headers],[Energy Supply Market Intelligence]],Definitions!$A$21:$A$37,0)),AND(Table3[[#This Row],[Scale]:[Scale]]="Small",Table3[[#This Row],[Energy Supply Market Intelligence]]=1),INDEX(Definitions!$B$21:$B$37,MATCH(Table3[[#Headers],[Energy Supply Market Intelligence]],Definitions!$A$21:$A$37,0)),Table3[[#This Row],[Energy Supply Market Intelligence]]=0,0)} -> 43200 | AN3: {=_xlfn.IFS(AND(Table3[[#This Row],[Scale]:[Scale]]="Large",Table3[[#This Row],[Energy Supply RTM Analysis]]=1),INDEX(Definitions!$C$21:$C$37,MATCH(Table3[[#Headers],[Energy Supply RTM Analysis]],Definitions!$A$21:$A$37,0)),AND(Table3[[#This Row],[Scale]:[Scale]]="Small",Table3[[#This Row],[Energy Supply RTM Analysis]]=1),INDEX(Definitions!$B$21:$B$37,MATCH(Table3[[#Headers],[Energy Supply RTM Analysis]],Definitions!$A$21:$A$37,0)),Table3[[#This Row],[Energy Supply RTM Analysis]]=0,0)} -> 73800 | AO3: {=_xlfn.IFS(AND(Table3[[#This Row],[Scale]:[Scale]]="Large",Table3[[#This Row],[Energy Supply Forecasts]]=1),INDEX(Definitions!$C$21:$C$37,MATCH(Table3[[#Headers],[Energy Supply Forecasts]],Definitions!$A$21:$A$37,0)),AND(Table3[[#This Row],[Scale]:[Scale]]="Small",Table3[[#This Row],[Energy Supply Forecasts]]=1),INDEX(Definitions!$B$21:$B$37,MATCH(Table3[[#Headers],[Energy Supply Forecasts]],Definitions!$A$21:$A$37,0)),Table3[[#This Row],[Energy Supply Forecasts]]=0,0)} -> 48600 | AP3: {=_xlfn.IFS(AND(Table3[[#This Row],[Scale]:[Scale]]="Large",Table3[[#This Row],[Energy Supply Regulation]]=1),INDEX(Definitions!$C$21:$C$37,MATCH(Table3[[#Headers],[Energy Supply Regulation]],Definitions!$A$21:$A$37,0)),AND(Table3[[#This Row],[Scale]:[Scale]]="Small",Table3[[#This Row],[Energy Supply Regulation]]=1),INDEX(Definitions!$B$21:$B$37,MATCH(Table3[[#Headers],[Energy Supply Regulation]],Definitions!$A$21:$A$37,0)),Table3[[#This Row],[Energy Supply Regulation]]=0,0)} -> 55800 | AQ3: {=_xlfn.IFS(AND(Table3[[#This Row],[Scale]:[Scale]]="Large",Table3[[#This Row],[Renewables Market Intelligence]]=1),INDEX(Definitions!$C$21:$C$37,MATCH(Table3[[#Headers],[Renewables Market Intelligence]],Definitions!$A$21:$A$37,0)),AND(Table3[[#This Row],[Scale]:[Scale]]="Small",Table3[[#This Row],[Renewables Market Intelligence]]=1),INDEX(Definitions!$B$21:$B$37,MATCH(Table3[[#Headers],[Renewables Market Intelligence]],Definitions!$A$21:$A$37,0)),Table3[[#This Row],[Renewables Market Intelligence]]=0,0)} -> 23400 | AR3: {=_xlfn.IFS(AND(Table3[[#This Row],[Scale]:[Scale]]="Large",Table3[[#This Row],[Renewables RTM Analysis]]=1),INDEX(Definitions!$C$21:$C$37,MATCH(Table3[[#Headers],[Renewables RTM Analysis]],Definitions!$A$21:$A$37,0)),AND(Table3[[#This Row],[Scale]:[Scale]]="Small",Table3[[#This Row],[Renewables RTM Analysis]]=1),INDEX(Definitions!$B$21:$B$37,MATCH(Table3[[#Headers],[Renewables RTM Analysis]],Definitions!$A$21:$A$37,0)),Table3[[#This Row],[Renewables RTM Analysis]]=0,0)} -> 20700 | AS3: {=_xlfn.IFS(AND(Table3[[#This Row],[Scale]:[Scale]]="Large",Table3[[#This Row],[Renewables Forecasts]]=1),INDEX(Definitions!$C$21:$C$37,MATCH(Table3[[#Headers],[Renewables Forecasts]],Definitions!$A$21:$A$37,0)),AND(Table3[[#This Row],[Scale]:[Scale]]="Small",Table3[[#This Row],[Renewables Forecasts]]=1),INDEX(Definitions!$B$21:$B$37,MATCH(Table3[[#Headers],[Renewables Forecasts]],Definitions!$A$21:$A$37,0)),Table3[[#This Row],[Renewables Forecasts]]=0,0)} -> 59400 | AT3: {=_xlfn.IFS(AND(Table3[[#This Row],[Scale]:[Scale]]="Large",Table3[[#This Row],[Renewables Regulation]]=1),INDEX(Definitions!$C$21:$C$37,MATCH(Table3[[#Headers],[Renewables Regulation]],Definitions!$A$21:$A$37,0)),AND(Table3[[#This Row],[Scale]:[Scale]]="Small",Table3[[#This Row],[Renewables Regulation]]=1),INDEX(Definitions!$B$21:$B$37,MATCH(Table3[[#Headers],[Renewables Regulation]],Definitions!$A$21:$A$37,0)),Table3[[#This Row],[Renewables Regulation]]=0,0)} -> 26100 | AU3: {=_xlfn.IFS(AND(Table3[[#This Row],[Scale]:[Scale]]="Large",Table3[[#This Row],[Flexibility Market Intelligence]]=1),INDEX(Definitions!$C$21:$C$37,MATCH(Table3[[#Headers],[Flexibility Market Intelligence]],Definitions!$A$21:$A$37,0)),AND(Table3[[#This Row],[Scale]:[Scale]]="Small",Table3[[#This Row],[Flexibility Market Intelligence]]=1),INDEX(Definitions!$B$21:$B$37,MATCH(Table3[[#Headers],[Flexibility Market Intelligence]],Definitions!$A$21:$A$37,0)),Table3[[#This Row],[Flexibility Market Intelligence]]=0,0)} -> 29700 | AV3: {=_xlfn.IFS(AND(Table3[[#This Row],[Scale]:[Scale]]="Large",Table3[[#This Row],[Flexibility RTM Analysis]]=1),INDEX(Definitions!$C$21:$C$37,MATCH(Table3[[#Headers],[Flexibility RTM Analysis]],Definitions!$A$21:$A$37,0)),AND(Table3[[#This Row],[Scale]:[Scale]]="Small",Table3[[#This Row],[Flexibility RTM Analysis]]=1),INDEX(Definitions!$B$21:$B$37,MATCH(Table3[[#Headers],[Flexibility RTM Analysis]],Definitions!$A$21:$A$37,0)),Table3[[#This Row],[Flexibility RTM Analysis]]=0,0)} -> 10800 | AW3: {=_xlfn.IFS(AND(Table3[[#This Row],[Scale]:[Scale]]="Large",Table3[[#This Row],[Flexibility Forecasts]]=1),INDEX(Definitions!$C$21:$C$37,MATCH(Table3[[#Headers],[Flexibility Forecasts]],Definitions!$A$21:$A$37,0)),AND(Table3[[#This Row],[Scale]:[Scale]]="Small",Table3[[#This Row],[Flexibility Forecasts]]=1),INDEX(Definitions!$B$21:$B$37,MATCH(Table3[[#Headers],[Flexibility Forecasts]],Definitions!$A$21:$A$37,0)),Table3[[#This Row],[Flexibility Forecasts]]=0,0)} -> 44100 | AX3: {=_xlfn.IFS(AND(Table3[[#This Row],[Scale]:[Scale]]="Large",Table3[[#This Row],[Flexibility Regulation]]=1),INDEX(Definitions!$C$21:$C$37,MATCH(Table3[[#Headers],[Flexibility Regulation]],Definitions!$A$21:$A$37,0)),AND(Table3[[#This Row],[Scale]:[Scale]]="Small",Table3[[#This Row],[Flexibility Regulation]]=1),INDEX(Definitions!$B$21:$B$37,MATCH(Table3[[#Headers],[Flexibility Regulation]],Definitions!$A$21:$A$37,0)),Table3[[#This Row],[Flexibility Regulation]]=0,0)} -> 36000 | AY3: {=_xlfn.IFS(AND(Table3[[#This Row],[Scale]:[Scale]]="Large",Table3[[#This Row],[Business Energy Essentials]]=1),INDEX(Definitions!$C$21:$C$37,MATCH(Table3[[#Headers],[Business Energy Essentials]],Definitions!$A$21:$A$37,0)),AND(Table3[[#This Row],[Scale]:[Scale]]="Small",Table3[[#This Row],[Business Energy Essentials]]=1),INDEX(Definitions!$B$21:$B$37,MATCH(Table3[[#Headers],[Business Energy Essentials]],Definitions!$A$21:$A$37,0)),Table3[[#This Row],[Business Energy Essentials]]=0,0)} -> 0 | AZ3: {=_xlfn.IFS(AND(Table3[[#This Row],[Scale]:[Scale]]="Large",Table3[[#This Row],[Energy User RTM Analysis]]=1),INDEX(Definitions!$C$21:$C$37,MATCH(Table3[[#Headers],[Energy User RTM Analysis]],Definitions!$A$21:$A$37,0)),AND(Table3[[#This Row],[Scale]:[Scale]]="Small",Table3[[#This Row],[Energy User RTM Analysis]]=1),INDEX(Definitions!$B$21:$B$37,MATCH(Table3[[#Headers],[Energy User RTM Analysis]],Definitions!$A$21:$A$37,0)),Table3[[#This Row],[Energy User RTM Analysis]]=0,0)} -> 0 | BA3: {=_xlfn.IFS(AND(Table3[[#This Row],[Scale]:[Scale]]="Large",Table3[[#This Row],[Energy User Forecasts]]=1),INDEX(Definitions!$C$21:$C$37,MATCH(Table3[[#Headers],[Energy User Forecasts]],Definitions!$A$21:$A$37,0)),AND(Table3[[#This Row],[Scale]:[Scale]]="Small",Table3[[#This Row],[Energy User Forecasts]]=1),INDEX(Definitions!$B$21:$B$37,MATCH(Table3[[#Headers],[Energy User Forecasts]],Definitions!$A$21:$A$37,0)),Table3[[#This Row],[Energy User Forecasts]]=0,0)} -> 0 | BB3: {=_xlfn.IFS(AND(Table3[[#This Row],[Scale]:[Scale]]="Large",Table3[[#This Row],[Energy User Regulation]]=1),INDEX(Definitions!$C$21:$C$37,MATCH(Table3[[#Headers],[Energy User Regulation]],Definitions!$A$21:$A$37,0)),AND(Table3[[#This Row],[Scale]:[Scale]]="Small",Table3[[#This Row],[Energy User Regulation]]=1),INDEX(Definitions!$B$21:$B$37,MATCH(Table3[[#Headers],[Energy User Regulation]],Definitions!$A$21:$A$37,0)),Table3[[#This Row],[Energy User Regulation]]=0,0)} -> 0 | BC3: =IF(SUM(Table3[[#This Row],[Column2]:[Column18]])>Table3[[#This Row],[Column19]],Table3[[#This Row],[Column19]],SUM(Table3[[#This Row],[Column2]:[Column18]])) -> 250000 | BD3: =Table3[[#This Row],[Total Spend]]/SUM(Table3[[#This Row],[Column2]:[Column18]]) -> 0.51824212
A4: Centrica Energy Limited | B4: Yes | C4: Yes | D4: 45566 | E4: Large | F4: =INDEX(Definitions!$G$13:$G$17,MATCH(Table3[[#This Row],[Propensity to buy/ buyer readiness]],Definitions!$A$13:$A$17,0)) -> 250000 | G4: 5 | H4: 5 | I4: 5 | J4: 5 | K4: 5 | L4: =SUM(Table3[[#This Row],[Strategic priority segment]:[Propensity to buy/ buyer readiness]]) -> 25 | M4: Energy Supply | N4: Energy supplier | O4: Renewables generator/developer | P4: Flexibility generator/developer | Q4: Energy traders | U4: 1 | V4: 1 | W4: 1 | X4: 1 | Y4: 1 | Z4: 1 | AA4: 1 | AB4: 1 | AC4: 1 | AD4: 1 | AE4: 1 | AF4: 1 | AG4: 1 | AH4: 0 | AI4: 0 | AJ4: 0 | AK4: 0 | AL4: {=_xlfn.IFS(AND(Table3[[#This Row],[Scale]:[Scale]]="Large",Table3[[#This Row],[Industry Essentials]]=1),INDEX(Definitions!$C$21:$C$37,MATCH(Table3[[#Headers],[Industry Essentials]],Definitions!$A$21:$A$37,0)),AND(Table3[[#This Row],[Scale]:[Scale]]="Small",Table3[[#This Row],[Industry Essentials]]=1),INDEX(Definitions!$B$21:$B$37,MATCH(Table3[[#Headers],[Industry Essentials]],Definitions!$A$21:$A$37,0)),Table3[[#This Row],[Industry Essentials]]=0,0)} -> 10800 | AM4: {=_xlfn.IFS(AND(Table3[[#This Row],[Scale]:[Scale]]="Large",Table3[[#This Row],[Energy Supply Market Intelligence]]=1),INDEX(Definitions!$C$21:$C$37,MATCH(Table3[[#Headers],[Energy Supply Market Intelligence]],Definitions!$A$21:$A$37,0)),AND(Table3[[#This Row],[Scale]:[Scale]]="Small",Table3[[#This Row],[Energy Supply Market Intelligence]]=1),INDEX(Definitions!$B$21:$B$37,MATCH(Table3[[#Headers],[Energy Supply Market Intelligence]],Definitions!$A$21:$A$37,0)),Table3[[#This Row],[Energy Supply Market Intelligence]]=0,0)} -> 43200 | AN4: {=_xlfn.IFS(AND(Table3[[#This Row],[Scale]:[Scale]]="Large",Table3[[#This Row],[Energy Supply RTM Analysis]]=1),INDEX(Definitions!$C$21:$C$37,MATCH(Table3[[#Headers],[Energy Supply RTM Analysis]],Definitions!$A$21:$A$37,0)),AND(Table3[[#This Row],[Scale]:[Scale]]="Small",Table3[[#This Row],[Energy Supply RTM Analysis]]=1),INDEX(Definitions!$B$21:$B$37,MATCH(Table3[[#Headers],[Energy Supply RTM Analysis]],Definitions!$A$21:$A$37,0)),Table3[[#This Row],[Energy Supply RTM Analysis]]=0,0)} -> 73800 | AO4: {=_xlfn.IFS(AND(Table3[[#This Row],[Scale]:[Scale]]="Large",Table3[[#This Row],[Energy Supply Forecasts]]=1),INDEX(Definitions!$C$21:$C$37,MATCH(Table3[[#Headers],[Energy Supply Forecasts]],Definitions!$A$21:$A$37,0)),AND(Table3[[#This Row],[Scale]:[Scale]]="Small",Table3[[#This Row],[Energy Supply Forecasts]]=1),INDEX(Definitions!$B$21:$B$37,MATCH(Table3[[#Headers],[Energy Supply Forecasts]],Definitions!$A$21:$A$37,0)),Table3[[#This Row],[Energy Supply Forecasts]]=0,0)} -> 48600 | AP4: {=_xlfn.IFS(AND(Table3[[#This Row],[Scale]:[Scale]]="Large",Table3[[#This Row],[Energy Supply Regulation]]=1),INDEX(Definitions!$C$21:$C$37,MATCH(Table3[[#Headers],[Energy Supply Regulation]],Definitions!$A$21:$A$37,0)),AND(Table3[[#This Row],[Scale]:[Scale]]="Small",Table3[[#This Row],[Energy Supply Regulation]]=1),INDEX(Definitions!$B$21:$B$37,MATCH(Table3[[#Headers],[Energy Supply Regulation]],Definitions!$A$21:$A$37,0)),Table3[[#This Row],[Energy Supply Regulation]]=0,0)} -> 55800 | AQ4: {=_xlfn.IFS(AND(Table3[[#This Row],[Scale]:[Scale]]="Large",Table3[[#This Row],[Renewables Market Intelligence]]=1),INDEX(Definitions!$C$21:$C$37,MATCH(Table3[[#Headers],[Renewables Market Intelligence]],Definitions!$A$21:$A$37,0)),AND(Table3[[#This Row],[Scale]:[Scale]]="Small",Table3[[#This Row],[Renewables Market Intelligence]]=1),INDEX(Definitions!$B$21:$B$37,MATCH(Table3[[#Headers],[Renewables Market Intelligence]],Definitions!$A$21:$A$37,0)),Table3[[#This Row],[Renewables Market Intelligence]]=0,0)} -> 23400 | AR4: {=_xlfn.IFS(AND(Table3[[#This Row],[Scale]:[Scale]]="Large",Table3[[#This Row],[Renewables RTM Analysis]]=1),INDEX(Definitions!$C$21:$C$37,MATCH(Table3[[#Headers],[Renewables RTM Analysis]],Definitions!$A$21:$A$37,0)),AND(Table3[[#This Row],[Scale]:[Scale]]="Small",Table3[[#This Row],[Renewables RTM Analysis]]=1),INDEX(Definitions!$B$21:$B$37,MATCH(Table3[[#Headers],[Renewables RTM Analysis]],Definitions!$A$21:$A$37,0)),Table3[[#This Row],[Renewables RTM Analysis]]=0,0)} -> 20700 | AS4: {=_xlfn.IFS(AND(Table3[[#This Row],[Scale]:[Scale]]="Large",Table3[[#This Row],[Renewables Forecasts]]=1),INDEX(Definitions!$C$21:$C$37,MATCH(Table3[[#Headers],[Renewables Forecasts]],Definitions!$A$21:$A$37,0)),AND(Table3[[#This Row],[Scale]:[Scale]]="Small",Table3[[#This Row],[Renewables Forecasts]]=1),INDEX(Definitions!$B$21:$B$37,MATCH(Table3[[#Headers],[Renewables Forecasts]],Definitions!$A$21:$A$37,0)),Table3[[#This Row],[Renewables Forecasts]]=0,0)} -> 59400 | AT4: {=_xlfn.IFS(AND(Table3[[#This Row],[Scale]:[Scale]]="Large",Table3[[#This Row],[Renewables Regulation]]=1),INDEX(Definitions!$C$21:$C$37,MATCH(Table3[[#Headers],[Renewables Regulation]],Definitions!$A$21:$A$37,0)),AND(Table3[[#This Row],[Scale]:[Scale]]="Small",Table3[[#This Row],[Renewables Regulation]]=1),INDEX(Definitions!$B$21:$B$37,MATCH(Table3[[#Headers],[Renewables Regulation]],Definitions!$A$21:$A$37,0)),Table3[[#This Row],[Renewables Regulation]]=0,0)} -> 26100 | AU4: {=_xlfn.IFS(AND(Table3[[#This Row],[Scale]:[Scale]]="Large",Table3[[#This Row],[Flexibility Market Intelligence]]=1),INDEX(Definitions!$C$21:$C$37,MATCH(Table3[[#Headers],[Flexibility Market Intelligence]],Definitions!$A$21:$A$37,0)),AND(Table3[[#This Row],[Scale]:[Scale]]="Small",Table3[[#This Row],[Flexibility Market Intelligence]]=1),INDEX(Definitions!$B$21:$B$37,MATCH(Table3[[#Headers],[Flexibility Market Intelligence]],Definitions!$A$21:$A$37,0)),Table3[[#This Row],[Flexibility Market Intelligence]]=0,0)} -> 29700 | AV4: {=_xlfn.IFS(AND(Table3[[#This Row],[Scale]:[Scale]]="Large",Table3[[#This Row],[Flexibility RTM Analysis]]=1),INDEX(Definitions!$C$21:$C$37,MATCH(Table3[[#Headers],[Flexibility RTM Analysis]],Definitions!$A$21:$A$37,0)),AND(Table3[[#This Row],[Scale]:[Scale]]="Small",Table3[[#This Row],[Flexibility RTM Analysis]]=1),INDEX(Definitions!$B$21:$B$37,MATCH(Table3[[#Headers],[Flexibility RTM Analysis]],Definitions!$A$21:$A$37,0)),Table3[[#This Row],[Flexibility RTM Analysis]]=0,0)} -> 10800 | AW4: {=_xlfn.IFS(AND(Table3[[#This Row],[Scale]:[Scale]]="Large",Table3[[#This Row],[Flexibility Forecasts]]=1),INDEX(Definitions!$C$21:$C$37,MATCH(Table3[[#Headers],[Flexibility Forecasts]],Definitions!$A$21:$A$37,0)),AND(Table3[[#This Row],[Scale]:[Scale]]="Small",Table3[[#This Row],[Flexibility Forecasts]]=1),INDEX(Definitions!$B$21:$B$37,MATCH(Table3[[#Headers],[Flexibility Forecasts]],Definitions!$A$21:$A$37,0)),Table3[[#This Row],[Flexibility Forecasts]]=0,0)} -> 44100 | AX4: {=_xlfn.IFS(AND(Table3[[#This Row],[Scale]:[Scale]]="Large",Table3[[#This Row],[Flexibility Regulation]]=1),INDEX(Definitions!$C$21:$C$37,MATCH(Table3[[#Headers],[Flexibility Regulation]],Definitions!$A$21:$A$37,0)),AND(Table3[[#This Row],[Scale]:[Scale]]="Small",Table3[[#This Row],[Flexibility Regulation]]=1),INDEX(Definitions!$B$21:$B$37,MATCH(Table3[[#Headers],[Flexibility Regulation]],Definitions!$A$21:$A$37,0)),Table3[[#This Row],[Flexibility Regulation]]=0,0)} -> 36000 | AY4: {=_xlfn.IFS(AND(Table3[[#This Row],[Scale]:[Scale]]="Large",Table3[[#This Row],[Business Energy Essentials]]=1),INDEX(Definitions!$C$21:$C$37,MATCH(Table3[[#Headers],[Business Energy Essentials]],Definitions!$A$21:$A$37,0)),AND(Table3[[#This Row],[Scale]:[Scale]]="Small",Table3[[#This Row],[Business Energy Essentials]]=1),INDEX(Definitions!$B$21:$B$37,MATCH(Table3[[#Headers],[Business Energy Essentials]],Definitions!$A$21:$A$37,0)),Table3[[#This Row],[Business Energy Essentials]]=0,0)} -> 0 | AZ4: {=_xlfn.IFS(AND(Table3[[#This Row],[Scale]:[Scale]]="Large",Table3[[#This Row],[Energy User RTM Analysis]]=1),INDEX(Definitions!$C$21:$C$37,MATCH(Table3[[#Headers],[Energy User RTM Analysis]],Definitions!$A$21:$A$37,0)),AND(Table3[[#This Row],[Scale]:[Scale]]="Small",Table3[[#This Row],[Energy User RTM Analysis]]=1),INDEX(Definitions!$B$21:$B$37,MATCH(Table3[[#Headers],[Energy User RTM Analysis]],Definitions!$A$21:$A$37,0)),Table3[[#This Row],[Energy User RTM Analysis]]=0,0)} -> 0 | BA4: {=_xlfn.IFS(AND(Table3[[#This Row],[Scale]:[Scale]]="Large",Table3[[#This Row],[Energy User Forecasts]]=1),INDEX(Definitions!$C$21:$C$37,MATCH(Table3[[#Headers],[Energy User Forecasts]],Definitions!$A$21:$A$37,0)),AND(Table3[[#This Row],[Scale]:[Scale]]="Small",Table3[[#This Row],[Energy User Forecasts]]=1),INDEX(Definitions!$B$21:$B$37,MATCH(Table3[[#Headers],[Energy User Forecasts]],Definitions!$A$21:$A$37,0)),Table3[[#This Row],[Energy User Forecasts]]=0,0)} -> 0 | BB4: {=_xlfn.IFS(AND(Table3[[#This Row],[Scale]:[Scale]]="Large",Table3[[#This Row],[Energy User Regulation]]=1),INDEX(Definitions!$C$21:$C$37,MATCH(Table3[[#Headers],[Energy User Regulation]],Definitions!$A$21:$A$37,0)),AND(Table3[[#This Row],[Scale]:[Scale]]="Small",Table3[[#This Row],[Energy User Regulation]]=1),INDEX(Definitions!$B$21:$B$37,MATCH(Table3[[#Headers],[Energy User Regulation]],Definitions!$A$21:$A$37,0)),Table3[[#This Row],[Energy User Regulation]]=0,0)} -> 0 | BC4: =IF(SUM(Table3[[#This Row],[Column2]:[Column18]])>Table3[[#This Row],[Column19]],Table3[[#This Row],[Column19]],SUM(Table3[[#This Row],[Column2]:[Column18]])) -> 250000 | BD4: =Table3[[#This Row],[Total Spend]]/SUM(Table3[[#This Row],[Column2]:[Column18]]) -> 0.51824212
A5: Conrad Energy Limited | B5: Yes | C5: Yes | D5: 45566 | E5: Large | F5: =INDEX(Definitions!$G$13:$G$17,MATCH(Table3[[#This Row],[Propensity to buy/ buyer readiness]],Definitions!$A$13:$A$17,0)) -> 250000 | G5: 5 | H5: 5 | I5: 5 | J5: 5 | K5: 5 | L5: =SUM(Table3[[#This Row],[Strategic priority segment]:[Propensity to buy/ buyer readiness]]) -> 25 | M5: Flex Generation & Storage | N5: Flexibility generator/developer | O5: Energy traders | P5: Energy supplier | U5: 1 | V5: 1 | W5: 1 | X5: 1 | Y5: 1 | Z5: 0 | AA5: 1 | AB5: 0 | AC5: 0 | AD5: 1 | AE5: 1 | AF5: 1 | AG5: 1 | AH5: 0 | AI5: 0 | AJ5: 0 | AK5: 0 | AL5: {=_xlfn.IFS(AND(Table3[[#This Row],[Scale]:[Scale]]="Large",Table3[[#This Row],[Industry Essentials]]=1),INDEX(Definitions!$C$21:$C$37,MATCH(Table3[[#Headers],[Industry Essentials]],Definitions!$A$21:$A$37,0)),AND(Table3[[#This Row],[Scale]:[Scale]]="Small",Table3[[#This Row],[Industry Essentials]]=1),INDEX(Definitions!$B$21:$B$37,MATCH(Table3[[#Headers],[Industry Essentials]],Definitions!$A$21:$A$37,0)),Table3[[#This Row],[Industry Essentials]]=0,0)} -> 10800 | AM5: {=_xlfn.IFS(AND(Table3[[#This Row],[Scale]:[Scale]]="Large",Table3[[#This Row],[Energy Supply Market Intelligence]]=1),INDEX(Definitions!$C$21:$C$37,MATCH(Table3[[#Headers],[Energy Supply Market Intelligence]],Definitions!$A$21:$A$37,0)),AND(Table3[[#This Row],[Scale]:[Scale]]="Small",Table3[[#This Row],[Energy Supply Market Intelligence]]=1),INDEX(Definitions!$B$21:$B$37,MATCH(Table3[[#Headers],[Energy Supply Market Intelligence]],Definitions!$A$21:$A$37,0)),Table3[[#This Row],[Energy Supply Market Intelligence]]=0,0)} -> 43200 | AN5: {=_xlfn.IFS(AND(Table3[[#This Row],[Scale]:[Scale]]="Large",Table3[[#This Row],[Energy Supply RTM Analysis]]=1),INDEX(Definitions!$C$21:$C$37,MATCH(Table3[[#Headers],[Energy Supply RTM Analysis]],Definitions!$A$21:$A$37,0)),AND(Table3[[#This Row],[Scale]:[Scale]]="Small",Table3[[#This Row],[Energy Supply RTM Analysis]]=1),INDEX(Definitions!$B$21:$B$37,MATCH(Table3[[#Headers],[Energy Supply RTM Analysis]],Definitions!$A$21:$A$37,0)),Table3[[#This Row],[Energy Supply RTM Analysis]]=0,0)} -> 73800 | AO5: {=_xlfn.IFS(AND(Table3[[#This Row],[Scale]:[Scale]]="Large",Table3[[#This Row],[Energy Supply Forecasts]]=1),INDEX(Definitions!$C$21:$C$37,MATCH(Table3[[#Headers],[Energy Supply Forecasts]],Definitions!$A$21:$A$37,0)),AND(Table3[[#This Row],[Scale]:[Scale]]="Small",Table3[[#This Row],[Energy Supply Forecasts]]=1),INDEX(Definitions!$B$21:$B$37,MATCH(Table3[[#Headers],[Energy Supply Forecasts]],Definitions!$A$21:$A$37,0)),Table3[[#This Row],[Energy Supply Forecasts]]=0,0)} -> 48600 | AP5: {=_xlfn.IFS(AND(Table3[[#This Row],[Scale]:[Scale]]="Large",Table3[[#This Row],[Energy Supply Regulation]]=1),INDEX(Definitions!$C$21:$C$37,MATCH(Table3[[#Headers],[Energy Supply Regulation]],Definitions!$A$21:$A$37,0)),AND(Table3[[#This Row],[Scale]:[Scale]]="Small",Table3[[#This Row],[Energy Supply Regulation]]=1),INDEX(Definitions!$B$21:$B$37,MATCH(Table3[[#Headers],[Energy Supply Regulation]],Definitions!$A$21:$A$37,0)),Table3[[#This Row],[Energy Supply Regulation]]=0,0)} -> 55800 | AQ5: {=_xlfn.IFS(AND(Table3[[#This Row],[Scale]:[Scale]]="Large",Table3[[#This Row],[Renewables Market Intelligence]]=1),INDEX(Definitions!$C$21:$C$37,MATCH(Table3[[#Headers],[Renewables Market Intelligence]],Definitions!$A$21:$A$37,0)),AND(Table3[[#This Row],[Scale]:[Scale]]="Small",Table3[[#This Row],[Renewables Market Intelligence]]=1),INDEX(Definitions!$B$21:$B$37,MATCH(Table3[[#Headers],[Renewables Market Intelligence]],Definitions!$A$21:$A$37,0)),Table3[[#This Row],[Renewables Market Intelligence]]=0,0)} -> 0 | AR5: {=_xlfn.IFS(AND(Table3[[#This Row],[Scale]:[Scale]]="Large",Table3[[#This Row],[Renewables RTM Analysis]]=1),INDEX(Definitions!$C$21:$C$37,MATCH(Table3[[#Headers],[Renewables RTM Analysis]],Definitions!$A$21:$A$37,0)),AND(Table3[[#This Row],[Scale]:[Scale]]="Small",Table3[[#This Row],[Renewables RTM Analysis]]=1),INDEX(Definitions!$B$21:$B$37,MATCH(Table3[[#Headers],[Renewables RTM Analysis]],Definitions!$A$21:$A$37,0)),Table3[[#This Row],[Renewables RTM Analysis]]=0,0)} -> 20700 | AS5: {=_xlfn.IFS(AND(Table3[[#This Row],[Scale]:[Scale]]="Large",Table3[[#This Row],[Renewables Forecasts]]=1),INDEX(Definitions!$C$21:$C$37,MATCH(Table3[[#Headers],[Renewables Forecasts]],Definitions!$A$21:$A$37,0)),AND(Table3[[#This Row],[Scale]:[Scale]]="Small",Table3[[#This Row],[Renewables Forecasts]]=1),INDEX(Definitions!$B$21:$B$37,MATCH(Table3[[#Headers],[Renewables Forecasts]],Definitions!$A$21:$A$37,0)),Table3[[#This Row],[Renewables Forecasts]]=0,0)} -> 0 | AT5: {=_xlfn.IFS(AND(Table3[[#This Row],[Scale]:[Scale]]="Large",Table3[[#This Row],[Renewables Regulation]]=1),INDEX(Definitions!$C$21:$C$37,MATCH(Table3[[#Headers],[Renewables Regulation]],Definitions!$A$21:$A$37,0)),AND(Table3[[#This Row],[Scale]:[Scale]]="Small",Table3[[#This Row],[Renewables Regulation]]=1),INDEX(Definitions!$B$21:$B$37,MATCH(Table3[[#Headers],[Renewables Regulation]],Definitions!$A$21:$A$37,0)),Table3[[#This Row],[Renewables Regulation]]=0,0)} -> 0 | AU5: {=_xlfn.IFS(AND(Table3[[#This Row],[Scale]:[Scale]]="Large",Table3[[#This Row],[Flexibility Market Intelligence]]=1),INDEX(Definitions!$C$21:$C$37,MATCH(Table3[[#Headers],[Flexibility Market Intelligence]],Definitions!$A$21:$A$37,0)),AND(Table3[[#This Row],[Scale]:[Scale]]="Small",Table3[[#This Row],[Flexibility Market Intelligence]]=1),INDEX(Definitions!$B$21:$B$37,MATCH(Table3[[#Headers],[Flexibility Market Intelligence]],Definitions!$A$21:$A$37,0)),Table3[[#This Row],[Flexibility Market Intelligence]]=0,0)} -> 29700 | AV5: {=_xlfn.IFS(AND(Table3[[#This Row],[Scale]:[Scale]]="Large",Table3[[#This Row],[Flexibility RTM Analysis]]=1),INDEX(Definitions!$C$21:$C$37,MATCH(Table3[[#Headers],[Flexibility RTM Analysis]],Definitions!$A$21:$A$37,0)),AND(Table3[[#This Row],[Scale]:[Scale]]="Small",Table3[[#This Row],[Flexibility RTM Analysis]]=1),INDEX(Definitions!$B$21:$B$37,MATCH(Table3[[#Headers],[Flexibility RTM Analysis]],Definitions!$A$21:$A$37,0)),Table3[[#This Row],[Flexibility RTM Analysis]]=0,0)} -> 10800 | AW5: {=_xlfn.IFS(AND(Table3[[#This Row],[Scale]:[Scale]]="Large",Table3[[#This Row],[Flexibility Forecasts]]=1),INDEX(Definitions!$C$21:$C$37,MATCH(Table3[[#Headers],[Flexibility Forecasts]],Definitions!$A$21:$A$37,0)),AND(Table3[[#This Row],[Scale]:[Scale]]="Small",Table3[[#This Row],[Flexibility Forecasts]]=1),INDEX(Definitions!$B$21:$B$37,MATCH(Table3[[#Headers],[Flexibility Forecasts]],Definitions!$A$21:$A$37,0)),Table3[[#This Row],[Flexibility Forecasts]]=0,0)} -> 44100 | AX5: {=_xlfn.IFS(AND(Table3[[#This Row],[Scale]:[Scale]]="Large",Table3[[#This Row],[Flexibility Regulation]]=1),INDEX(Definitions!$C$21:$C$37,MATCH(Table3[[#Headers],[Flexibility Regulation]],Definitions!$A$21:$A$37,0)),AND(Table3[[#This Row],[Scale]:[Scale]]="Small",Table3[[#This Row],[Flexibility Regulation]]=1),INDEX(Definitions!$B$21:$B$37,MATCH(Table3[[#Headers],[Flexibility Regulation]],Definitions!$A$21:$A$37,0)),Table3[[#This Row],[Flexibility Regulation]]=0,0)} -> 36000 | AY5: {=_xlfn.IFS(AND(Table3[[#This Row],[Scale]:[Scale]]="Large",Table3[[#This Row],[Business Energy Essentials]]=1),INDEX(Definitions!$C$21:$C$37,MATCH(Table3[[#Headers],[Business Energy Essentials]],Definitions!$A$21:$A$37,0)),AND(Table3[[#This Row],[Scale]:[Scale]]="Small",Table3[[#This Row],[Business Energy Essentials]]=1),INDEX(Definitions!$B$21:$B$37,MATCH(Table3[[#Headers],[Business Energy Essentials]],Definitions!$A$21:$A$37,0)),Table3[[#This Row],[Business Energy Essentials]]=0,0)} -> 0 | AZ5: {=_xlfn.IFS(AND(Table3[[#This Row],[Scale]:[Scale]]="Large",Table3[[#This Row],[Energy User RTM Analysis]]=1),INDEX(Definitions!$C$21:$C$37,MATCH(Table3[[#Headers],[Energy User RTM Analysis]],Definitions!$A$21:$A$37,0)),AND(Table3[[#This Row],[Scale]:[Scale]]="Small",Table3[[#This Row],[Energy User RTM Analysis]]=1),INDEX(Definitions!$B$21:$B$37,MATCH(Table3[[#Headers],[Energy User RTM Analysis]],Definitions!$A$21:$A$37,0)),Table3[[#This Row],[Energy User RTM Analysis]]=0,0)} -> 0 | BA5: {=_xlfn.IFS(AND(Table3[[#This Row],[Scale]:[Scale]]="Large",Table3[[#This Row],[Energy User Forecasts]]=1),INDEX(Definitions!$C$21:$C$37,MATCH(Table3[[#Headers],[Energy User Forecasts]],Definitions!$A$21:$A$37,0)),AND(Table3[[#This Row],[Scale]:[Scale]]="Small",Table3[[#This Row],[Energy User Forecasts]]=1),INDEX(Definitions!$B$21:$B$37,MATCH(Table3[[#Headers],[Energy User Forecasts]],Definitions!$A$21:$A$37,0)),Table3[[#This Row],[Energy User Forecasts]]=0,0)} -> 0 | BB5: {=_xlfn.IFS(AND(Table3[[#This Row],[Scale]:[Scale]]="Large",Table3[[#This Row],[Energy User Regulation]]=1),INDEX(Definitions!$C$21:$C$37,MATCH(Table3[[#Headers],[Energy User Regulation]],Definitions!$A$21:$A$37,0)),AND(Table3[[#This Row],[Scale]:[Scale]]="Small",Table3[[#This Row],[Energy User Regulation]]=1),INDEX(Definitions!$B$21:$B$37,MATCH(Table3[[#Headers],[Energy User Regulation]],Definitions!$A$21:$A$37,0)),Table3[[#This Row],[Energy User Regulation]]=0,0)} -> 0 | BC5: =IF(SUM(Table3[[#This Row],[Column2]:[Column18]])>Table3[[#This Row],[Column19]],Table3[[#This Row],[Column19]],SUM(Table3[[#This Row],[Column2]:[Column18]])) -> 250000 | BD5: =Table3[[#This Row],[Total Spend]]/SUM(Table3[[#This Row],[Column2]:[Column18]]) -> 0.66934404
A6: Corona Energy Retail 1 Ltd | B6: Yes | D6: 45566 | E6: Large | F6: =INDEX(Definitions!$G$13:$G$17,MATCH(Table3[[#This Row],[Propensity to buy/ buyer readiness]],Definitions!$A$13:$A$17,0)) -> 250000 | G6: 5 | H6: 5 | I6: 5 | J6: 5 | K6: 5 | L6: =SUM(Table3[[#This Row],[Strategic priority segment]:[Propensity to buy/ buyer readiness]]) -> 25 | M6: Energy Supply | N6: Energy supplier | O6: Energy traders | U6: 1 | V6: 1 | W6: 1 | X6: 1 | Y6: 1 | Z6: 0 | AA6: 1 | AB6: 0 | AC6: 0 | AD6: 1 | AE6: 1 | AF6: 1 | AG6: 0 | AH6: 0 | AI6: 0 | AJ6: 0 | AK6: 0 | AL6: {=_xlfn.IFS(AND(Table3[[#This Row],[Scale]:[Scale]]="Large",Table3[[#This Row],[Industry Essentials]]=1),INDEX(Definitions!$C$21:$C$37,MATCH(Table3[[#Headers],[Industry Essentials]],Definitions!$A$21:$A$37,0)),AND(Table3[[#This Row],[Scale]:[Scale]]="Small",Table3[[#This Row],[Industry Essentials]]=1),INDEX(Definitions!$B$21:$B$37,MATCH(Table3[[#Headers],[Industry Essentials]],Definitions!$A$21:$A$37,0)),Table3[[#This Row],[Industry Essentials]]=0,0)} -> 10800 | AM6: {=_xlfn.IFS(AND(Table3[[#This Row],[Scale]:[Scale]]="Large",Table3[[#This Row],[Energy Supply Market Intelligence]]=1),INDEX(Definitions!$C$21:$C$37,MATCH(Table3[[#Headers],[Energy Supply Market Intelligence]],Definitions!$A$21:$A$37,0)),AND(Table3[[#This Row],[Scale]:[Scale]]="Small",Table3[[#This Row],[Energy Supply Market Intelligence]]=1),INDEX(Definitions!$B$21:$B$37,MATCH(Table3[[#Headers],[Energy Supply Market Intelligence]],Definitions!$A$21:$A$37,0)),Table3[[#This Row],[Energy Supply Market Intelligence]]=0,0)} -> 43200 | AN6: {=_xlfn.IFS(AND(Table3[[#This Row],[Scale]:[Scale]]="Large",Table3[[#This Row],[Energy Supply RTM Analysis]]=1),INDEX(Definitions!$C$21:$C$37,MATCH(Table3[[#Headers],[Energy Supply RTM Analysis]],Definitions!$A$21:$A$37,0)),AND(Table3[[#This Row],[Scale]:[Scale]]="Small",Table3[[#This Row],[Energy Supply RTM Analysis]]=1),INDEX(Definitions!$B$21:$B$37,MATCH(Table3[[#Headers],[Energy Supply RTM Analysis]],Definitions!$A$21:$A$37,0)),Table3[[#This Row],[Energy Supply RTM Analysis]]=0,0)} -> 73800 | AO6: {=_xlfn.IFS(AND(Table3[[#This Row],[Scale]:[Scale]]="Large",Table3[[#This Row],[Energy Supply Forecasts]]=1),INDEX(Definitions!$C$21:$C$37,MATCH(Table3[[#Headers],[Energy Supply Forecasts]],Definitions!$A$21:$A$37,0)),AND(Table3[[#This Row],[Scale]:[Scale]]="Small",Table3[[#This Row],[Energy Supply Forecasts]]=1),INDEX(Definitions!$B$21:$B$37,MATCH(Table3[[#Headers],[Energy Supply Forecasts]],Definitions!$A$21:$A$37,0)),Table3[[#This Row],[Energy Supply Forecasts]]=0,0)} -> 48600 | AP6: {=_xlfn.IFS(AND(Table3[[#This Row],[Scale]:[Scale]]="Large",Table3[[#This Row],[Energy Supply Regulation]]=1),INDEX(Definitions!$C$21:$C$37,MATCH(Table3[[#Headers],[Energy Supply Regulation]],Definitions!$A$21:$A$37,0)),AND(Table3[[#This Row],[Scale]:[Scale]]="Small",Table3[[#This Row],[Energy Supply Regulation]]=1),INDEX(Definitions!$B$21:$B$37,MATCH(Table3[[#Headers],[Energy Supply Regulation]],Definitions!$A$21:$A$37,0)),Table3[[#This Row],[Energy Supply Regulation]]=0,0)} -> 55800 | AQ6: {=_xlfn.IFS(AND(Table3[[#This Row],[Scale]:[Scale]]="Large",Table3[[#This Row],[Renewables Market Intelligence]]=1),INDEX(Definitions!$C$21:$C$37,MATCH(Table3[[#Headers],[Renewables Market Intelligence]],Definitions!$A$21:$A$37,0)),AND(Table3[[#This Row],[Scale]:[Scale]]="Small",Table3[[#This Row],[Renewables Market Intelligence]]=1),INDEX(Definitions!$B$21:$B$37,MATCH(Table3[[#Headers],[Renewables Market Intelligence]],Definitions!$A$21:$A$37,0)),Table3[[#This Row],[Renewables Market Intelligence]]=0,0)} -> 0 | AR6: {=_xlfn.IFS(AND(Table3[[#This Row],[Scale]:[Scale]]="Large",Table3[[#This Row],[Renewables RTM Analysis]]=1),INDEX(Definitions!$C$21:$C$37,MATCH(Table3[[#Headers],[Renewables RTM Analysis]],Definitions!$A$21:$A$37,0)),AND(Table3[[#This Row],[Scale]:[Scale]]="Small",Table3[[#This Row],[Renewables RTM Analysis]]=1),INDEX(Definitions!$B$21:$B$37,MATCH(Table3[[#Headers],[Renewables RTM Analysis]],Definitions!$A$21:$A$37,0)),Table3[[#This Row],[Renewables RTM Analysis]]=0,0)} -> 20700 | AS6: {=_xlfn.IFS(AND(Table3[[#This Row],[Scale]:[Scale]]="Large",Table3[[#This Row],[Renewables Forecasts]]=1),INDEX(Definitions!$C$21:$C$37,MATCH(Table3[[#Headers],[Renewables Forecasts]],Definitions!$A$21:$A$37,0)),AND(Table3[[#This Row],[Scale]:[Scale]]="Small",Table3[[#This Row],[Renewables Forecasts]]=1),INDEX(Definitions!$B$21:$B$37,MATCH(Table3[[#Headers],[Renewables Forecasts]],Definitions!$A$21:$A$37,0)),Table3[[#This Row],[Renewables Forecasts]]=0,0)} -> 0 | AT6: {=_xlfn.IFS(AND(Table3[[#This Row],[Scale]:[Scale]]="Large",Table3[[#This Row],[Renewables Regulation]]=1),INDEX(Definitions!$C$21:$C$37,MATCH(Table3[[#Headers],[Renewables Regulation]],Definitions!$A$21:$A$37,0)),AND(Table3[[#This Row],[Scale]:[Scale]]="Small",Table3[[#This Row],[Renewables Regulation]]=1),INDEX(Definitions!$B$21:$B$37,MATCH(Table3[[#Headers],[Renewables Regulation]],Definitions!$A$21:$A$37,0)),Table3[[#This Row],[Renewables Regulation]]=0,0)} -> 0 | AU6: {=_xlfn.IFS(AND(Table3[[#This Row],[Scale]:[Scale]]="Large",Table3[[#This Row],[Flexibility Market Intelligence]]=1),INDEX(Definitions!$C$21:$C$37,MATCH(Table3[[#Headers],[Flexibility Market Intelligence]],Definitions!$A$21:$A$37,0)),AND(Table3[[#This Row],[Scale]:[Scale]]="Small",Table3[[#This Row],[Flexibility Market Intelligence]]=1),INDEX(Definitions!$B$21:$B$37,MATCH(Table3[[#Headers],[Flexibility Market Intelligence]],Definitions!$A$21:$A$37,0)),Table3[[#This Row],[Flexibility Market Intelligence]]=0,0)} -> 29700 | AV6: {=_xlfn.IFS(AND(Table3[[#This Row],[Scale]:[Scale]]="Large",Table3[[#This Row],[Flexibility RTM Analysis]]=1),INDEX(Definitions!$C$21:$C$37,MATCH(Table3[[#Headers],[Flexibility RTM Analysis]],Definitions!$A$21:$A$37,0)),AND(Table3[[#This Row],[Scale]:[Scale]]="Small",Table3[[#This Row],[Flexibility RTM Analysis]]=1),INDEX(Definitions!$B$21:$B$37,MATCH(Table3[[#Headers],[Flexibility RTM Analysis]],Definitions!$A$21:$A$37,0)),Table3[[#This Row],[Flexibility RTM Analysis]]=0,0)} -> 10800 | AW6: {=_xlfn.IFS(AND(Table3[[#This Row],[Scale]:[Scale]]="Large",Table3[[#This Row],[Flexibility Forecasts]]=1),INDEX(Definitions!$C$21:$C$37,MATCH(Table3[[#Headers],[Flexibility Forecasts]],Definitions!$A$21:$A$37,0)),AND(Table3[[#This Row],[Scale]:[Scale]]="Small",Table3[[#This Row],[Flexibility Forecasts]]=1),INDEX(Definitions!$B$21:$B$37,MATCH(Table3[[#Headers],[Flexibility Forecasts]],Definitions!$A$21:$A$37,0)),Table3[[#This Row],[Flexibility Forecasts]]=0,0)} -> 44100 | AX6: {=_xlfn.IFS(AND(Table3[[#This Row],[Scale]:[Scale]]="Large",Table3[[#This Row],[Flexibility Regulation]]=1),INDEX(Definitions!$C$21:$C$37,MATCH(Table3[[#Headers],[Flexibility Regulation]],Definitions!$A$21:$A$37,0)),AND(Table3[[#This Row],[Scale]:[Scale]]="Small",Table3[[#This Row],[Flexibility Regulation]]=1),INDEX(Definitions!$B$21:$B$37,MATCH(Table3[[#Headers],[Flexibility Regulation]],Definitions!$A$21:$A$37,0)),Table3[[#This Row],[Flexibility Regulation]]=0,0)} -> 0 | AY6: {=_xlfn.IFS(AND(Table3[[#This Row],[Scale]:[Scale]]="Large",Table3[[#This Row],[Business Energy Essentials]]=1),INDEX(Definitions!$C$21:$C$37,MATCH(Table3[[#Headers],[Business Energy Essentials]],Definitions!$A$21:$A$37,0)),AND(Table3[[#This Row],[Scale]:[Scale]]="Small",Table3[[#This Row],[Business Energy Essentials]]=1),INDEX(Definitions!$B$21:$B$37,MATCH(Table3[[#Headers],[Business Energy Essentials]],Definitions!$A$21:$A$37,0)),Table3[[#This Row],[Business Energy Essentials]]=0,0)} -> 0 | AZ6: {=_xlfn.IFS(AND(Table3[[#This Row],[Scale]:[Scale]]="Large",Table3[[#This Row],[Energy User RTM Analysis]]=1),INDEX(Definitions!$C$21:$C$37,MATCH(Table3[[#Headers],[Energy User RTM Analysis]],Definitions!$A$21:$A$37,0)),AND(Table3[[#This Row],[Scale]:[Scale]]="Small",Table3[[#This Row],[Energy User RTM Analysis]]=1),INDEX(Definitions!$B$21:$B$37,MATCH(Table3[[#Headers],[Energy User RTM Analysis]],Definitions!$A$21:$A$37,0)),Table3[[#This Row],[Energy User RTM Analysis]]=0,0)} -> 0 | BA6: {=_xlfn.IFS(AND(Table3[[#This Row],[Scale]:[Scale]]="Large",Table3[[#This Row],[Energy User Forecasts]]=1),INDEX(Definitions!$C$21:$C$37,MATCH(Table3[[#Headers],[Energy User Forecasts]],Definitions!$A$21:$A$37,0)),AND(Table3[[#This Row],[Scale]:[Scale]]="Small",Table3[[#This Row],[Energy User Forecasts]]=1),INDEX(Definitions!$B$21:$B$37,MATCH(Table3[[#Headers],[Energy User Forecasts]],Definitions!$A$21:$A$37,0)),Table3[[#This Row],[Energy User Forecasts]]=0,0)} -> 0 | BB6: {=_xlfn.IFS(AND(Table3[[#This Row],[Scale]:[Scale]]="Large",Table3[[#This Row],[Energy User Regulation]]=1),INDEX(Definitions!$C$21:$C$37,MATCH(Table3[[#Headers],[Energy User Regulation]],Definitions!$A$21:$A$37,0)),AND(Table3[[#This Row],[Scale]:[Scale]]="Small",Table3[[#This Row],[Energy User Regulation]]=1),INDEX(Definitions!$B$21:$B$37,MATCH(Table3[[#Headers],[Energy User Regulation]],Definitions!$A$21:$A$37,0)),Table3[[#This Row],[Energy User Regulation]]=0,0)} -> 0 | BC6: =IF(SUM(Table3[[#This Row],[Column2]:[Column18]])>Table3[[#This Row],[Column19]],Table3[[#This Row],[Column19]],SUM(Table3[[#This Row],[Column2]:[Column18]])) -> 250000 | BD6: =Table3[[#This Row],[Total Spend]]/SUM(Table3[[#This Row],[Column2]:[Column18]]) -> 0.74074074
A7: Drax Power Limited | B7: Yes | D7: 45566 | E7: Large | F7: =INDEX(Definitions!$G$13:$G$17,MATCH(Table3[[#This Row],[Propensity to buy/ buyer readiness]],Definitions!$A$13:$A$17,0)) -> 250000 | G7: 5 | H7: 5 | I7: 5 | J7: 5 | K7: 5 | L7: =SUM(Table3[[#This Row],[Strategic priority segment]:[Propensity to buy/ buyer readiness]]) -> 25 | M7: Flex Generation & Storage | N7: Flexibility generator/developer | O7: Renewables generator/developer | P7: Energy supplier | Q7: Energy traders | U7: 1 | V7: 1 | W7: 1 | X7: 1 | Y7: 1 | Z7: 1 | AA7: 1 | AB7: 1 | AC7: 1 | AD7: 1 | AE7: 1 | AF7: 1 | AG7: 1 | AH7: 0 | AI7: 0 | AJ7: 0 | AK7: 0 | AL7: {=_xlfn.IFS(AND(Table3[[#This Row],[Scale]:[Scale]]="Large",Table3[[#This Row],[Industry Essentials]]=1),INDEX(Definitions!$C$21:$C$37,MATCH(Table3[[#Headers],[Industry Essentials]],Definitions!$A$21:$A$37,0)),AND(Table3[[#This Row],[Scale]:[Scale]]="Small",Table3[[#This Row],[Industry Essentials]]=1),INDEX(Definitions!$B$21:$B$37,MATCH(Table3[[#Headers],[Industry Essentials]],Definitions!$A$21:$A$37,0)),Table3[[#This Row],[Industry Essentials]]=0,0)} -> 10800 | AM7: {=_xlfn.IFS(AND(Table3[[#This Row],[Scale]:[Scale]]="Large",Table3[[#This Row],[Energy Supply Market Intelligence]]=1),INDEX(Definitions!$C$21:$C$37,MATCH(Table3[[#Headers],[Energy Supply Market Intelligence]],Definitions!$A$21:$A$37,0)),AND(Table3[[#This Row],[Scale]:[Scale]]="Small",Table3[[#This Row],[Energy Supply Market Intelligence]]=1),INDEX(Definitions!$B$21:$B$37,MATCH(Table3[[#Headers],[Energy Supply Market Intelligence]],Definitions!$A$21:$A$37,0)),Table3[[#This Row],[Energy Supply Market Intelligence]]=0,0)} -> 43200 | AN7: {=_xlfn.IFS(AND(Table3[[#This Row],[Scale]:[Scale]]="Large",Table3[[#This Row],[Energy Supply RTM Analysis]]=1),INDEX(Definitions!$C$21:$C$37,MATCH(Table3[[#Headers],[Energy Supply RTM Analysis]],Definitions!$A$21:$A$37,0)),AND(Table3[[#This Row],[Scale]:[Scale]]="Small",Table3[[#This Row],[Energy Supply RTM Analysis]]=1),INDEX(Definitions!$B$21:$B$37,MATCH(Table3[[#Headers],[Energy Supply RTM Analysis]],Definitions!$A$21:$A$37,0)),Table3[[#This Row],[Energy Supply RTM Analysis]]=0,0)} -> 73800 | AO7: {=_xlfn.IFS(AND(Table3[[#This Row],[Scale]:[Scale]]="Large",Table3[[#This Row],[Energy Supply Forecasts]]=1),INDEX(Definitions!$C$21:$C$37,MATCH(Table3[[#Headers],[Energy Supply Forecasts]],Definitions!$A$21:$A$37,0)),AND(Table3[[#This Row],[Scale]:[Scale]]="Small",Table3[[#This Row],[Energy Supply Forecasts]]=1),INDEX(Definitions!$B$21:$B$37,MATCH(Table3[[#Headers],[Energy Supply Forecasts]],Definitions!$A$21:$A$37,0)),Table3[[#This Row],[Energy Supply Forecasts]]=0,0)} -> 48600 | AP7: {=_xlfn.IFS(AND(Table3[[#This Row],[Scale]:[Scale]]="Large",Table3[[#This Row],[Energy Supply Regulation]]=1),INDEX(Definitions!$C$21:$C$37,MATCH(Table3[[#Headers],[Energy Supply Regulation]],Definitions!$A$21:$A$37,0)),AND(Table3[[#This Row],[Scale]:[Scale]]="Small",Table3[[#This Row],[Energy Supply Regulation]]=1),INDEX(Definitions!$B$21:$B$37,MATCH(Table3[[#Headers],[Energy Supply Regulation]],Definitions!$A$21:$A$37,0)),Table3[[#This Row],[Energy Supply Regulation]]=0,0)} -> 55800 | AQ7: {=_xlfn.IFS(AND(Table3[[#This Row],[Scale]:[Scale]]="Large",Table3[[#This Row],[Renewables Market Intelligence]]=1),INDEX(Definitions!$C$21:$C$37,MATCH(Table3[[#Headers],[Renewables Market Intelligence]],Definitions!$A$21:$A$37,0)),AND(Table3[[#This Row],[Scale]:[Scale]]="Small",Table3[[#This Row],[Renewables Market Intelligence]]=1),INDEX(Definitions!$B$21:$B$37,MATCH(Table3[[#Headers],[Renewables Market Intelligence]],Definitions!$A$21:$A$37,0)),Table3[[#This Row],[Renewables Market Intelligence]]=0,0)} -> 23400 | AR7: {=_xlfn.IFS(AND(Table3[[#This Row],[Scale]:[Scale]]="Large",Table3[[#This Row],[Renewables RTM Analysis]]=1),INDEX(Definitions!$C$21:$C$37,MATCH(Table3[[#Headers],[Renewables RTM Analysis]],Definitions!$A$21:$A$37,0)),AND(Table3[[#This Row],[Scale]:[Scale]]="Small",Table3[[#This Row],[Renewables RTM Analysis]]=1),INDEX(Definitions!$B$21:$B$37,MATCH(Table3[[#Headers],[Renewables RTM Analysis]],Definitions!$A$21:$A$37,0)),Table3[[#This Row],[Renewables RTM Analysis]]=0,0)} -> 20700 | AS7: {=_xlfn.IFS(AND(Table3[[#This Row],[Scale]:[Scale]]="Large",Table3[[#This Row],[Renewables Forecasts]]=1),INDEX(Definitions!$C$21:$C$37,MATCH(Table3[[#Headers],[Renewables Forecasts]],Definitions!$A$21:$A$37,0)),AND(Table3[[#This Row],[Scale]:[Scale]]="Small",Table3[[#This Row],[Renewables Forecasts]]=1),INDEX(Definitions!$B$21:$B$37,MATCH(Table3[[#Headers],[Renewables Forecasts]],Definitions!$A$21:$A$37,0)),Table3[[#This Row],[Renewables Forecasts]]=0,0)} -> 59400 | AT7: {=_xlfn.IFS(AND(Table3[[#This Row],[Scale]:[Scale]]="Large",Table3[[#This Row],[Renewables Regulation]]=1),INDEX(Definitions!$C$21:$C$37,MATCH(Table3[[#Headers],[Renewables Regulation]],Definitions!$A$21:$A$37,0)),AND(Table3[[#This Row],[Scale]:[Scale]]="Small",Table3[[#This Row],[Renewables Regulation]]=1),INDEX(Definitions!$B$21:$B$37,MATCH(Table3[[#Headers],[Renewables Regulation]],Definitions!$A$21:$A$37,0)),Table3[[#This Row],[Renewables Regulation]]=0,0)} -> 26100 | AU7: {=_xlfn.IFS(AND(Table3[[#This Row],[Scale]:[Scale]]="Large",Table3[[#This Row],[Flexibility Market Intelligence]]=1),INDEX(Definitions!$C$21:$C$37,MATCH(Table3[[#Headers],[Flexibility Market Intelligence]],Definitions!$A$21:$A$37,0)),AND(Table3[[#This Row],[Scale]:[Scale]]="Small",Table3[[#This Row],[Flexibility Market Intelligence]]=1),INDEX(Definitions!$B$21:$B$37,MATCH(Table3[[#Headers],[Flexibility Market Intelligence]],Definitions!$A$21:$A$37,0)),Table3[[#This Row],[Flexibility Market Intelligence]]=0,0)} -> 29700 | AV7: {=_xlfn.IFS(AND(Table3[[#This Row],[Scale]:[Scale]]="Large",Table3[[#This Row],[Flexibility RTM Analysis]]=1),INDEX(Definitions!$C$21:$C$37,MATCH(Table3[[#Headers],[Flexibility RTM Analysis]],Definitions!$A$21:$A$37,0)),AND(Table3[[#This Row],[Scale]:[Scale]]="Small",Table3[[#This Row],[Flexibility RTM Analysis]]=1),INDEX(Definitions!$B$21:$B$37,MATCH(Table3[[#Headers],[Flexibility RTM Analysis]],Definitions!$A$21:$A$37,0)),Table3[[#This Row],[Flexibility RTM Analysis]]=0,0)} -> 10800 | AW7: {=_xlfn.IFS(AND(Table3[[#This Row],[Scale]:[Scale]]="Large",Table3[[#This Row],[Flexibility Forecasts]]=1),INDEX(Definitions!$C$21:$C$37,MATCH(Table3[[#Headers],[Flexibility Forecasts]],Definitions!$A$21:$A$37,0)),AND(Table3[[#This Row],[Scale]:[Scale]]="Small",Table3[[#This Row],[Flexibility Forecasts]]=1),INDEX(Definitions!$B$21:$B$37,MATCH(Table3[[#Headers],[Flexibility Forecasts]],Definitions!$A$21:$A$37,0)),Table3[[#This Row],[Flexibility Forecasts]]=0,0)} -> 44100 | AX7: {=_xlfn.IFS(AND(Table3[[#This Row],[Scale]:[Scale]]="Large",Table3[[#This Row],[Flexibility Regulation]]=1),INDEX(Definitions!$C$21:$C$37,MATCH(Table3[[#Headers],[Flexibility Regulation]],Definitions!$A$21:$A$37,0)),AND(Table3[[#This Row],[Scale]:[Scale]]="Small",Table3[[#This Row],[Flexibility Regulation]]=1),INDEX(Definitions!$B$21:$B$37,MATCH(Table3[[#Headers],[Flexibility Regulation]],Definitions!$A$21:$A$37,0)),Table3[[#This Row],[Flexibility Regulation]]=0,0)} -> 36000 | AY7: {=_xlfn.IFS(AND(Table3[[#This Row],[Scale]:[Scale]]="Large",Table3[[#This Row],[Business Energy Essentials]]=1),INDEX(Definitions!$C$21:$C$37,MATCH(Table3[[#Headers],[Business Energy Essentials]],Definitions!$A$21:$A$37,0)),AND(Table3[[#This Row],[Scale]:[Scale]]="Small",Table3[[#This Row],[Business Energy Essentials]]=1),INDEX(Definitions!$B$21:$B$37,MATCH(Table3[[#Headers],[Business Energy Essentials]],Definitions!$A$21:$A$37,0)),Table3[[#This Row],[Business Energy Essentials]]=0,0)} -> 0 | AZ7: {=_xlfn.IFS(AND(Table3[[#This Row],[Scale]:[Scale]]="Large",Table3[[#This Row],[Energy User RTM Analysis]]=1),INDEX(Definitions!$C$21:$C$37,MATCH(Table3[[#Headers],[Energy User RTM Analysis]],Definitions!$A$21:$A$37,0)),AND(Table3[[#This Row],[Scale]:[Scale]]="Small",Table3[[#This Row],[Energy User RTM Analysis]]=1),INDEX(Definitions!$B$21:$B$37,MATCH(Table3[[#Headers],[Energy User RTM Analysis]],Definitions!$A$21:$A$37,0)),Table3[[#This Row],[Energy User RTM Analysis]]=0,0)} -> 0 | BA7: {=_xlfn.IFS(AND(Table3[[#This Row],[Scale]:[Scale]]="Large",Table3[[#This Row],[Energy User Forecasts]]=1),INDEX(Definitions!$C$21:$C$37,MATCH(Table3[[#Headers],[Energy User Forecasts]],Definitions!$A$21:$A$37,0)),AND(Table3[[#This Row],[Scale]:[Scale]]="Small",Table3[[#This Row],[Energy User Forecasts]]=1),INDEX(Definitions!$B$21:$B$37,MATCH(Table3[[#Headers],[Energy User Forecasts]],Definitions!$A$21:$A$37,0)),Table3[[#This Row],[Energy User Forecasts]]=0,0)} -> 0 | BB7: {=_xlfn.IFS(AND(Table3[[#This Row],[Scale]:[Scale]]="Large",Table3[[#This Row],[Energy User Regulation]]=1),INDEX(Definitions!$C$21:$C$37,MATCH(Table3[[#Headers],[Energy User Regulation]],Definitions!$A$21:$A$37,0)),AND(Table3[[#This Row],[Scale]:[Scale]]="Small",Table3[[#This Row],[Energy User Regulation]]=1),INDEX(Definitions!$B$21:$B$37,MATCH(Table3[[#Headers],[Energy User Regulation]],Definitions!$A$21:$A$37,0)),Table3[[#This Row],[Energy User Regulation]]=0,0)} -> 0 | BC7: =IF(SUM(Table3[[#This Row],[Column2]:[Column18]])>Table3[[#This Row],[Column19]],Table3[[#This Row],[Column19]],SUM(Table3[[#This Row],[Column2]:[Column18]])) -> 250000 | BD7: =Table3[[#This Row],[Total Spend]]/SUM(Table3[[#This Row],[Column2]:[Column18]]) -> 0.51824212
A8: E.ON Connecting Energies Ltd. | B8: Yes | D8: 45566 | E8: Large | F8: =INDEX(Definitions!$G$13:$G$17,MATCH(Table3[[#This Row],[Propensity to buy/ buyer readiness]],Definitions!$A$13:$A$17,0)) -> 250000 | G8: 5 | H8: 5 | I8: 5 | J8: 5 | K8: 5 | L8: =SUM(Table3[[#This Row],[Strategic priority segment]:[Propensity to buy/ buyer readiness]]) -> 25 | M8: Energy Supply | N8: Energy supplier | O8: Flexibility generator/developer | P8: Renewables generator/developer | Q8: Energy traders | U8: 1 | V8: 1 | W8: 1 | X8: 1 | Y8: 1 | Z8: 1 | AA8: 1 | AB8: 1 | AC8: 1 | AD8: 1 | AE8: 1 | AF8: 1 | AG8: 1 | AH8: 0 | AI8: 0 | AJ8: 0 | AK8: 0 | AL8: {=_xlfn.IFS(AND(Table3[[#This Row],[Scale]:[Scale]]="Large",Table3[[#This Row],[Industry Essentials]]=1),INDEX(Definitions!$C$21:$C$37,MATCH(Table3[[#Headers],[Industry Essentials]],Definitions!$A$21:$A$37,0)),AND(Table3[[#This Row],[Scale]:[Scale]]="Small",Table3[[#This Row],[Industry Essentials]]=1),INDEX(Definitions!$B$21:$B$37,MATCH(Table3[[#Headers],[Industry Essentials]],Definitions!$A$21:$A$37,0)),Table3[[#This Row],[Industry Essentials]]=0,0)} -> 10800 | AM8: {=_xlfn.IFS(AND(Table3[[#This Row],[Scale]:[Scale]]="Large",Table3[[#This Row],[Energy Supply Market Intelligence]]=1),INDEX(Definitions!$C$21:$C$37,MATCH(Table3[[#Headers],[Energy Supply Market Intelligence]],Definitions!$A$21:$A$37,0)),AND(Table3[[#This Row],[Scale]:[Scale]]="Small",Table3[[#This Row],[Energy Supply Market Intelligence]]=1),INDEX(Definitions!$B$21:$B$37,MATCH(Table3[[#Headers],[Energy Supply Market Intelligence]],Definitions!$A$21:$A$37,0)),Table3[[#This Row],[Energy Supply Market Intelligence]]=0,0)} -> 43200 | AN8: {=_xlfn.IFS(AND(Table3[[#This Row],[Scale]:[Scale]]="Large",Table3[[#This Row],[Energy Supply RTM Analysis]]=1),INDEX(Definitions!$C$21:$C$37,MATCH(Table3[[#Headers],[Energy Supply RTM Analysis]],Definitions!$A$21:$A$37,0)),AND(Table3[[#This Row],[Scale]:[Scale]]="Small",Table3[[#This Row],[Energy Supply RTM Analysis]]=1),INDEX(Definitions!$B$21:$B$37,MATCH(Table3[[#Headers],[Energy Supply RTM Analysis]],Definitions!$A$21:$A$37,0)),Table3[[#This Row],[Energy Supply RTM Analysis]]=0,0)} -> 73800 | AO8: {=_xlfn.IFS(AND(Table3[[#This Row],[Scale]:[Scale]]="Large",Table3[[#This Row],[Energy Supply Forecasts]]=1),INDEX(Definitions!$C$21:$C$37,MATCH(Table3[[#Headers],[Energy Supply Forecasts]],Definitions!$A$21:$A$37,0)),AND(Table3[[#This Row],[Scale]:[Scale]]="Small",Table3[[#This Row],[Energy Supply Forecasts]]=1),INDEX(Definitions!$B$21:$B$37,MATCH(Table3[[#Headers],[Energy Supply Forecasts]],Definitions!$A$21:$A$37,0)),Table3[[#This Row],[Energy Supply Forecasts]]=0,0)} -> 48600 | AP8: {=_xlfn.IFS(AND(Table3[[#This Row],[Scale]:[Scale]]="Large",Table3[[#This Row],[Energy Supply Regulation]]=1),INDEX(Definitions!$C$21:$C$37,MATCH(Table3[[#Headers],[Energy Supply Regulation]],Definitions!$A$21:$A$37,0)),AND(Table3[[#This Row],[Scale]:[Scale]]="Small",Table3[[#This Row],[Energy Supply Regulation]]=1),INDEX(Definitions!$B$21:$B$37,MATCH(Table3[[#Headers],[Energy Supply Regulation]],Definitions!$A$21:$A$37,0)),Table3[[#This Row],[Energy Supply Regulation]]=0,0)} -> 55800 | AQ8: {=_xlfn.IFS(AND(Table3[[#This Row],[Scale]:[Scale]]="Large",Table3[[#This Row],[Renewables Market Intelligence]]=1),INDEX(Definitions!$C$21:$C$37,MATCH(Table3[[#Headers],[Renewables Market Intelligence]],Definitions!$A$21:$A$37,0)),AND(Table3[[#This Row],[Scale]:[Scale]]="Small",Table3[[#This Row],[Renewables Market Intelligence]]=1),INDEX(Definitions!$B$21:$B$37,MATCH(Table3[[#Headers],[Renewables Market Intelligence]],Definitions!$A$21:$A$37,0)),Table3[[#This Row],[Renewables Market Intelligence]]=0,0)} -> 23400 | AR8: {=_xlfn.IFS(AND(Table3[[#This Row],[Scale]:[Scale]]="Large",Table3[[#This Row],[Renewables RTM Analysis]]=1),INDEX(Definitions!$C$21:$C$37,MATCH(Table3[[#Headers],[Renewables RTM Analysis]],Definitions!$A$21:$A$37,0)),AND(Table3[[#This Row],[Scale]:[Scale]]="Small",Table3[[#This Row],[Renewables RTM Analysis]]=1),INDEX(Definitions!$B$21:$B$37,MATCH(Table3[[#Headers],[Renewables RTM Analysis]],Definitions!$A$21:$A$37,0)),Table3[[#This Row],[Renewables RTM Analysis]]=0,0)} -> 20700 | AS8: {=_xlfn.IFS(AND(Table3[[#This Row],[Scale]:[Scale]]="Large",Table3[[#This Row],[Renewables Forecasts]]=1),INDEX(Definitions!$C$21:$C$37,MATCH(Table3[[#Headers],[Renewables Forecasts]],Definitions!$A$21:$A$37,0)),AND(Table3[[#This Row],[Scale]:[Scale]]="Small",Table3[[#This Row],[Renewables Forecasts]]=1),INDEX(Definitions!$B$21:$B$37,MATCH(Table3[[#Headers],[Renewables Forecasts]],Definitions!$A$21:$A$37,0)),Table3[[#This Row],[Renewables Forecasts]]=0,0)} -> 59400 | AT8: {=_xlfn.IFS(AND(Table3[[#This Row],[Scale]:[Scale]]="Large",Table3[[#This Row],[Renewables Regulation]]=1),INDEX(Definitions!$C$21:$C$37,MATCH(Table3[[#Headers],[Renewables Regulation]],Definitions!$A$21:$A$37,0)),AND(Table3[[#This Row],[Scale]:[Scale]]="Small",Table3[[#This Row],[Renewables Regulation]]=1),INDEX(Definitions!$B$21:$B$37,MATCH(Table3[[#Headers],[Renewables Regulation]],Definitions!$A$21:$A$37,0)),Table3[[#This Row],[Renewables Regulation]]=0,0)} -> 26100 | AU8: {=_xlfn.IFS(AND(Table3[[#This Row],[Scale]:[Scale]]="Large",Table3[[#This Row],[Flexibility Market Intelligence]]=1),INDEX(Definitions!$C$21:$C$37,MATCH(Table3[[#Headers],[Flexibility Market Intelligence]],Definitions!$A$21:$A$37,0)),AND(Table3[[#This Row],[Scale]:[Scale]]="Small",Table3[[#This Row],[Flexibility Market Intelligence]]=1),INDEX(Definitions!$B$21:$B$37,MATCH(Table3[[#Headers],[Flexibility Market Intelligence]],Definitions!$A$21:$A$37,0)),Table3[[#This Row],[Flexibility Market Intelligence]]=0,0)} -> 29700 | AV8: {=_xlfn.IFS(AND(Table3[[#This Row],[Scale]:[Scale]]="Large",Table3[[#This Row],[Flexibility RTM Analysis]]=1),INDEX(Definitions!$C$21:$C$37,MATCH(Table3[[#Headers],[Flexibility RTM Analysis]],Definitions!$A$21:$A$37,0)),AND(Table3[[#This Row],[Scale]:[Scale]]="Small",Table3[[#This Row],[Flexibility RTM Analysis]]=1),INDEX(Definitions!$B$21:$B$37,MATCH(Table3[[#Headers],[Flexibility RTM Analysis]],Definitions!$A$21:$A$37,0)),Table3[[#This Row],[Flexibility RTM Analysis]]=0,0)} -> 10800 | AW8: {=_xlfn.IFS(AND(Table3[[#This Row],[Scale]:[Scale]]="Large",Table3[[#This Row],[Flexibility Forecasts]]=1),INDEX(Definitions!$C$21:$C$37,MATCH(Table3[[#Headers],[Flexibility Forecasts]],Definitions!$A$21:$A$37,0)),AND(Table3[[#This Row],[Scale]:[Scale]]="Small",Table3[[#This Row],[Flexibility Forecasts]]=1),INDEX(Definitions!$B$21:$B$37,MATCH(Table3[[#Headers],[Flexibility Forecasts]],Definitions!$A$21:$A$37,0)),Table3[[#This Row],[Flexibility Forecasts]]=0,0)} -> 44100 | AX8: {=_xlfn.IFS(AND(Table3[[#This Row],[Scale]:[Scale]]="Large",Table3[[#This Row],[Flexibility Regulation]]=1),INDEX(Definitions!$C$21:$C$37,MATCH(Table3[[#Headers],[Flexibility Regulation]],Definitions!$A$21:$A$37,0)),AND(Table3[[#This Row],[Scale]:[Scale]]="Small",Table3[[#This Row],[Flexibility Regulation]]=1),INDEX(Definitions!$B$21:$B$37,MATCH(Table3[[#Headers],[Flexibility Regulation]],Definitions!$A$21:$A$37,0)),Table3[[#This Row],[Flexibility Regulation]]=0,0)} -> 36000 | AY8: {=_xlfn.IFS(AND(Table3[[#This Row],[Scale]:[Scale]]="Large",Table3[[#This Row],[Business Energy Essentials]]=1),INDEX(Definitions!$C$21:$C$37,MATCH(Table3[[#Headers],[Business Energy Essentials]],Definitions!$A$21:$A$37,0)),AND(Table3[[#This Row],[Scale]:[Scale]]="Small",Table3[[#This Row],[Business Energy Essentials]]=1),INDEX(Definitions!$B$21:$B$37,MATCH(Table3[[#Headers],[Business Energy Essentials]],Definitions!$A$21:$A$37,0)),Table3[[#This Row],[Business Energy Essentials]]=0,0)} -> 0 | AZ8: {=_xlfn.IFS(AND(Table3[[#This Row],[Scale]:[Scale]]="Large",Table3[[#This Row],[Energy User RTM Analysis]]=1),INDEX(Definitions!$C$21:$C$37,MATCH(Table3[[#Headers],[Energy User RTM Analysis]],Definitions!$A$21:$A$37,0)),AND(Table3[[#This Row],[Scale]:[Scale]]="Small",Table3[[#This Row],[Energy User RTM Analysis]]=1),INDEX(Definitions!$B$21:$B$37,MATCH(Table3[[#Headers],[Energy User RTM Analysis]],Definitions!$A$21:$A$37,0)),Table3[[#This Row],[Energy User RTM Analysis]]=0,0)} -> 0 | BA8: {=_xlfn.IFS(AND(Table3[[#This Row],[Scale]:[Scale]]="Large",Table3[[#This Row],[Energy User Forecasts]]=1),INDEX(Definitions!$C$21:$C$37,MATCH(Table3[[#Headers],[Energy User Forecasts]],Definitions!$A$21:$A$37,0)),AND(Table3[[#This Row],[Scale]:[Scale]]="Small",Table3[[#This Row],[Energy User Forecasts]]=1),INDEX(Definitions!$B$21:$B$37,MATCH(Table3[[#Headers],[Energy User Forecasts]],Definitions!$A$21:$A$37,0)),Table3[[#This Row],[Energy User Forecasts]]=0,0)} -> 0 | BB8: {=_xlfn.IFS(AND(Table3[[#This Row],[Scale]:[Scale]]="Large",Table3[[#This Row],[Energy User Regulation]]=1),INDEX(Definitions!$C$21:$C$37,MATCH(Table3[[#Headers],[Energy User Regulation]],Definitions!$A$21:$A$37,0)),AND(Table3[[#This Row],[Scale]:[Scale]]="Small",Table3[[#This Row],[Energy User Regulation]]=1),INDEX(Definitions!$B$21:$B$37,MATCH(Table3[[#Headers],[Energy User Regulation]],Definitions!$A$21:$A$37,0)),Table3[[#This Row],[Energy User Regulation]]=0,0)} -> 0 | BC8: =IF(SUM(Table3[[#This Row],[Column2]:[Column18]])>Table3[[#This Row],[Column19]],Table3[[#This Row],[Column19]],SUM(Table3[[#This Row],[Column2]:[Column18]])) -> 250000 | BD8: =Table3[[#This Row],[Total Spend]]/SUM(Table3[[#This Row],[Column2]:[Column18]]) -> 0.51824212
A9: E.ON UK PLC | B9: Yes | D9: 45566 | E9: Large | F9: =INDEX(Definitions!$G$13:$G$17,MATCH(Table3[[#This Row],[Propensity to buy/ buyer readiness]],Definitions!$A$13:$A$17,0)) -> 250000 | G9: 5 | H9: 5 | I9: 5 | J9: 5 | K9: 5 | L9: =SUM(Table3[[#This Row],[Strategic priority segment]:[Propensity to buy/ buyer readiness]]) -> 25 | M9: Energy Supply | N9: Energy supplier | O9: Flexibility generator/developer | P9: Renewables generator/developer | Q9: Energy traders | U9: 1 | V9: 1 | W9: 1 | X9: 1 | Y9: 1 | Z9: 1 | AA9: 1 | AB9: 1 | AC9: 1 | AD9: 1 | AE9: 1 | AF9: 1 | AG9: 1 | AH9: 0 | AI9: 0 | AJ9: 0 | AK9: 0 | AL9: {=_xlfn.IFS(AND(Table3[[#This Row],[Scale]:[Scale]]="Large",Table3[[#This Row],[Industry Essentials]]=1),INDEX(Definitions!$C$21:$C$37,MATCH(Table3[[#Headers],[Industry Essentials]],Definitions!$A$21:$A$37,0)),AND(Table3[[#This Row],[Scale]:[Scale]]="Small",Table3[[#This Row],[Industry Essentials]]=1),INDEX(Definitions!$B$21:$B$37,MATCH(Table3[[#Headers],[Industry Essentials]],Definitions!$A$21:$A$37,0)),Table3[[#This Row],[Industry Essentials]]=0,0)} -> 10800 | AM9: {=_xlfn.IFS(AND(Table3[[#This Row],[Scale]:[Scale]]="Large",Table3[[#This Row],[Energy Supply Market Intelligence]]=1),INDEX(Definitions!$C$21:$C$37,MATCH(Table3[[#Headers],[Energy Supply Market Intelligence]],Definitions!$A$21:$A$37,0)),AND(Table3[[#This Row],[Scale]:[Scale]]="Small",Table3[[#This Row],[Energy Supply Market Intelligence]]=1),INDEX(Definitions!$B$21:$B$37,MATCH(Table3[[#Headers],[Energy Supply Market Intelligence]],Definitions!$A$21:$A$37,0)),Table3[[#This Row],[Energy Supply Market Intelligence]]=0,0)} -> 43200 | AN9: {=_xlfn.IFS(AND(Table3[[#This Row],[Scale]:[Scale]]="Large",Table3[[#This Row],[Energy Supply RTM Analysis]]=1),INDEX(Definitions!$C$21:$C$37,MATCH(Table3[[#Headers],[Energy Supply RTM Analysis]],Definitions!$A$21:$A$37,0)),AND(Table3[[#This Row],[Scale]:[Scale]]="Small",Table3[[#This Row],[Energy Supply RTM Analysis]]=1),INDEX(Definitions!$B$21:$B$37,MATCH(Table3[[#Headers],[Energy Supply RTM Analysis]],Definitions!$A$21:$A$37,0)),Table3[[#This Row],[Energy Supply RTM Analysis]]=0,0)} -> 73800 | AO9: {=_xlfn.IFS(AND(Table3[[#This Row],[Scale]:[Scale]]="Large",Table3[[#This Row],[Energy Supply Forecasts]]=1),INDEX(Definitions!$C$21:$C$37,MATCH(Table3[[#Headers],[Energy Supply Forecasts]],Definitions!$A$21:$A$37,0)),AND(Table3[[#This Row],[Scale]:[Scale]]="Small",Table3[[#This Row],[Energy Supply Forecasts]]=1),INDEX(Definitions!$B$21:$B$37,MATCH(Table3[[#Headers],[Energy Supply Forecasts]],Definitions!$A$21:$A$37,0)),Table3[[#This Row],[Energy Supply Forecasts]]=0,0)} -> 48600 | AP9: {=_xlfn.IFS(AND(Table3[[#This Row],[Scale]:[Scale]]="Large",Table3[[#This Row],[Energy Supply Regulation]]=1),INDEX(Definitions!$C$21:$C$37,MATCH(Table3[[#Headers],[Energy Supply Regulation]],Definitions!$A$21:$A$37,0)),AND(Table3[[#This Row],[Scale]:[Scale]]="Small",Table3[[#This Row],[Energy Supply Regulation]]=1),INDEX(Definitions!$B$21:$B$37,MATCH(Table3[[#Headers],[Energy Supply Regulation]],Definitions!$A$21:$A$37,0)),Table3[[#This Row],[Energy Supply Regulation]]=0,0)} -> 55800 | AQ9: {=_xlfn.IFS(AND(Table3[[#This Row],[Scale]:[Scale]]="Large",Table3[[#This Row],[Renewables Market Intelligence]]=1),INDEX(Definitions!$C$21:$C$37,MATCH(Table3[[#Headers],[Renewables Market Intelligence]],Definitions!$A$21:$A$37,0)),AND(Table3[[#This Row],[Scale]:[Scale]]="Small",Table3[[#This Row],[Renewables Market Intelligence]]=1),INDEX(Definitions!$B$21:$B$37,MATCH(Table3[[#Headers],[Renewables Market Intelligence]],Definitions!$A$21:$A$37,0)),Table3[[#This Row],[Renewables Market Intelligence]]=0,0)} -> 23400 | AR9: {=_xlfn.IFS(AND(Table3[[#This Row],[Scale]:[Scale]]="Large",Table3[[#This Row],[Renewables RTM Analysis]]=1),INDEX(Definitions!$C$21:$C$37,MATCH(Table3[[#Headers],[Renewables RTM Analysis]],Definitions!$A$21:$A$37,0)),AND(Table3[[#This Row],[Scale]:[Scale]]="Small",Table3[[#This Row],[Renewables RTM Analysis]]=1),INDEX(Definitions!$B$21:$B$37,MATCH(Table3[[#Headers],[Renewables RTM Analysis]],Definitions!$A$21:$A$37,0)),Table3[[#This Row],[Renewables RTM Analysis]]=0,0)} -> 20700 | AS9: {=_xlfn.IFS(AND(Table3[[#This Row],[Scale]:[Scale]]="Large",Table3[[#This Row],[Renewables Forecasts]]=1),INDEX(Definitions!$C$21:$C$37,MATCH(Table3[[#Headers],[Renewables Forecasts]],Definitions!$A$21:$A$37,0)),AND(Table3[[#This Row],[Scale]:[Scale]]="Small",Table3[[#This Row],[Renewables Forecasts]]=1),INDEX(Definitions!$B$21:$B$37,MATCH(Table3[[#Headers],[Renewables Forecasts]],Definitions!$A$21:$A$37,0)),Table3[[#This Row],[Renewables Forecasts]]=0,0)} -> 59400 | AT9: {=_xlfn.IFS(AND(Table3[[#This Row],[Scale]:[Scale]]="Large",Table3[[#This Row],[Renewables Regulation]]=1),INDEX(Definitions!$C$21:$C$37,MATCH(Table3[[#Headers],[Renewables Regulation]],Definitions!$A$21:$A$37,0)),AND(Table3[[#This Row],[Scale]:[Scale]]="Small",Table3[[#This Row],[Renewables Regulation]]=1),INDEX(Definitions!$B$21:$B$37,MATCH(Table3[[#Headers],[Renewables Regulation]],Definitions!$A$21:$A$37,0)),Table3[[#This Row],[Renewables Regulation]]=0,0)} -> 26100 | AU9: {=_xlfn.IFS(AND(Table3[[#This Row],[Scale]:[Scale]]="Large",Table3[[#This Row],[Flexibility Market Intelligence]]=1),INDEX(Definitions!$C$21:$C$37,MATCH(Table3[[#Headers],[Flexibility Market Intelligence]],Definitions!$A$21:$A$37,0)),AND(Table3[[#This Row],[Scale]:[Scale]]="Small",Table3[[#This Row],[Flexibility Market Intelligence]]=1),INDEX(Definitions!$B$21:$B$37,MATCH(Table3[[#Headers],[Flexibility Market Intelligence]],Definitions!$A$21:$A$37,0)),Table3[[#This Row],[Flexibility Market Intelligence]]=0,0)} -> 29700 | AV9: {=_xlfn.IFS(AND(Table3[[#This Row],[Scale]:[Scale]]="Large",Table3[[#This Row],[Flexibility RTM Analysis]]=1),INDEX(Definitions!$C$21:$C$37,MATCH(Table3[[#Headers],[Flexibility RTM Analysis]],Definitions!$A$21:$A$37,0)),AND(Table3[[#This Row],[Scale]:[Scale]]="Small",Table3[[#This Row],[Flexibility RTM Analysis]]=1),INDEX(Definitions!$B$21:$B$37,MATCH(Table3[[#Headers],[Flexibility RTM Analysis]],Definitions!$A$21:$A$37,0)),Table3[[#This Row],[Flexibility RTM Analysis]]=0,0)} -> 10800 | AW9: {=_xlfn.IFS(AND(Table3[[#This Row],[Scale]:[Scale]]="Large",Table3[[#This Row],[Flexibility Forecasts]]=1),INDEX(Definitions!$C$21:$C$37,MATCH(Table3[[#Headers],[Flexibility Forecasts]],Definitions!$A$21:$A$37,0)),AND(Table3[[#This Row],[Scale]:[Scale]]="Small",Table3[[#This Row],[Flexibility Forecasts]]=1),INDEX(Definitions!$B$21:$B$37,MATCH(Table3[[#Headers],[Flexibility Forecasts]],Definitions!$A$21:$A$37,0)),Table3[[#This Row],[Flexibility Forecasts]]=0,0)} -> 44100 | AX9: {=_xlfn.IFS(AND(Table3[[#This Row],[Scale]:[Scale]]="Large",Table3[[#This Row],[Flexibility Regulation]]=1),INDEX(Definitions!$C$21:$C$37,MATCH(Table3[[#Headers],[Flexibility Regulation]],Definitions!$A$21:$A$37,0)),AND(Table3[[#This Row],[Scale]:[Scale]]="Small",Table3[[#This Row],[Flexibility Regulation]]=1),INDEX(Definitions!$B$21:$B$37,MATCH(Table3[[#Headers],[Flexibility Regulation]],Definitions!$A$21:$A$37,0)),Table3[[#This Row],[Flexibility Regulation]]=0,0)} -> 36000 | AY9: {=_xlfn.IFS(AND(Table3[[#This Row],[Scale]:[Scale]]="Large",Table3[[#This Row],[Business Energy Essentials]]=1),INDEX(Definitions!$C$21:$C$37,MATCH(Table3[[#Headers],[Business Energy Essentials]],Definitions!$A$21:$A$37,0)),AND(Table3[[#This Row],[Scale]:[Scale]]="Small",Table3[[#This Row],[Business Energy Essentials]]=1),INDEX(Definitions!$B$21:$B$37,MATCH(Table3[[#Headers],[Business Energy Essentials]],Definitions!$A$21:$A$37,0)),Table3[[#This Row],[Business Energy Essentials]]=0,0)} -> 0 | AZ9: {=_xlfn.IFS(AND(Table3[[#This Row],[Scale]:[Scale]]="Large",Table3[[#This Row],[Energy User RTM Analysis]]=1),INDEX(Definitions!$C$21:$C$37,MATCH(Table3[[#Headers],[Energy User RTM Analysis]],Definitions!$A$21:$A$37,0)),AND(Table3[[#This Row],[Scale]:[Scale]]="Small",Table3[[#This Row],[Energy User RTM Analysis]]=1),INDEX(Definitions!$B$21:$B$37,MATCH(Table3[[#Headers],[Energy User RTM Analysis]],Definitions!$A$21:$A$37,0)),Table3[[#This Row],[Energy User RTM Analysis]]=0,0)} -> 0 | BA9: {=_xlfn.IFS(AND(Table3[[#This Row],[Scale]:[Scale]]="Large",Table3[[#This Row],[Energy User Forecasts]]=1),INDEX(Definitions!$C$21:$C$37,MATCH(Table3[[#Headers],[Energy User Forecasts]],Definitions!$A$21:$A$37,0)),AND(Table3[[#This Row],[Scale]:[Scale]]="Small",Table3[[#This Row],[Energy User Forecasts]]=1),INDEX(Definitions!$B$21:$B$37,MATCH(Table3[[#Headers],[Energy User Forecasts]],Definitions!$A$21:$A$37,0)),Table3[[#This Row],[Energy User Forecasts]]=0,0)} -> 0 | BB9: {=_xlfn.IFS(AND(Table3[[#This Row],[Scale]:[Scale]]="Large",Table3[[#This Row],[Energy User Regulation]]=1),INDEX(Definitions!$C$21:$C$37,MATCH(Table3[[#Headers],[Energy User Regulation]],Definitions!$A$21:$A$37,0)),AND(Table3[[#This Row],[Scale]:[Scale]]="Small",Table3[[#This Row],[Energy User Regulation]]=1),INDEX(Definitions!$B$21:$B$37,MATCH(Table3[[#Headers],[Energy User Regulation]],Definitions!$A$21:$A$37,0)),Table3[[#This Row],[Energy User Regulation]]=0,0)} -> 0 | BC9: =IF(SUM(Table3[[#This Row],[Column2]:[Column18]])>Table3[[#This Row],[Column19]],Table3[[#This Row],[Column19]],SUM(Table3[[#This Row],[Column2]:[Column18]])) -> 250000 | BD9: =Table3[[#This Row],[Total Spend]]/SUM(Table3[[#This Row],[Column2]:[Column18]]) -> 0.51824212
A10: EDF Energy Customers Limited | B10: Yes | D10: 45566 | E10: Large | F10: =INDEX(Definitions!$G$13:$G$17,MATCH(Table3[[#This Row],[Propensity to buy/ buyer readiness]],Definitions!$A$13:$A$17,0)) -> 250000 | G10: 5 | H10: 5 | I10: 5 | J10: 5 | K10: 5 | L10: =SUM(Table3[[#This Row],[Strategic priority segment]:[Propensity to buy/ buyer readiness]]) -> 25 | M10: Energy Supply | N10: Energy supplier | U10: 1 | V10: 1 | W10: 1 | X10: 1 | Y10: 1 | Z10: 0 | AA10: 0 | AB10: 0 | AC10: 0 | AD10: 1 | AE10: 0 | AF10: 0 | AG10: 0 | AH10: 0 | AI10: 0 | AJ10: 0 | AK10: 0 | AL10: {=_xlfn.IFS(AND(Table3[[#This Row],[Scale]:[Scale]]="Large",Table3[[#This Row],[Industry Essentials]]=1),INDEX(Definitions!$C$21:$C$37,MATCH(Table3[[#Headers],[Industry Essentials]],Definitions!$A$21:$A$37,0)),AND(Table3[[#This Row],[Scale]:[Scale]]="Small",Table3[[#This Row],[Industry Essentials]]=1),INDEX(Definitions!$B$21:$B$37,MATCH(Table3[[#Headers],[Industry Essentials]],Definitions!$A$21:$A$37,0)),Table3[[#This Row],[Industry Essentials]]=0,0)} -> 10800 | AM10: {=_xlfn.IFS(AND(Table3[[#This Row],[Scale]:[Scale]]="Large",Table3[[#This Row],[Energy Supply Market Intelligence]]=1),INDEX(Definitions!$C$21:$C$37,MATCH(Table3[[#Headers],[Energy Supply Market Intelligence]],Definitions!$A$21:$A$37,0)),AND(Table3[[#This Row],[Scale]:[Scale]]="Small",Table3[[#This Row],[Energy Supply Market Intelligence]]=1),INDEX(Definitions!$B$21:$B$37,MATCH(Table3[[#Headers],[Energy Supply Market Intelligence]],Definitions!$A$21:$A$37,0)),Table3[[#This Row],[Energy Supply Market Intelligence]]=0,0)} -> 43200 | AN10: {=_xlfn.IFS(AND(Table3[[#This Row],[Scale]:[Scale]]="Large",Table3[[#This Row],[Energy Supply RTM Analysis]]=1),INDEX(Definitions!$C$21:$C$37,MATCH(Table3[[#Headers],[Energy Supply RTM Analysis]],Definitions!$A$21:$A$37,0)),AND(Table3[[#This Row],[Scale]:[Scale]]="Small",Table3[[#This Row],[Energy Supply RTM Analysis]]=1),INDEX(Definitions!$B$21:$B$37,MATCH(Table3[[#Headers],[Energy Supply RTM Analysis]],Definitions!$A$21:$A$37,0)),Table3[[#This Row],[Energy Supply RTM Analysis]]=0,0)} -> 73800 | AO10: {=_xlfn.IFS(AND(Table3[[#This Row],[Scale]:[Scale]]="Large",Table3[[#This Row],[Energy Supply Forecasts]]=1),INDEX(Definitions!$C$21:$C$37,MATCH(Table3[[#Headers],[Energy Supply Forecasts]],Definitions!$A$21:$A$37,0)),AND(Table3[[#This Row],[Scale]:[Scale]]="Small",Table3[[#This Row],[Energy Supply Forecasts]]=1),INDEX(Definitions!$B$21:$B$37,MATCH(Table3[[#Headers],[Energy Supply Forecasts]],Definitions!$A$21:$A$37,0)),Table3[[#This Row],[Energy Supply Forecasts]]=0,0)} -> 48600 | AP10: {=_xlfn.IFS(AND(Table3[[#This Row],[Scale]:[Scale]]="Large",Table3[[#This Row],[Energy Supply Regulation]]=1),INDEX(Definitions!$C$21:$C$37,MATCH(Table3[[#Headers],[Energy Supply Regulation]],Definitions!$A$21:$A$37,0)),AND(Table3[[#This Row],[Scale]:[Scale]]="Small",Table3[[#This Row],[Energy Supply Regulation]]=1),INDEX(Definitions!$B$21:$B$37,MATCH(Table3[[#Headers],[Energy Supply Regulation]],Definitions!$A$21:$A$37,0)),Table3[[#This Row],[Energy Supply Regulation]]=0,0)} -> 55800 | AQ10: {=_xlfn.IFS(AND(Table3[[#This Row],[Scale]:[Scale]]="Large",Table3[[#This Row],[Renewables Market Intelligence]]=1),INDEX(Definitions!$C$21:$C$37,MATCH(Table3[[#Headers],[Renewables Market Intelligence]],Definitions!$A$21:$A$37,0)),AND(Table3[[#This Row],[Scale]:[Scale]]="Small",Table3[[#This Row],[Renewables Market Intelligence]]=1),INDEX(Definitions!$B$21:$B$37,MATCH(Table3[[#Headers],[Renewables Market Intelligence]],Definitions!$A$21:$A$37,0)),Table3[[#This Row],[Renewables Market Intelligence]]=0,0)} -> 0 | AR10: {=_xlfn.IFS(AND(Table3[[#This Row],[Scale]:[Scale]]="Large",Table3[[#This Row],[Renewables RTM Analysis]]=1),INDEX(Definitions!$C$21:$C$37,MATCH(Table3[[#Headers],[Renewables RTM Analysis]],Definitions!$A$21:$A$37,0)),AND(Table3[[#This Row],[Scale]:[Scale]]="Small",Table3[[#This Row],[Renewables RTM Analysis]]=1),INDEX(Definitions!$B$21:$B$37,MATCH(Table3[[#Headers],[Renewables RTM Analysis]],Definitions!$A$21:$A$37,0)),Table3[[#This Row],[Renewables RTM Analysis]]=0,0)} -> 0 | AS10: {=_xlfn.IFS(AND(Table3[[#This Row],[Scale]:[Scale]]="Large",Table3[[#This Row],[Renewables Forecasts]]=1),INDEX(Definitions!$C$21:$C$37,MATCH(Table3[[#Headers],[Renewables Forecasts]],Definitions!$A$21:$A$37,0)),AND(Table3[[#This Row],[Scale]:[Scale]]="Small",Table3[[#This Row],[Renewables Forecasts]]=1),INDEX(Definitions!$B$21:$B$37,MATCH(Table3[[#Headers],[Renewables Forecasts]],Definitions!$A$21:$A$37,0)),Table3[[#This Row],[Renewables Forecasts]]=0,0)} -> 0 | AT10: {=_xlfn.IFS(AND(Table3[[#This Row],[Scale]:[Scale]]="Large",Table3[[#This Row],[Renewables Regulation]]=1),INDEX(Definitions!$C$21:$C$37,MATCH(Table3[[#Headers],[Renewables Regulation]],Definitions!$A$21:$A$37,0)),AND(Table3[[#This Row],[Scale]:[Scale]]="Small",Table3[[#This Row],[Renewables Regulation]]=1),INDEX(Definitions!$B$21:$B$37,MATCH(Table3[[#Headers],[Renewables Regulation]],Definitions!$A$21:$A$37,0)),Table3[[#This Row],[Renewables Regulation]]=0,0)} -> 0 | AU10: {=_xlfn.IFS(AND(Table3[[#This Row],[Scale]:[Scale]]="Large",Table3[[#This Row],[Flexibility Market Intelligence]]=1),INDEX(Definitions!$C$21:$C$37,MATCH(Table3[[#Headers],[Flexibility Market Intelligence]],Definitions!$A$21:$A$37,0)),AND(Table3[[#This Row],[Scale]:[Scale]]="Small",Table3[[#This Row],[Flexibility Market Intelligence]]=1),INDEX(Definitions!$B$21:$B$37,MATCH(Table3[[#Headers],[Flexibility Market Intelligence]],Definitions!$A$21:$A$37,0)),Table3[[#This Row],[Flexibility Market Intelligence]]=0,0)} -> 29700 | AV10: {=_xlfn.IFS(AND(Table3[[#This Row],[Scale]:[Scale]]="Large",Table3[[#This Row],[Flexibility RTM Analysis]]=1),INDEX(Definitions!$C$21:$C$37,MATCH(Table3[[#Headers],[Flexibility RTM Analysis]],Definitions!$A$21:$A$37,0)),AND(Table3[[#This Row],[Scale]:[Scale]]="Small",Table3[[#This Row],[Flexibility RTM Analysis]]=1),INDEX(Definitions!$B$21:$B$37,MATCH(Table3[[#Headers],[Flexibility RTM Analysis]],Definitions!$A$21:$A$37,0)),Table3[[#This Row],[Flexibility RTM Analysis]]=0,0)} -> 0 | AW10: {=_xlfn.IFS(AND(Table3[[#This Row],[Scale]:[Scale]]="Large",Table3[[#This Row],[Flexibility Forecasts]]=1),INDEX(Definitions!$C$21:$C$37,MATCH(Table3[[#Headers],[Flexibility Forecasts]],Definitions!$A$21:$A$37,0)),AND(Table3[[#This Row],[Scale]:[Scale]]="Small",Table3[[#This Row],[Flexibility Forecasts]]=1),INDEX(Definitions!$B$21:$B$37,MATCH(Table3[[#Headers],[Flexibility Forecasts]],Definitions!$A$21:$A$37,0)),Table3[[#This Row],[Flexibility Forecasts]]=0,0)} -> 0 | AX10: {=_xlfn.IFS(AND(Table3[[#This Row],[Scale]:[Scale]]="Large",Table3[[#This Row],[Flexibility Regulation]]=1),INDEX(Definitions!$C$21:$C$37,MATCH(Table3[[#Headers],[Flexibility Regulation]],Definitions!$A$21:$A$37,0)),AND(Table3[[#This Row],[Scale]:[Scale]]="Small",Table3[[#This Row],[Flexibility Regulation]]=1),INDEX(Definitions!$B$21:$B$37,MATCH(Table3[[#Headers],[Flexibility Regulation]],Definitions!$A$21:$A$37,0)),Table3[[#This Row],[Flexibility Regulation]]=0,0)} -> 0 | AY10: {=_xlfn.IFS(AND(Table3[[#This Row],[Scale]:[Scale]]="Large",Table3[[#This Row],[Business Energy Essentials]]=1),INDEX(Definitions!$C$21:$C$37,MATCH(Table3[[#Headers],[Business Energy Essentials]],Definitions!$A$21:$A$37,0)),AND(Table3[[#This Row],[Scale]:[Scale]]="Small",Table3[[#This Row],[Business Energy Essentials]]=1),INDEX(Definitions!$B$21:$B$37,MATCH(Table3[[#Headers],[Business Energy Essentials]],Definitions!$A$21:$A$37,0)),Table3[[#This Row],[Business Energy Essentials]]=0,0)} -> 0 | AZ10: {=_xlfn.IFS(AND(Table3[[#This Row],[Scale]:[Scale]]="Large",Table3[[#This Row],[Energy User RTM Analysis]]=1),INDEX(Definitions!$C$21:$C$37,MATCH(Table3[[#Headers],[Energy User RTM Analysis]],Definitions!$A$21:$A$37,0)),AND(Table3[[#This Row],[Scale]:[Scale]]="Small",Table3[[#This Row],[Energy User RTM Analysis]]=1),INDEX(Definitions!$B$21:$B$37,MATCH(Table3[[#Headers],[Energy User RTM Analysis]],Definitions!$A$21:$A$37,0)),Table3[[#This Row],[Energy User RTM Analysis]]=0,0)} -> 0 | BA10: {=_xlfn.IFS(AND(Table3[[#This Row],[Scale]:[Scale]]="Large",Table3[[#This Row],[Energy User Forecasts]]=1),INDEX(Definitions!$C$21:$C$37,MATCH(Table3[[#Headers],[Energy User Forecasts]],Definitions!$A$21:$A$37,0)),AND(Table3[[#This Row],[Scale]:[Scale]]="Small",Table3[[#This Row],[Energy User Forecasts]]=1),INDEX(Definitions!$B$21:$B$37,MATCH(Table3[[#Headers],[Energy User Forecasts]],Definitions!$A$21:$A$37,0)),Table3[[#This Row],[Energy User Forecasts]]=0,0)} -> 0 | BB10: {=_xlfn.IFS(AND(Table3[[#This Row],[Scale]:[Scale]]="Large",Table3[[#This Row],[Energy User Regulation]]=1),INDEX(Definitions!$C$21:$C$37,MATCH(Table3[[#Headers],[Energy User Regulation]],Definitions!$A$21:$A$37,0)),AND(Table3[[#This Row],[Scale]:[Scale]]="Small",Table3[[#This Row],[Energy User Regulation]]=1),INDEX(Definitions!$B$21:$B$37,MATCH(Table3[[#Headers],[Energy User Regulation]],Definitions!$A$21:$A$37,0)),Table3[[#This Row],[Energy User Regulation]]=0,0)} -> 0 | BC10: =IF(SUM(Table3[[#This Row],[Column2]:[Column18]])>Table3[[#This Row],[Column19]],Table3[[#This Row],[Column19]],SUM(Table3[[#This Row],[Column2]:[Column18]])) -> 250000 | BD10: =Table3[[#This Row],[Total Spend]]/SUM(Table3[[#This Row],[Column2]:[Column18]]) -> 0.95456281
A11: EDF Energy Limited | B11: Yes | D11: 45566 | E11: Large | F11: =INDEX(Definitions!$G$13:$G$17,MATCH(Table3[[#This Row],[Propensity to buy/ buyer readiness]],Definitions!$A$13:$A$17,0)) -> 250000 | G11: 5 | H11: 5 | I11: 5 | J11: 5 | K11: 5 | L11: =SUM(Table3[[#This Row],[Strategic priority segment]:[Propensity to buy/ buyer readiness]]) -> 25 | M11: Energy Supply | N11: Energy supplier | O11: Energy traders | P11: Flexibility generator/developer | Q11: Renewables generator/developer | U11: 1 | V11: 1 | W11: 1 | X11: 1 | Y11: 1 | Z11: 1 | AA11: 1 | AB11: 1 | AC11: 1 | AD11: 1 | AE11: 1 | AF11: 1 | AG11: 1 | AH11: 0 | AI11: 0 | AJ11: 0 | AK11: 0 | AL11: {=_xlfn.IFS(AND(Table3[[#This Row],[Scale]:[Scale]]="Large",Table3[[#This Row],[Industry Essentials]]=1),INDEX(Definitions!$C$21:$C$37,MATCH(Table3[[#Headers],[Industry Essentials]],Definitions!$A$21:$A$37,0)),AND(Table3[[#This Row],[Scale]:[Scale]]="Small",Table3[[#This Row],[Industry Essentials]]=1),INDEX(Definitions!$B$21:$B$37,MATCH(Table3[[#Headers],[Industry Essentials]],Definitions!$A$21:$A$37,0)),Table3[[#This Row],[Industry Essentials]]=0,0)} -> 10800 | AM11: {=_xlfn.IFS(AND(Table3[[#This Row],[Scale]:[Scale]]="Large",Table3[[#This Row],[Energy Supply Market Intelligence]]=1),INDEX(Definitions!$C$21:$C$37,MATCH(Table3[[#Headers],[Energy Supply Market Intelligence]],Definitions!$A$21:$A$37,0)),AND(Table3[[#This Row],[Scale]:[Scale]]="Small",Table3[[#This Row],[Energy Supply Market Intelligence]]=1),INDEX(Definitions!$B$21:$B$37,MATCH(Table3[[#Headers],[Energy Supply Market Intelligence]],Definitions!$A$21:$A$37,0)),Table3[[#This Row],[Energy Supply Market Intelligence]]=0,0)} -> 43200 | AN11: {=_xlfn.IFS(AND(Table3[[#This Row],[Scale]:[Scale]]="Large",Table3[[#This Row],[Energy Supply RTM Analysis]]=1),INDEX(Definitions!$C$21:$C$37,MATCH(Table3[[#Headers],[Energy Supply RTM Analysis]],Definitions!$A$21:$A$37,0)),AND(Table3[[#This Row],[Scale]:[Scale]]="Small",Table3[[#This Row],[Energy Supply RTM Analysis]]=1),INDEX(Definitions!$B$21:$B$37,MATCH(Table3[[#Headers],[Energy Supply RTM Analysis]],Definitions!$A$21:$A$37,0)),Table3[[#This Row],[Energy Supply RTM Analysis]]=0,0)} -> 73800 | AO11: {=_xlfn.IFS(AND(Table3[[#This Row],[Scale]:[Scale]]="Large",Table3[[#This Row],[Energy Supply Forecasts]]=1),INDEX(Definitions!$C$21:$C$37,MATCH(Table3[[#Headers],[Energy Supply Forecasts]],Definitions!$A$21:$A$37,0)),AND(Table3[[#This Row],[Scale]:[Scale]]="Small",Table3[[#This Row],[Energy Supply Forecasts]]=1),INDEX(Definitions!$B$21:$B$37,MATCH(Table3[[#Headers],[Energy Supply Forecasts]],Definitions!$A$21:$A$37,0)),Table3[[#This Row],[Energy Supply Forecasts]]=0,0)} -> 48600 | AP11: {=_xlfn.IFS(AND(Table3[[#This Row],[Scale]:[Scale]]="Large",Table3[[#This Row],[Energy Supply Regulation]]=1),INDEX(Definitions!$C$21:$C$37,MATCH(Table3[[#Headers],[Energy Supply Regulation]],Definitions!$A$21:$A$37,0)),AND(Table3[[#This Row],[Scale]:[Scale]]="Small",Table3[[#This Row],[Energy Supply Regulation]]=1),INDEX(Definitions!$B$21:$B$37,MATCH(Table3[[#Headers],[Energy Supply Regulation]],Definitions!$A$21:$A$37,0)),Table3[[#This Row],[Energy Supply Regulation]]=0,0)} -> 55800 | AQ11: {=_xlfn.IFS(AND(Table3[[#This Row],[Scale]:[Scale]]="Large",Table3[[#This Row],[Renewables Market Intelligence]]=1),INDEX(Definitions!$C$21:$C$37,MATCH(Table3[[#Headers],[Renewables Market Intelligence]],Definitions!$A$21:$A$37,0)),AND(Table3[[#This Row],[Scale]:[Scale]]="Small",Table3[[#This Row],[Renewables Market Intelligence]]=1),INDEX(Definitions!$B$21:$B$37,MATCH(Table3[[#Headers],[Renewables Market Intelligence]],Definitions!$A$21:$A$37,0)),Table3[[#This Row],[Renewables Market Intelligence]]=0,0)} -> 23400 | AR11: {=_xlfn.IFS(AND(Table3[[#This Row],[Scale]:[Scale]]="Large",Table3[[#This Row],[Renewables RTM Analysis]]=1),INDEX(Definitions!$C$21:$C$37,MATCH(Table3[[#Headers],[Renewables RTM Analysis]],Definitions!$A$21:$A$37,0)),AND(Table3[[#This Row],[Scale]:[Scale]]="Small",Table3[[#This Row],[Renewables RTM Analysis]]=1),INDEX(Definitions!$B$21:$B$37,MATCH(Table3[[#Headers],[Renewables RTM Analysis]],Definitions!$A$21:$A$37,0)),Table3[[#This Row],[Renewables RTM Analysis]]=0,0)} -> 20700 | AS11: {=_xlfn.IFS(AND(Table3[[#This Row],[Scale]:[Scale]]="Large",Table3[[#This Row],[Renewables Forecasts]]=1),INDEX(Definitions!$C$21:$C$37,MATCH(Table3[[#Headers],[Renewables Forecasts]],Definitions!$A$21:$A$37,0)),AND(Table3[[#This Row],[Scale]:[Scale]]="Small",Table3[[#This Row],[Renewables Forecasts]]=1),INDEX(Definitions!$B$21:$B$37,MATCH(Table3[[#Headers],[Renewables Forecasts]],Definitions!$A$21:$A$37,0)),Table3[[#This Row],[Renewables Forecasts]]=0,0)} -> 59400 | AT11: {=_xlfn.IFS(AND(Table3[[#This Row],[Scale]:[Scale]]="Large",Table3[[#This Row],[Renewables Regulation]]=1),INDEX(Definitions!$C$21:$C$37,MATCH(Table3[[#Headers],[Renewables Regulation]],Definitions!$A$21:$A$37,0)),AND(Table3[[#This Row],[Scale]:[Scale]]="Small",Table3[[#This Row],[Renewables Regulation]]=1),INDEX(Definitions!$B$21:$B$37,MATCH(Table3[[#Headers],[Renewables Regulation]],Definitions!$A$21:$A$37,0)),Table3[[#This Row],[Renewables Regulation]]=0,0)} -> 26100 | AU11: {=_xlfn.IFS(AND(Table3[[#This Row],[Scale]:[Scale]]="Large",Table3[[#This Row],[Flexibility Market Intelligence]]=1),INDEX(Definitions!$C$21:$C$37,MATCH(Table3[[#Headers],[Flexibility Market Intelligence]],Definitions!$A$21:$A$37,0)),AND(Table3[[#This Row],[Scale]:[Scale]]="Small",Table3[[#This Row],[Flexibility Market Intelligence]]=1),INDEX(Definitions!$B$21:$B$37,MATCH(Table3[[#Headers],[Flexibility Market Intelligence]],Definitions!$A$21:$A$37,0)),Table3[[#This Row],[Flexibility Market Intelligence]]=0,0)} -> 29700 | AV11: {=_xlfn.IFS(AND(Table3[[#This Row],[Scale]:[Scale]]="Large",Table3[[#This Row],[Flexibility RTM Analysis]]=1),INDEX(Definitions!$C$21:$C$37,MATCH(Table3[[#Headers],[Flexibility RTM Analysis]],Definitions!$A$21:$A$37,0)),AND(Table3[[#This Row],[Scale]:[Scale]]="Small",Table3[[#This Row],[Flexibility RTM Analysis]]=1),INDEX(Definitions!$B$21:$B$37,MATCH(Table3[[#Headers],[Flexibility RTM Analysis]],Definitions!$A$21:$A$37,0)),Table3[[#This Row],[Flexibility RTM Analysis]]=0,0)} -> 10800 | AW11: {=_xlfn.IFS(AND(Table3[[#This Row],[Scale]:[Scale]]="Large",Table3[[#This Row],[Flexibility Forecasts]]=1),INDEX(Definitions!$C$21:$C$37,MATCH(Table3[[#Headers],[Flexibility Forecasts]],Definitions!$A$21:$A$37,0)),AND(Table3[[#This Row],[Scale]:[Scale]]="Small",Table3[[#This Row],[Flexibility Forecasts]]=1),INDEX(Definitions!$B$21:$B$37,MATCH(Table3[[#Headers],[Flexibility Forecasts]],Definitions!$A$21:$A$37,0)),Table3[[#This Row],[Flexibility Forecasts]]=0,0)} -> 44100 | AX11: {=_xlfn.IFS(AND(Table3[[#This Row],[Scale]:[Scale]]="Large",Table3[[#This Row],[Flexibility Regulation]]=1),INDEX(Definitions!$C$21:$C$37,MATCH(Table3[[#Headers],[Flexibility Regulation]],Definitions!$A$21:$A$37,0)),AND(Table3[[#This Row],[Scale]:[Scale]]="Small",Table3[[#This Row],[Flexibility Regulation]]=1),INDEX(Definitions!$B$21:$B$37,MATCH(Table3[[#Headers],[Flexibility Regulation]],Definitions!$A$21:$A$37,0)),Table3[[#This Row],[Flexibility Regulation]]=0,0)} -> 36000 | AY11: {=_xlfn.IFS(AND(Table3[[#This Row],[Scale]:[Scale]]="Large",Table3[[#This Row],[Business Energy Essentials]]=1),INDEX(Definitions!$C$21:$C$37,MATCH(Table3[[#Headers],[Business Energy Essentials]],Definitions!$A$21:$A$37,0)),AND(Table3[[#This Row],[Scale]:[Scale]]="Small",Table3[[#This Row],[Business Energy Essentials]]=1),INDEX(Definitions!$B$21:$B$37,MATCH(Table3[[#Headers],[Business Energy Essentials]],Definitions!$A$21:$A$37,0)),Table3[[#This Row],[Business Energy Essentials]]=0,0)} -> 0 | AZ11: {=_xlfn.IFS(AND(Table3[[#This Row],[Scale]:[Scale]]="Large",Table3[[#This Row],[Energy User RTM Analysis]]=1),INDEX(Definitions!$C$21:$C$37,MATCH(Table3[[#Headers],[Energy User RTM Analysis]],Definitions!$A$21:$A$37,0)),AND(Table3[[#This Row],[Scale]:[Scale]]="Small",Table3[[#This Row],[Energy User RTM Analysis]]=1),INDEX(Definitions!$B$21:$B$37,MATCH(Table3[[#Headers],[Energy User RTM Analysis]],Definitions!$A$21:$A$37,0)),Table3[[#This Row],[Energy User RTM Analysis]]=0,0)} -> 0 | BA11: {=_xlfn.IFS(AND(Table3[[#This Row],[Scale]:[Scale]]="Large",Table3[[#This Row],[Energy User Forecasts]]=1),INDEX(Definitions!$C$21:$C$37,MATCH(Table3[[#Headers],[Energy User Forecasts]],Definitions!$A$21:$A$37,0)),AND(Table3[[#This Row],[Scale]:[Scale]]="Small",Table3[[#This Row],[Energy User Forecasts]]=1),INDEX(Definitions!$B$21:$B$37,MATCH(Table3[[#Headers],[Energy User Forecasts]],Definitions!$A$21:$A$37,0)),Table3[[#This Row],[Energy User Forecasts]]=0,0)} -> 0 | BB11: {=_xlfn.IFS(AND(Table3[[#This Row],[Scale]:[Scale]]="Large",Table3[[#This Row],[Energy User Regulation]]=1),INDEX(Definitions!$C$21:$C$37,MATCH(Table3[[#Headers],[Energy User Regulation]],Definitions!$A$21:$A$37,0)),AND(Table3[[#This Row],[Scale]:[Scale]]="Small",Table3[[#This Row],[Energy User Regulation]]=1),INDEX(Definitions!$B$21:$B$37,MATCH(Table3[[#Headers],[Energy User Regulation]],Definitions!$A$21:$A$37,0)),Table3[[#This Row],[Energy User Regulation]]=0,0)} -> 0 | BC11: =IF(SUM(Table3[[#This Row],[Column2]:[Column18]])>Table3[[#This Row],[Column19]],Table3[[#This Row],[Column19]],SUM(Table3[[#This Row],[Column2]:[Column18]])) -> 250000 | BD11: =Table3[[#This Row],[Total Spend]]/SUM(Table3[[#This Row],[Column2]:[Column18]]) -> 0.51824212
A12: ENGIE Power Limited | B12: Yes | D12: 45566 | E12: Large | F12: =INDEX(Definitions!$G$13:$G$17,MATCH(Table3[[#This Row],[Propensity to buy/ buyer readiness]],Definitions!$A$13:$A$17,0)) -> 250000 | G12: 5 | H12: 5 | I12: 5 | J12: 5 | K12: 5 | L12: =SUM(Table3[[#This Row],[Strategic priority segment]:[Propensity to buy/ buyer readiness]]) -> 25 | M12: Energy Supply | N12: Energy supplier | O12: Renewables generator/developer | P12: Flexibility generator/developer | Q12: Energy traders | U12: 1 | V12: 1 | W12: 1 | X12: 1 | Y12: 1 | Z12: 1 | AA12: 1 | AB12: 1 | AC12: 1 | AD12: 1 | AE12: 1 | AF12: 1 | AG12: 1 | AH12: 0 | AI12: 0 | AJ12: 0 | AK12: 0 | AL12: {=_xlfn.IFS(AND(Table3[[#This Row],[Scale]:[Scale]]="Large",Table3[[#This Row],[Industry Essentials]]=1),INDEX(Definitions!$C$21:$C$37,MATCH(Table3[[#Headers],[Industry Essentials]],Definitions!$A$21:$A$37,0)),AND(Table3[[#This Row],[Scale]:[Scale]]="Small",Table3[[#This Row],[Industry Essentials]]=1),INDEX(Definitions!$B$21:$B$37,MATCH(Table3[[#Headers],[Industry Essentials]],Definitions!$A$21:$A$37,0)),Table3[[#This Row],[Industry Essentials]]=0,0)} -> 10800 | AM12: {=_xlfn.IFS(AND(Table3[[#This Row],[Scale]:[Scale]]="Large",Table3[[#This Row],[Energy Supply Market Intelligence]]=1),INDEX(Definitions!$C$21:$C$37,MATCH(Table3[[#Headers],[Energy Supply Market Intelligence]],Definitions!$A$21:$A$37,0)),AND(Table3[[#This Row],[Scale]:[Scale]]="Small",Table3[[#This Row],[Energy Supply Market Intelligence]]=1),INDEX(Definitions!$B$21:$B$37,MATCH(Table3[[#Headers],[Energy Supply Market Intelligence]],Definitions!$A$21:$A$37,0)),Table3[[#This Row],[Energy Supply Market Intelligence]]=0,0)} -> 43200 | AN12: {=_xlfn.IFS(AND(Table3[[#This Row],[Scale]:[Scale]]="Large",Table3[[#This Row],[Energy Supply RTM Analysis]]=1),INDEX(Definitions!$C$21:$C$37,MATCH(Table3[[#Headers],[Energy Supply RTM Analysis]],Definitions!$A$21:$A$37,0)),AND(Table3[[#This Row],[Scale]:[Scale]]="Small",Table3[[#This Row],[Energy Supply RTM Analysis]]=1),INDEX(Definitions!$B$21:$B$37,MATCH(Table3[[#Headers],[Energy Supply RTM Analysis]],Definitions!$A$21:$A$37,0)),Table3[[#This Row],[Energy Supply RTM Analysis]]=0,0)} -> 73800 | AO12: {=_xlfn.IFS(AND(Table3[[#This Row],[Scale]:[Scale]]="Large",Table3[[#This Row],[Energy Supply Forecasts]]=1),INDEX(Definitions!$C$21:$C$37,MATCH(Table3[[#Headers],[Energy Supply Forecasts]],Definitions!$A$21:$A$37,0)),AND(Table3[[#This Row],[Scale]:[Scale]]="Small",Table3[[#This Row],[Energy Supply Forecasts]]=1),INDEX(Definitions!$B$21:$B$37,MATCH(Table3[[#Headers],[Energy Supply Forecasts]],Definitions!$A$21:$A$37,0)),Table3[[#This Row],[Energy Supply Forecasts]]=0,0)} -> 48600 | AP12: {=_xlfn.IFS(AND(Table3[[#This Row],[Scale]:[Scale]]="Large",Table3[[#This Row],[Energy Supply Regulation]]=1),INDEX(Definitions!$C$21:$C$37,MATCH(Table3[[#Headers],[Energy Supply Regulation]],Definitions!$A$21:$A$37,0)),AND(Table3[[#This Row],[Scale]:[Scale]]="Small",Table3[[#This Row],[Energy Supply Regulation]]=1),INDEX(Definitions!$B$21:$B$37,MATCH(Table3[[#Headers],[Energy Supply Regulation]],Definitions!$A$21:$A$37,0)),Table3[[#This Row],[Energy Supply Regulation]]=0,0)} -> 55800 | AQ12: {=_xlfn.IFS(AND(Table3[[#This Row],[Scale]:[Scale]]="Large",Table3[[#This Row],[Renewables Market Intelligence]]=1),INDEX(Definitions!$C$21:$C$37,MATCH(Table3[[#Headers],[Renewables Market Intelligence]],Definitions!$A$21:$A$37,0)),AND(Table3[[#This Row],[Scale]:[Scale]]="Small",Table3[[#This Row],[Renewables Market Intelligence]]=1),INDEX(Definitions!$B$21:$B$37,MATCH(Table3[[#Headers],[Renewables Market Intelligence]],Definitions!$A$21:$A$37,0)),Table3[[#This Row],[Renewables Market Intelligence]]=0,0)} -> 23400 | AR12: {=_xlfn.IFS(AND(Table3[[#This Row],[Scale]:[Scale]]="Large",Table3[[#This Row],[Renewables RTM Analysis]]=1),INDEX(Definitions!$C$21:$C$37,MATCH(Table3[[#Headers],[Renewables RTM Analysis]],Definitions!$A$21:$A$37,0)),AND(Table3[[#This Row],[Scale]:[Scale]]="Small",Table3[[#This Row],[Renewables RTM Analysis]]=1),INDEX(Definitions!$B$21:$B$37,MATCH(Table3[[#Headers],[Renewables RTM Analysis]],Definitions!$A$21:$A$37,0)),Table3[[#This Row],[Renewables RTM Analysis]]=0,0)} -> 20700 | AS12: {=_xlfn.IFS(AND(Table3[[#This Row],[Scale]:[Scale]]="Large",Table3[[#This Row],[Renewables Forecasts]]=1),INDEX(Definitions!$C$21:$C$37,MATCH(Table3[[#Headers],[Renewables Forecasts]],Definitions!$A$21:$A$37,0)),AND(Table3[[#This Row],[Scale]:[Scale]]="Small",Table3[[#This Row],[Renewables Forecasts]]=1),INDEX(Definitions!$B$21:$B$37,MATCH(Table3[[#Headers],[Renewables Forecasts]],Definitions!$A$21:$A$37,0)),Table3[[#This Row],[Renewables Forecasts]]=0,0)} -> 59400 | AT12: {=_xlfn.IFS(AND(Table3[[#This Row],[Scale]:[Scale]]="Large",Table3[[#This Row],[Renewables Regulation]]=1),INDEX(Definitions!$C$21:$C$37,MATCH(Table3[[#Headers],[Renewables Regulation]],Definitions!$A$21:$A$37,0)),AND(Table3[[#This Row],[Scale]:[Scale]]="Small",Table3[[#This Row],[Renewables Regulation]]=1),INDEX(Definitions!$B$21:$B$37,MATCH(Table3[[#Headers],[Renewables Regulation]],Definitions!$A$21:$A$37,0)),Table3[[#This Row],[Renewables Regulation]]=0,0)} -> 26100 | AU12: {=_xlfn.IFS(AND(Table3[[#This Row],[Scale]:[Scale]]="Large",Table3[[#This Row],[Flexibility Market Intelligence]]=1),INDEX(Definitions!$C$21:$C$37,MATCH(Table3[[#Headers],[Flexibility Market Intelligence]],Definitions!$A$21:$A$37,0)),AND(Table3[[#This Row],[Scale]:[Scale]]="Small",Table3[[#This Row],[Flexibility Market Intelligence]]=1),INDEX(Definitions!$B$21:$B$37,MATCH(Table3[[#Headers],[Flexibility Market Intelligence]],Definitions!$A$21:$A$37,0)),Table3[[#This Row],[Flexibility Market Intelligence]]=0,0)} -> 29700 | AV12: {=_xlfn.IFS(AND(Table3[[#This Row],[Scale]:[Scale]]="Large",Table3[[#This Row],[Flexibility RTM Analysis]]=1),INDEX(Definitions!$C$21:$C$37,MATCH(Table3[[#Headers],[Flexibility RTM Analysis]],Definitions!$A$21:$A$37,0)),AND(Table3[[#This Row],[Scale]:[Scale]]="Small",Table3[[#This Row],[Flexibility RTM Analysis]]=1),INDEX(Definitions!$B$21:$B$37,MATCH(Table3[[#Headers],[Flexibility RTM Analysis]],Definitions!$A$21:$A$37,0)),Table3[[#This Row],[Flexibility RTM Analysis]]=0,0)} -> 10800 | AW12: {=_xlfn.IFS(AND(Table3[[#This Row],[Scale]:[Scale]]="Large",Table3[[#This Row],[Flexibility Forecasts]]=1),INDEX(Definitions!$C$21:$C$37,MATCH(Table3[[#Headers],[Flexibility Forecasts]],Definitions!$A$21:$A$37,0)),AND(Table3[[#This Row],[Scale]:[Scale]]="Small",Table3[[#This Row],[Flexibility Forecasts]]=1),INDEX(Definitions!$B$21:$B$37,MATCH(Table3[[#Headers],[Flexibility Forecasts]],Definitions!$A$21:$A$37,0)),Table3[[#This Row],[Flexibility Forecasts]]=0,0)} -> 44100 | AX12: {=_xlfn.IFS(AND(Table3[[#This Row],[Scale]:[Scale]]="Large",Table3[[#This Row],[Flexibility Regulation]]=1),INDEX(Definitions!$C$21:$C$37,MATCH(Table3[[#Headers],[Flexibility Regulation]],Definitions!$A$21:$A$37,0)),AND(Table3[[#This Row],[Scale]:[Scale]]="Small",Table3[[#This Row],[Flexibility Regulation]]=1),INDEX(Definitions!$B$21:$B$37,MATCH(Table3[[#Headers],[Flexibility Regulation]],Definitions!$A$21:$A$37,0)),Table3[[#This Row],[Flexibility Regulation]]=0,0)} -> 36000 | AY12: {=_xlfn.IFS(AND(Table3[[#This Row],[Scale]:[Scale]]="Large",Table3[[#This Row],[Business Energy Essentials]]=1),INDEX(Definitions!$C$21:$C$37,MATCH(Table3[[#Headers],[Business Energy Essentials]],Definitions!$A$21:$A$37,0)),AND(Table3[[#This Row],[Scale]:[Scale]]="Small",Table3[[#This Row],[Business Energy Essentials]]=1),INDEX(Definitions!$B$21:$B$37,MATCH(Table3[[#Headers],[Business Energy Essentials]],Definitions!$A$21:$A$37,0)),Table3[[#This Row],[Business Energy Essentials]]=0,0)} -> 0 | AZ12: {=_xlfn.IFS(AND(Table3[[#This Row],[Scale]:[Scale]]="Large",Table3[[#This Row],[Energy User RTM Analysis]]=1),INDEX(Definitions!$C$21:$C$37,MATCH(Table3[[#Headers],[Energy User RTM Analysis]],Definitions!$A$21:$A$37,0)),AND(Table3[[#This Row],[Scale]:[Scale]]="Small",Table3[[#This Row],[Energy User RTM Analysis]]=1),INDEX(Definitions!$B$21:$B$37,MATCH(Table3[[#Headers],[Energy User RTM Analysis]],Definitions!$A$21:$A$37,0)),Table3[[#This Row],[Energy User RTM Analysis]]=0,0)} -> 0 | BA12: {=_xlfn.IFS(AND(Table3[[#This Row],[Scale]:[Scale]]="Large",Table3[[#This Row],[Energy User Forecasts]]=1),INDEX(Definitions!$C$21:$C$37,MATCH(Table3[[#Headers],[Energy User Forecasts]],Definitions!$A$21:$A$37,0)),AND(Table3[[#This Row],[Scale]:[Scale]]="Small",Table3[[#This Row],[Energy User Forecasts]]=1),INDEX(Definitions!$B$21:$B$37,MATCH(Table3[[#Headers],[Energy User Forecasts]],Definitions!$A$21:$A$37,0)),Table3[[#This Row],[Energy User Forecasts]]=0,0)} -> 0 | BB12: {=_xlfn.IFS(AND(Table3[[#This Row],[Scale]:[Scale]]="Large",Table3[[#This Row],[Energy User Regulation]]=1),INDEX(Definitions!$C$21:$C$37,MATCH(Table3[[#Headers],[Energy User Regulation]],Definitions!$A$21:$A$37,0)),AND(Table3[[#This Row],[Scale]:[Scale]]="Small",Table3[[#This Row],[Energy User Regulation]]=1),INDEX(Definitions!$B$21:$B$37,MATCH(Table3[[#Headers],[Energy User Regulation]],Definitions!$A$21:$A$37,0)),Table3[[#This Row],[Energy User Regulation]]=0,0)} -> 0 | BC12: =IF(SUM(Table3[[#This Row],[Column2]:[Column18]])>Table3[[#This Row],[Column19]],Table3[[#This Row],[Column19]],SUM(Table3[[#This Row],[Column2]:[Column18]])) -> 250000 | BD12: =Table3[[#This Row],[Total Spend]]/SUM(Table3[[#This Row],[Column2]:[Column18]]) -> 0.51824212
A13: NPower Limited | B13: Yes | D13: 45566 | E13: Large | F13: =INDEX(Definitions!$G$13:$G$17,MATCH(Table3[[#This Row],[Propensity to buy/ buyer readiness]],Definitions!$A$13:$A$17,0)) -> 250000 | G13: 5 | H13: 5 | I13: 5 | J13: 5 | K13: 5 | L13: =SUM(Table3[[#This Row],[Strategic priority segment]:[Propensity to buy/ buyer readiness]]) -> 25 | M13: Energy Supply | N13: Energy supplier | U13: 1 | V13: 1 | W13: 1 | X13: 1 | Y13: 1 | Z13: 0 | AA13: 0 | AB13: 0 | AC13: 0 | AD13: 1 | AE13: 0 | AF13: 0 | AG13: 0 | AH13: 0 | AI13: 0 | AJ13: 0 | AK13: 0 | AL13: {=_xlfn.IFS(AND(Table3[[#This Row],[Scale]:[Scale]]="Large",Table3[[#This Row],[Industry Essentials]]=1),INDEX(Definitions!$C$21:$C$37,MATCH(Table3[[#Headers],[Industry Essentials]],Definitions!$A$21:$A$37,0)),AND(Table3[[#This Row],[Scale]:[Scale]]="Small",Table3[[#This Row],[Industry Essentials]]=1),INDEX(Definitions!$B$21:$B$37,MATCH(Table3[[#Headers],[Industry Essentials]],Definitions!$A$21:$A$37,0)),Table3[[#This Row],[Industry Essentials]]=0,0)} -> 10800 | AM13: {=_xlfn.IFS(AND(Table3[[#This Row],[Scale]:[Scale]]="Large",Table3[[#This Row],[Energy Supply Market Intelligence]]=1),INDEX(Definitions!$C$21:$C$37,MATCH(Table3[[#Headers],[Energy Supply Market Intelligence]],Definitions!$A$21:$A$37,0)),AND(Table3[[#This Row],[Scale]:[Scale]]="Small",Table3[[#This Row],[Energy Supply Market Intelligence]]=1),INDEX(Definitions!$B$21:$B$37,MATCH(Table3[[#Headers],[Energy Supply Market Intelligence]],Definitions!$A$21:$A$37,0)),Table3[[#This Row],[Energy Supply Market Intelligence]]=0,0)} -> 43200 | AN13: {=_xlfn.IFS(AND(Table3[[#This Row],[Scale]:[Scale]]="Large",Table3[[#This Row],[Energy Supply RTM Analysis]]=1),INDEX(Definitions!$C$21:$C$37,MATCH(Table3[[#Headers],[Energy Supply RTM Analysis]],Definitions!$A$21:$A$37,0)),AND(Table3[[#This Row],[Scale]:[Scale]]="Small",Table3[[#This Row],[Energy Supply RTM Analysis]]=1),INDEX(Definitions!$B$21:$B$37,MATCH(Table3[[#Headers],[Energy Supply RTM Analysis]],Definitions!$A$21:$A$37,0)),Table3[[#This Row],[Energy Supply RTM Analysis]]=0,0)} -> 73800 | AO13: {=_xlfn.IFS(AND(Table3[[#This Row],[Scale]:[Scale]]="Large",Table3[[#This Row],[Energy Supply Forecasts]]=1),INDEX(Definitions!$C$21:$C$37,MATCH(Table3[[#Headers],[Energy Supply Forecasts]],Definitions!$A$21:$A$37,0)),AND(Table3[[#This Row],[Scale]:[Scale]]="Small",Table3[[#This Row],[Energy Supply Forecasts]]=1),INDEX(Definitions!$B$21:$B$37,MATCH(Table3[[#Headers],[Energy Supply Forecasts]],Definitions!$A$21:$A$37,0)),Table3[[#This Row],[Energy Supply Forecasts]]=0,0)} -> 48600 | AP13: {=_xlfn.IFS(AND(Table3[[#This Row],[Scale]:[Scale]]="Large",Table3[[#This Row],[Energy Supply Regulation]]=1),INDEX(Definitions!$C$21:$C$37,MATCH(Table3[[#Headers],[Energy Supply Regulation]],Definitions!$A$21:$A$37,0)),AND(Table3[[#This Row],[Scale]:[Scale]]="Small",Table3[[#This Row],[Energy Supply Regulation]]=1),INDEX(Definitions!$B$21:$B$37,MATCH(Table3[[#Headers],[Energy Supply Regulation]],Definitions!$A$21:$A$37,0)),Table3[[#This Row],[Energy Supply Regulation]]=0,0)} -> 55800 | AQ13: {=_xlfn.IFS(AND(Table3[[#This Row],[Scale]:[Scale]]="Large",Table3[[#This Row],[Renewables Market Intelligence]]=1),INDEX(Definitions!$C$21:$C$37,MATCH(Table3[[#Headers],[Renewables Market Intelligence]],Definitions!$A$21:$A$37,0)),AND(Table3[[#This Row],[Scale]:[Scale]]="Small",Table3[[#This Row],[Renewables Market Intelligence]]=1),INDEX(Definitions!$B$21:$B$37,MATCH(Table3[[#Headers],[Renewables Market Intelligence]],Definitions!$A$21:$A$37,0)),Table3[[#This Row],[Renewables Market Intelligence]]=0,0)} -> 0 | AR13: {=_xlfn.IFS(AND(Table3[[#This Row],[Scale]:[Scale]]="Large",Table3[[#This Row],[Renewables RTM Analysis]]=1),INDEX(Definitions!$C$21:$C$37,MATCH(Table3[[#Headers],[Renewables RTM Analysis]],Definitions!$A$21:$A$37,0)),AND(Table3[[#This Row],[Scale]:[Scale]]="Small",Table3[[#This Row],[Renewables RTM Analysis]]=1),INDEX(Definitions!$B$21:$B$37,MATCH(Table3[[#Headers],[Renewables RTM Analysis]],Definitions!$A$21:$A$37,0)),Table3[[#This Row],[Renewables RTM Analysis]]=0,0)} -> 0 | AS13: {=_xlfn.IFS(AND(Table3[[#This Row],[Scale]:[Scale]]="Large",Table3[[#This Row],[Renewables Forecasts]]=1),INDEX(Definitions!$C$21:$C$37,MATCH(Table3[[#Headers],[Renewables Forecasts]],Definitions!$A$21:$A$37,0)),AND(Table3[[#This Row],[Scale]:[Scale]]="Small",Table3[[#This Row],[Renewables Forecasts]]=1),INDEX(Definitions!$B$21:$B$37,MATCH(Table3[[#Headers],[Renewables Forecasts]],Definitions!$A$21:$A$37,0)),Table3[[#This Row],[Renewables Forecasts]]=0,0)} -> 0 | AT13: {=_xlfn.IFS(AND(Table3[[#This Row],[Scale]:[Scale]]="Large",Table3[[#This Row],[Renewables Regulation]]=1),INDEX(Definitions!$C$21:$C$37,MATCH(Table3[[#Headers],[Renewables Regulation]],Definitions!$A$21:$A$37,0)),AND(Table3[[#This Row],[Scale]:[Scale]]="Small",Table3[[#This Row],[Renewables Regulation]]=1),INDEX(Definitions!$B$21:$B$37,MATCH(Table3[[#Headers],[Renewables Regulation]],Definitions!$A$21:$A$37,0)),Table3[[#This Row],[Renewables Regulation]]=0,0)} -> 0 | AU13: {=_xlfn.IFS(AND(Table3[[#This Row],[Scale]:[Scale]]="Large",Table3[[#This Row],[Flexibility Market Intelligence]]=1),INDEX(Definitions!$C$21:$C$37,MATCH(Table3[[#Headers],[Flexibility Market Intelligence]],Definitions!$A$21:$A$37,0)),AND(Table3[[#This Row],[Scale]:[Scale]]="Small",Table3[[#This Row],[Flexibility Market Intelligence]]=1),INDEX(Definitions!$B$21:$B$37,MATCH(Table3[[#Headers],[Flexibility Market Intelligence]],Definitions!$A$21:$A$37,0)),Table3[[#This Row],[Flexibility Market Intelligence]]=0,0)} -> 29700 | AV13: {=_xlfn.IFS(AND(Table3[[#This Row],[Scale]:[Scale]]="Large",Table3[[#This Row],[Flexibility RTM Analysis]]=1),INDEX(Definitions!$C$21:$C$37,MATCH(Table3[[#Headers],[Flexibility RTM Analysis]],Definitions!$A$21:$A$37,0)),AND(Table3[[#This Row],[Scale]:[Scale]]="Small",Table3[[#This Row],[Flexibility RTM Analysis]]=1),INDEX(Definitions!$B$21:$B$37,MATCH(Table3[[#Headers],[Flexibility RTM Analysis]],Definitions!$A$21:$A$37,0)),Table3[[#This Row],[Flexibility RTM Analysis]]=0,0)} -> 0 | AW13: {=_xlfn.IFS(AND(Table3[[#This Row],[Scale]:[Scale]]="Large",Table3[[#This Row],[Flexibility Forecasts]]=1),INDEX(Definitions!$C$21:$C$37,MATCH(Table3[[#Headers],[Flexibility Forecasts]],Definitions!$A$21:$A$37,0)),AND(Table3[[#This Row],[Scale]:[Scale]]="Small",Table3[[#This Row],[Flexibility Forecasts]]=1),INDEX(Definitions!$B$21:$B$37,MATCH(Table3[[#Headers],[Flexibility Forecasts]],Definitions!$A$21:$A$37,0)),Table3[[#This Row],[Flexibility Forecasts]]=0,0)} -> 0 | AX13: {=_xlfn.IFS(AND(Table3[[#This Row],[Scale]:[Scale]]="Large",Table3[[#This Row],[Flexibility Regulation]]=1),INDEX(Definitions!$C$21:$C$37,MATCH(Table3[[#Headers],[Flexibility Regulation]],Definitions!$A$21:$A$37,0)),AND(Table3[[#This Row],[Scale]:[Scale]]="Small",Table3[[#This Row],[Flexibility Regulation]]=1),INDEX(Definitions!$B$21:$B$37,MATCH(Table3[[#Headers],[Flexibility Regulation]],Definitions!$A$21:$A$37,0)),Table3[[#This Row],[Flexibility Regulation]]=0,0)} -> 0 | AY13: {=_xlfn.IFS(AND(Table3[[#This Row],[Scale]:[Scale]]="Large",Table3[[#This Row],[Business Energy Essentials]]=1),INDEX(Definitions!$C$21:$C$37,MATCH(Table3[[#Headers],[Business Energy Essentials]],Definitions!$A$21:$A$37,0)),AND(Table3[[#This Row],[Scale]:[Scale]]="Small",Table3[[#This Row],[Business Energy Essentials]]=1),INDEX(Definitions!$B$21:$B$37,MATCH(Table3[[#Headers],[Business Energy Essentials]],Definitions!$A$21:$A$37,0)),Table3[[#This Row],[Business Energy Essentials]]=0,0)} -> 0 | AZ13: {=_xlfn.IFS(AND(Table3[[#This Row],[Scale]:[Scale]]="Large",Table3[[#This Row],[Energy User RTM Analysis]]=1),INDEX(Definitions!$C$21:$C$37,MATCH(Table3[[#Headers],[Energy User RTM Analysis]],Definitions!$A$21:$A$37,0)),AND(Table3[[#This Row],[Scale]:[Scale]]="Small",Table3[[#This Row],[Energy User RTM Analysis]]=1),INDEX(Definitions!$B$21:$B$37,MATCH(Table3[[#Headers],[Energy User RTM Analysis]],Definitions!$A$21:$A$37,0)),Table3[[#This Row],[Energy User RTM Analysis]]=0,0)} -> 0 | BA13: {=_xlfn.IFS(AND(Table3[[#This Row],[Scale]:[Scale]]="Large",Table3[[#This Row],[Energy User Forecasts]]=1),INDEX(Definitions!$C$21:$C$37,MATCH(Table3[[#Headers],[Energy User Forecasts]],Definitions!$A$21:$A$37,0)),AND(Table3[[#This Row],[Scale]:[Scale]]="Small",Table3[[#This Row],[Energy User Forecasts]]=1),INDEX(Definitions!$B$21:$B$37,MATCH(Table3[[#Headers],[Energy User Forecasts]],Definitions!$A$21:$A$37,0)),Table3[[#This Row],[Energy User Forecasts]]=0,0)} -> 0 | BB13: {=_xlfn.IFS(AND(Table3[[#This Row],[Scale]:[Scale]]="Large",Table3[[#This Row],[Energy User Regulation]]=1),INDEX(Definitions!$C$21:$C$37,MATCH(Table3[[#Headers],[Energy User Regulation]],Definitions!$A$21:$A$37,0)),AND(Table3[[#This Row],[Scale]:[Scale]]="Small",Table3[[#This Row],[Energy User Regulation]]=1),INDEX(Definitions!$B$21:$B$37,MATCH(Table3[[#Headers],[Energy User Regulation]],Definitions!$A$21:$A$37,0)),Table3[[#This Row],[Energy User Regulation]]=0,0)} -> 0 | BC13: =IF(SUM(Table3[[#This Row],[Column2]:[Column18]])>Table3[[#This Row],[Column19]],Table3[[#This Row],[Column19]],SUM(Table3[[#This Row],[Column2]:[Column18]])) -> 250000 | BD13: =Table3[[#This Row],[Total Spend]]/SUM(Table3[[#This Row],[Column2]:[Column18]]) -> 0.95456281
A14: Octopus Energy Ltd | B14: Yes | C14: Yes | D14: 45566 | E14: Large | F14: =INDEX(Definitions!$G$13:$G$17,MATCH(Table3[[#This Row],[Propensity to buy/ buyer readiness]],Definitions!$A$13:$A$17,0)) -> 250000 | G14: 5 | H14: 5 | I14: 5 | J14: 5 | K14: 5 | L14: =SUM(Table3[[#This Row],[Strategic priority segment]:[Propensity to buy/ buyer readiness]]) -> 25 | M14: Energy Supply | N14: Energy supplier | O14: Renewables generator/developer | P14: E-mobility | Q14: Energy traders | U14: 1 | V14: 1 | W14: 1 | X14: 1 | Y14: 1 | Z14: 1 | AA14: 1 | AB14: 1 | AC14: 1 | AD14: 1 | AE14: 1 | AF14: 1 | AG14: 0 | AH14: 1 | AI14: 0 | AJ14: 1 | AK14: 0 | AL14: {=_xlfn.IFS(AND(Table3[[#This Row],[Scale]:[Scale]]="Large",Table3[[#This Row],[Industry Essentials]]=1),INDEX(Definitions!$C$21:$C$37,MATCH(Table3[[#Headers],[Industry Essentials]],Definitions!$A$21:$A$37,0)),AND(Table3[[#This Row],[Scale]:[Scale]]="Small",Table3[[#This Row],[Industry Essentials]]=1),INDEX(Definitions!$B$21:$B$37,MATCH(Table3[[#Headers],[Industry Essentials]],Definitions!$A$21:$A$37,0)),Table3[[#This Row],[Industry Essentials]]=0,0)} -> 10800 | AM14: {=_xlfn.IFS(AND(Table3[[#This Row],[Scale]:[Scale]]="Large",Table3[[#This Row],[Energy Supply Market Intelligence]]=1),INDEX(Definitions!$C$21:$C$37,MATCH(Table3[[#Headers],[Energy Supply Market Intelligence]],Definitions!$A$21:$A$37,0)),AND(Table3[[#This Row],[Scale]:[Scale]]="Small",Table3[[#This Row],[Energy Supply Market Intelligence]]=1),INDEX(Definitions!$B$21:$B$37,MATCH(Table3[[#Headers],[Energy Supply Market Intelligence]],Definitions!$A$21:$A$37,0)),Table3[[#This Row],[Energy Supply Market Intelligence]]=0,0)} -> 43200 | AN14: {=_xlfn.IFS(AND(Table3[[#This Row],[Scale]:[Scale]]="Large",Table3[[#This Row],[Energy Supply RTM Analysis]]=1),INDEX(Definitions!$C$21:$C$37,MATCH(Table3[[#Headers],[Energy Supply RTM Analysis]],Definitions!$A$21:$A$37,0)),AND(Table3[[#This Row],[Scale]:[Scale]]="Small",Table3[[#This Row],[Energy Supply RTM Analysis]]=1),INDEX(Definitions!$B$21:$B$37,MATCH(Table3[[#Headers],[Energy Supply RTM Analysis]],Definitions!$A$21:$A$37,0)),Table3[[#This Row],[Energy Supply RTM Analysis]]=0,0)} -> 73800 | AO14: {=_xlfn.IFS(AND(Table3[[#This Row],[Scale]:[Scale]]="Large",Table3[[#This Row],[Energy Supply Forecasts]]=1),INDEX(Definitions!$C$21:$C$37,MATCH(Table3[[#Headers],[Energy Supply Forecasts]],Definitions!$A$21:$A$37,0)),AND(Table3[[#This Row],[Scale]:[Scale]]="Small",Table3[[#This Row],[Energy Supply Forecasts]]=1),INDEX(Definitions!$B$21:$B$37,MATCH(Table3[[#Headers],[Energy Supply Forecasts]],Definitions!$A$21:$A$37,0)),Table3[[#This Row],[Energy Supply Forecasts]]=0,0)} -> 48600 | AP14: {=_xlfn.IFS(AND(Table3[[#This Row],[Scale]:[Scale]]="Large",Table3[[#This Row],[Energy Supply Regulation]]=1),INDEX(Definitions!$C$21:$C$37,MATCH(Table3[[#Headers],[Energy Supply Regulation]],Definitions!$A$21:$A$37,0)),AND(Table3[[#This Row],[Scale]:[Scale]]="Small",Table3[[#This Row],[Energy Supply Regulation]]=1),INDEX(Definitions!$B$21:$B$37,MATCH(Table3[[#Headers],[Energy Supply Regulation]],Definitions!$A$21:$A$37,0)),Table3[[#This Row],[Energy Supply Regulation]]=0,0)} -> 55800 | AQ14: {=_xlfn.IFS(AND(Table3[[#This Row],[Scale]:[Scale]]="Large",Table3[[#This Row],[Renewables Market Intelligence]]=1),INDEX(Definitions!$C$21:$C$37,MATCH(Table3[[#Headers],[Renewables Market Intelligence]],Definitions!$A$21:$A$37,0)),AND(Table3[[#This Row],[Scale]:[Scale]]="Small",Table3[[#This Row],[Renewables Market Intelligence]]=1),INDEX(Definitions!$B$21:$B$37,MATCH(Table3[[#Headers],[Renewables Market Intelligence]],Definitions!$A$21:$A$37,0)),Table3[[#This Row],[Renewables Market Intelligence]]=0,0)} -> 23400 | AR14: {=_xlfn.IFS(AND(Table3[[#This Row],[Scale]:[Scale]]="Large",Table3[[#This Row],[Renewables RTM Analysis]]=1),INDEX(Definitions!$C$21:$C$37,MATCH(Table3[[#Headers],[Renewables RTM Analysis]],Definitions!$A$21:$A$37,0)),AND(Table3[[#This Row],[Scale]:[Scale]]="Small",Table3[[#This Row],[Renewables RTM Analysis]]=1),INDEX(Definitions!$B$21:$B$37,MATCH(Table3[[#Headers],[Renewables RTM Analysis]],Definitions!$A$21:$A$37,0)),Table3[[#This Row],[Renewables RTM Analysis]]=0,0)} -> 20700 | AS14: {=_xlfn.IFS(AND(Table3[[#This Row],[Scale]:[Scale]]="Large",Table3[[#This Row],[Renewables Forecasts]]=1),INDEX(Definitions!$C$21:$C$37,MATCH(Table3[[#Headers],[Renewables Forecasts]],Definitions!$A$21:$A$37,0)),AND(Table3[[#This Row],[Scale]:[Scale]]="Small",Table3[[#This Row],[Renewables Forecasts]]=1),INDEX(Definitions!$B$21:$B$37,MATCH(Table3[[#Headers],[Renewables Forecasts]],Definitions!$A$21:$A$37,0)),Table3[[#This Row],[Renewables Forecasts]]=0,0)} -> 59400 | AT14: {=_xlfn.IFS(AND(Table3[[#This Row],[Scale]:[Scale]]="Large",Table3[[#This Row],[Renewables Regulation]]=1),INDEX(Definitions!$C$21:$C$37,MATCH(Table3[[#Headers],[Renewables Regulation]],Definitions!$A$21:$A$37,0)),AND(Table3[[#This Row],[Scale]:[Scale]]="Small",Table3[[#This Row],[Renewables Regulation]]=1),INDEX(Definitions!$B$21:$B$37,MATCH(Table3[[#Headers],[Renewables Regulation]],Definitions!$A$21:$A$37,0)),Table3[[#This Row],[Renewables Regulation]]=0,0)} -> 26100 | AU14: {=_xlfn.IFS(AND(Table3[[#This Row],[Scale]:[Scale]]="Large",Table3[[#This Row],[Flexibility Market Intelligence]]=1),INDEX(Definitions!$C$21:$C$37,MATCH(Table3[[#Headers],[Flexibility Market Intelligence]],Definitions!$A$21:$A$37,0)),AND(Table3[[#This Row],[Scale]:[Scale]]="Small",Table3[[#This Row],[Flexibility Market Intelligence]]=1),INDEX(Definitions!$B$21:$B$37,MATCH(Table3[[#Headers],[Flexibility Market Intelligence]],Definitions!$A$21:$A$37,0)),Table3[[#This Row],[Flexibility Market Intelligence]]=0,0)} -> 29700 | AV14: {=_xlfn.IFS(AND(Table3[[#This Row],[Scale]:[Scale]]="Large",Table3[[#This Row],[Flexibility RTM Analysis]]=1),INDEX(Definitions!$C$21:$C$37,MATCH(Table3[[#Headers],[Flexibility RTM Analysis]],Definitions!$A$21:$A$37,0)),AND(Table3[[#This Row],[Scale]:[Scale]]="Small",Table3[[#This Row],[Flexibility RTM Analysis]]=1),INDEX(Definitions!$B$21:$B$37,MATCH(Table3[[#Headers],[Flexibility RTM Analysis]],Definitions!$A$21:$A$37,0)),Table3[[#This Row],[Flexibility RTM Analysis]]=0,0)} -> 10800 | AW14: {=_xlfn.IFS(AND(Table3[[#This Row],[Scale]:[Scale]]="Large",Table3[[#This Row],[Flexibility Forecasts]]=1),INDEX(Definitions!$C$21:$C$37,MATCH(Table3[[#Headers],[Flexibility Forecasts]],Definitions!$A$21:$A$37,0)),AND(Table3[[#This Row],[Scale]:[Scale]]="Small",Table3[[#This Row],[Flexibility Forecasts]]=1),INDEX(Definitions!$B$21:$B$37,MATCH(Table3[[#Headers],[Flexibility Forecasts]],Definitions!$A$21:$A$37,0)),Table3[[#This Row],[Flexibility Forecasts]]=0,0)} -> 44100 | AX14: {=_xlfn.IFS(AND(Table3[[#This Row],[Scale]:[Scale]]="Large",Table3[[#This Row],[Flexibility Regulation]]=1),INDEX(Definitions!$C$21:$C$37,MATCH(Table3[[#Headers],[Flexibility Regulation]],Definitions!$A$21:$A$37,0)),AND(Table3[[#This Row],[Scale]:[Scale]]="Small",Table3[[#This Row],[Flexibility Regulation]]=1),INDEX(Definitions!$B$21:$B$37,MATCH(Table3[[#Headers],[Flexibility Regulation]],Definitions!$A$21:$A$37,0)),Table3[[#This Row],[Flexibility Regulation]]=0,0)} -> 0 | AY14: {=_xlfn.IFS(AND(Table3[[#This Row],[Scale]:[Scale]]="Large",Table3[[#This Row],[Business Energy Essentials]]=1),INDEX(Definitions!$C$21:$C$37,MATCH(Table3[[#Headers],[Business Energy Essentials]],Definitions!$A$21:$A$37,0)),AND(Table3[[#This Row],[Scale]:[Scale]]="Small",Table3[[#This Row],[Business Energy Essentials]]=1),INDEX(Definitions!$B$21:$B$37,MATCH(Table3[[#Headers],[Business Energy Essentials]],Definitions!$A$21:$A$37,0)),Table3[[#This Row],[Business Energy Essentials]]=0,0)} -> 15300 | AZ14: {=_xlfn.IFS(AND(Table3[[#This Row],[Scale]:[Scale]]="Large",Table3[[#This Row],[Energy User RTM Analysis]]=1),INDEX(Definitions!$C$21:$C$37,MATCH(Table3[[#Headers],[Energy User RTM Analysis]],Definitions!$A$21:$A$37,0)),AND(Table3[[#This Row],[Scale]:[Scale]]="Small",Table3[[#This Row],[Energy User RTM Analysis]]=1),INDEX(Definitions!$B$21:$B$37,MATCH(Table3[[#Headers],[Energy User RTM Analysis]],Definitions!$A$21:$A$37,0)),Table3[[#This Row],[Energy User RTM Analysis]]=0,0)} -> 0 | BA14: {=_xlfn.IFS(AND(Table3[[#This Row],[Scale]:[Scale]]="Large",Table3[[#This Row],[Energy User Forecasts]]=1),INDEX(Definitions!$C$21:$C$37,MATCH(Table3[[#Headers],[Energy User Forecasts]],Definitions!$A$21:$A$37,0)),AND(Table3[[#This Row],[Scale]:[Scale]]="Small",Table3[[#This Row],[Energy User Forecasts]]=1),INDEX(Definitions!$B$21:$B$37,MATCH(Table3[[#Headers],[Energy User Forecasts]],Definitions!$A$21:$A$37,0)),Table3[[#This Row],[Energy User Forecasts]]=0,0)} -> 27000 | BB14: {=_xlfn.IFS(AND(Table3[[#This Row],[Scale]:[Scale]]="Large",Table3[[#This Row],[Energy User Regulation]]=1),INDEX(Definitions!$C$21:$C$37,MATCH(Table3[[#Headers],[Energy User Regulation]],Definitions!$A$21:$A$37,0)),AND(Table3[[#This Row],[Scale]:[Scale]]="Small",Table3[[#This Row],[Energy User Regulation]]=1),INDEX(Definitions!$B$21:$B$37,MATCH(Table3[[#Headers],[Energy User Regulation]],Definitions!$A$21:$A$37,0)),Table3[[#This Row],[Energy User Regulation]]=0,0)} -> 0 | BC14: =IF(SUM(Table3[[#This Row],[Column2]:[Column18]])>Table3[[#This Row],[Column19]],Table3[[#This Row],[Column19]],SUM(Table3[[#This Row],[Column2]:[Column18]])) -> 250000 | BD14: =Table3[[#This Row],[Total Spend]]/SUM(Table3[[#This Row],[Column2]:[Column18]]) -> 0.51156129
A15: Opus Energy | B15: Yes | D15: 45566 | E15: Large | F15: =INDEX(Definitions!$G$13:$G$17,MATCH(Table3[[#This Row],[Propensity to buy/ buyer readiness]],Definitions!$A$13:$A$17,0)) -> 250000 | G15: 5 | H15: 5 | I15: 5 | J15: 5 | K15: 5 | L15: =SUM(Table3[[#This Row],[Strategic priority segment]:[Propensity to buy/ buyer readiness]]) -> 25 | M15: Energy Supply | N15: Energy supplier | U15: 1 | V15: 1 | W15: 1 | X15: 1 | Y15: 1 | Z15: 0 | AA15: 0 | AB15: 0 | AC15: 0 | AD15: 1 | AE15: 0 | AF15: 0 | AG15: 0 | AH15: 0 | AI15: 0 | AJ15: 0 | AK15: 0 | AL15: {=_xlfn.IFS(AND(Table3[[#This Row],[Scale]:[Scale]]="Large",Table3[[#This Row],[Industry Essentials]]=1),INDEX(Definitions!$C$21:$C$37,MATCH(Table3[[#Headers],[Industry Essentials]],Definitions!$A$21:$A$37,0)),AND(Table3[[#This Row],[Scale]:[Scale]]="Small",Table3[[#This Row],[Industry Essentials]]=1),INDEX(Definitions!$B$21:$B$37,MATCH(Table3[[#Headers],[Industry Essentials]],Definitions!$A$21:$A$37,0)),Table3[[#This Row],[Industry Essentials]]=0,0)} -> 10800 | AM15: {=_xlfn.IFS(AND(Table3[[#This Row],[Scale]:[Scale]]="Large",Table3[[#This Row],[Energy Supply Market Intelligence]]=1),INDEX(Definitions!$C$21:$C$37,MATCH(Table3[[#Headers],[Energy Supply Market Intelligence]],Definitions!$A$21:$A$37,0)),AND(Table3[[#This Row],[Scale]:[Scale]]="Small",Table3[[#This Row],[Energy Supply Market Intelligence]]=1),INDEX(Definitions!$B$21:$B$37,MATCH(Table3[[#Headers],[Energy Supply Market Intelligence]],Definitions!$A$21:$A$37,0)),Table3[[#This Row],[Energy Supply Market Intelligence]]=0,0)} -> 43200 | AN15: {=_xlfn.IFS(AND(Table3[[#This Row],[Scale]:[Scale]]="Large",Table3[[#This Row],[Energy Supply RTM Analysis]]=1),INDEX(Definitions!$C$21:$C$37,MATCH(Table3[[#Headers],[Energy Supply RTM Analysis]],Definitions!$A$21:$A$37,0)),AND(Table3[[#This Row],[Scale]:[Scale]]="Small",Table3[[#This Row],[Energy Supply RTM Analysis]]=1),INDEX(Definitions!$B$21:$B$37,MATCH(Table3[[#Headers],[Energy Supply RTM Analysis]],Definitions!$A$21:$A$37,0)),Table3[[#This Row],[Energy Supply RTM Analysis]]=0,0)} -> 73800 | AO15: {=_xlfn.IFS(AND(Table3[[#This Row],[Scale]:[Scale]]="Large",Table3[[#This Row],[Energy Supply Forecasts]]=1),INDEX(Definitions!$C$21:$C$37,MATCH(Table3[[#Headers],[Energy Supply Forecasts]],Definitions!$A$21:$A$37,0)),AND(Table3[[#This Row],[Scale]:[Scale]]="Small",Table3[[#This Row],[Energy Supply Forecasts]]=1),INDEX(Definitions!$B$21:$B$37,MATCH(Table3[[#Headers],[Energy Supply Forecasts]],Definitions!$A$21:$A$37,0)),Table3[[#This Row],[Energy Supply Forecasts]]=0,0)} -> 48600 | AP15: {=_xlfn.IFS(AND(Table3[[#This Row],[Scale]:[Scale]]="Large",Table3[[#This Row],[Energy Supply Regulation]]=1),INDEX(Definitions!$C$21:$C$37,MATCH(Table3[[#Headers],[Energy Supply Regulation]],Definitions!$A$21:$A$37,0)),AND(Table3[[#This Row],[Scale]:[Scale]]="Small",Table3[[#This Row],[Energy Supply Regulation]]=1),INDEX(Definitions!$B$21:$B$37,MATCH(Table3[[#Headers],[Energy Supply Regulation]],Definitions!$A$21:$A$37,0)),Table3[[#This Row],[Energy Supply Regulation]]=0,0)} -> 55800 | AQ15: {=_xlfn.IFS(AND(Table3[[#This Row],[Scale]:[Scale]]="Large",Table3[[#This Row],[Renewables Market Intelligence]]=1),INDEX(Definitions!$C$21:$C$37,MATCH(Table3[[#Headers],[Renewables Market Intelligence]],Definitions!$A$21:$A$37,0)),AND(Table3[[#This Row],[Scale]:[Scale]]="Small",Table3[[#This Row],[Renewables Market Intelligence]]=1),INDEX(Definitions!$B$21:$B$37,MATCH(Table3[[#Headers],[Renewables Market Intelligence]],Definitions!$A$21:$A$37,0)),Table3[[#This Row],[Renewables Market Intelligence]]=0,0)} -> 0 | AR15: {=_xlfn.IFS(AND(Table3[[#This Row],[Scale]:[Scale]]="Large",Table3[[#This Row],[Renewables RTM Analysis]]=1),INDEX(Definitions!$C$21:$C$37,MATCH(Table3[[#Headers],[Renewables RTM Analysis]],Definitions!$A$21:$A$37,0)),AND(Table3[[#This Row],[Scale]:[Scale]]="Small",Table3[[#This Row],[Renewables RTM Analysis]]=1),INDEX(Definitions!$B$21:$B$37,MATCH(Table3[[#Headers],[Renewables RTM Analysis]],Definitions!$A$21:$A$37,0)),Table3[[#This Row],[Renewables RTM Analysis]]=0,0)} -> 0 | AS15: {=_xlfn.IFS(AND(Table3[[#This Row],[Scale]:[Scale]]="Large",Table3[[#This Row],[Renewables Forecasts]]=1),INDEX(Definitions!$C$21:$C$37,MATCH(Table3[[#Headers],[Renewables Forecasts]],Definitions!$A$21:$A$37,0)),AND(Table3[[#This Row],[Scale]:[Scale]]="Small",Table3[[#This Row],[Renewables Forecasts]]=1),INDEX(Definitions!$B$21:$B$37,MATCH(Table3[[#Headers],[Renewables Forecasts]],Definitions!$A$21:$A$37,0)),Table3[[#This Row],[Renewables Forecasts]]=0,0)} -> 0 | AT15: {=_xlfn.IFS(AND(Table3[[#This Row],[Scale]:[Scale]]="Large",Table3[[#This Row],[Renewables Regulation]]=1),INDEX(Definitions!$C$21:$C$37,MATCH(Table3[[#Headers],[Renewables Regulation]],Definitions!$A$21:$A$37,0)),AND(Table3[[#This Row],[Scale]:[Scale]]="Small",Table3[[#This Row],[Renewables Regulation]]=1),INDEX(Definitions!$B$21:$B$37,MATCH(Table3[[#Headers],[Renewables Regulation]],Definitions!$A$21:$A$37,0)),Table3[[#This Row],[Renewables Regulation]]=0,0)} -> 0 | AU15: {=_xlfn.IFS(AND(Table3[[#This Row],[Scale]:[Scale]]="Large",Table3[[#This Row],[Flexibility Market Intelligence]]=1),INDEX(Definitions!$C$21:$C$37,MATCH(Table3[[#Headers],[Flexibility Market Intelligence]],Definitions!$A$21:$A$37,0)),AND(Table3[[#This Row],[Scale]:[Scale]]="Small",Table3[[#This Row],[Flexibility Market Intelligence]]=1),INDEX(Definitions!$B$21:$B$37,MATCH(Table3[[#Headers],[Flexibility Market Intelligence]],Definitions!$A$21:$A$37,0)),Table3[[#This Row],[Flexibility Market Intelligence]]=0,0)} -> 29700 | AV15: {=_xlfn.IFS(AND(Table3[[#This Row],[Scale]:[Scale]]="Large",Table3[[#This Row],[Flexibility RTM Analysis]]=1),INDEX(Definitions!$C$21:$C$37,MATCH(Table3[[#Headers],[Flexibility RTM Analysis]],Definitions!$A$21:$A$37,0)),AND(Table3[[#This Row],[Scale]:[Scale]]="Small",Table3[[#This Row],[Flexibility RTM Analysis]]=1),INDEX(Definitions!$B$21:$B$37,MATCH(Table3[[#Headers],[Flexibility RTM Analysis]],Definitions!$A$21:$A$37,0)),Table3[[#This Row],[Flexibility RTM Analysis]]=0,0)} -> 0 | AW15: {=_xlfn.IFS(AND(Table3[[#This Row],[Scale]:[Scale]]="Large",Table3[[#This Row],[Flexibility Forecasts]]=1),INDEX(Definitions!$C$21:$C$37,MATCH(Table3[[#Headers],[Flexibility Forecasts]],Definitions!$A$21:$A$37,0)),AND(Table3[[#This Row],[Scale]:[Scale]]="Small",Table3[[#This Row],[Flexibility Forecasts]]=1),INDEX(Definitions!$B$21:$B$37,MATCH(Table3[[#Headers],[Flexibility Forecasts]],Definitions!$A$21:$A$37,0)),Table3[[#This Row],[Flexibility Forecasts]]=0,0)} -> 0 | AX15: {=_xlfn.IFS(AND(Table3[[#This Row],[Scale]:[Scale]]="Large",Table3[[#This Row],[Flexibility Regulation]]=1),INDEX(Definitions!$C$21:$C$37,MATCH(Table3[[#Headers],[Flexibility Regulation]],Definitions!$A$21:$A$37,0)),AND(Table3[[#This Row],[Scale]:[Scale]]="Small",Table3[[#This Row],[Flexibility Regulation]]=1),INDEX(Definitions!$B$21:$B$37,MATCH(Table3[[#Headers],[Flexibility Regulation]],Definitions!$A$21:$A$37,0)),Table3[[#This Row],[Flexibility Regulation]]=0,0)} -> 0 | AY15: {=_xlfn.IFS(AND(Table3[[#This Row],[Scale]:[Scale]]="Large",Table3[[#This Row],[Business Energy Essentials]]=1),INDEX(Definitions!$C$21:$C$37,MATCH(Table3[[#Headers],[Business Energy Essentials]],Definitions!$A$21:$A$37,0)),AND(Table3[[#This Row],[Scale]:[Scale]]="Small",Table3[[#This Row],[Business Energy Essentials]]=1),INDEX(Definitions!$B$21:$B$37,MATCH(Table3[[#Headers],[Business Energy Essentials]],Definitions!$A$21:$A$37,0)),Table3[[#This Row],[Business Energy Essentials]]=0,0)} -> 0 | AZ15: {=_xlfn.IFS(AND(Table3[[#This Row],[Scale]:[Scale]]="Large",Table3[[#This Row],[Energy User RTM Analysis]]=1),INDEX(Definitions!$C$21:$C$37,MATCH(Table3[[#Headers],[Energy User RTM Analysis]],Definitions!$A$21:$A$37,0)),AND(Table3[[#This Row],[Scale]:[Scale]]="Small",Table3[[#This Row],[Energy User RTM Analysis]]=1),INDEX(Definitions!$B$21:$B$37,MATCH(Table3[[#Headers],[Energy User RTM Analysis]],Definitions!$A$21:$A$37,0)),Table3[[#This Row],[Energy User RTM Analysis]]=0,0)} -> 0 | BA15: {=_xlfn.IFS(AND(Table3[[#This Row],[Scale]:[Scale]]="Large",Table3[[#This Row],[Energy User Forecasts]]=1),INDEX(Definitions!$C$21:$C$37,MATCH(Table3[[#Headers],[Energy User Forecasts]],Definitions!$A$21:$A$37,0)),AND(Table3[[#This Row],[Scale]:[Scale]]="Small",Table3[[#This Row],[Energy User Forecasts]]=1),INDEX(Definitions!$B$21:$B$37,MATCH(Table3[[#Headers],[Energy User Forecasts]],Definitions!$A$21:$A$37,0)),Table3[[#This Row],[Energy User Forecasts]]=0,0)} -> 0 | BB15: {=_xlfn.IFS(AND(Table3[[#This Row],[Scale]:[Scale]]="Large",Table3[[#This Row],[Energy User Regulation]]=1),INDEX(Definitions!$C$21:$C$37,MATCH(Table3[[#Headers],[Energy User Regulation]],Definitions!$A$21:$A$37,0)),AND(Table3[[#This Row],[Scale]:[Scale]]="Small",Table3[[#This Row],[Energy User Regulation]]=1),INDEX(Definitions!$B$21:$B$37,MATCH(Table3[[#Headers],[Energy User Regulation]],Definitions!$A$21:$A$37,0)),Table3[[#This Row],[Energy User Regulation]]=0,0)} -> 0 | BC15: =IF(SUM(Table3[[#This Row],[Column2]:[Column18]])>Table3[[#This Row],[Column19]],Table3[[#This Row],[Column19]],SUM(Table3[[#This Row],[Column2]:[Column18]])) -> 250000 | BD15: =Table3[[#This Row],[Total Spend]]/SUM(Table3[[#This Row],[Column2]:[Column18]]) -> 0.95456281
A16: OVO Energy Limited | B16: Yes | C16: Yes | D16: 45566 | E16: Large | F16: =INDEX(Definitions!$G$13:$G$17,MATCH(Table3[[#This Row],[Propensity to buy/ buyer readiness]],Definitions!$A$13:$A$17,0)) -> 250000 | G16: 5 | H16: 5 | I16: 5 | J16: 5 | K16: 5 | L16: =SUM(Table3[[#This Row],[Strategic priority segment]:[Propensity to buy/ buyer readiness]]) -> 25 | M16: Energy Supply | N16: Energy supplier | O16: E-mobility | P16: Energy traders | Q16: Renewables generator/developer | U16: 1 | V16: 1 | W16: 1 | X16: 1 | Y16: 1 | Z16: 1 | AA16: 1 | AB16: 1 | AC16: 1 | AD16: 1 | AE16: 1 | AF16: 1 | AG16: 0 | AH16: 1 | AI16: 0 | AJ16: 1 | AK16: 0 | AL16: {=_xlfn.IFS(AND(Table3[[#This Row],[Scale]:[Scale]]="Large",Table3[[#This Row],[Industry Essentials]]=1),INDEX(Definitions!$C$21:$C$37,MATCH(Table3[[#Headers],[Industry Essentials]],Definitions!$A$21:$A$37,0)),AND(Table3[[#This Row],[Scale]:[Scale]]="Small",Table3[[#This Row],[Industry Essentials]]=1),INDEX(Definitions!$B$21:$B$37,MATCH(Table3[[#Headers],[Industry Essentials]],Definitions!$A$21:$A$37,0)),Table3[[#This Row],[Industry Essentials]]=0,0)} -> 10800 | AM16: {=_xlfn.IFS(AND(Table3[[#This Row],[Scale]:[Scale]]="Large",Table3[[#This Row],[Energy Supply Market Intelligence]]=1),INDEX(Definitions!$C$21:$C$37,MATCH(Table3[[#Headers],[Energy Supply Market Intelligence]],Definitions!$A$21:$A$37,0)),AND(Table3[[#This Row],[Scale]:[Scale]]="Small",Table3[[#This Row],[Energy Supply Market Intelligence]]=1),INDEX(Definitions!$B$21:$B$37,MATCH(Table3[[#Headers],[Energy Supply Market Intelligence]],Definitions!$A$21:$A$37,0)),Table3[[#This Row],[Energy Supply Market Intelligence]]=0,0)} -> 43200 | AN16: {=_xlfn.IFS(AND(Table3[[#This Row],[Scale]:[Scale]]="Large",Table3[[#This Row],[Energy Supply RTM Analysis]]=1),INDEX(Definitions!$C$21:$C$37,MATCH(Table3[[#Headers],[Energy Supply RTM Analysis]],Definitions!$A$21:$A$37,0)),AND(Table3[[#This Row],[Scale]:[Scale]]="Small",Table3[[#This Row],[Energy Supply RTM Analysis]]=1),INDEX(Definitions!$B$21:$B$37,MATCH(Table3[[#Headers],[Energy Supply RTM Analysis]],Definitions!$A$21:$A$37,0)),Table3[[#This Row],[Energy Supply RTM Analysis]]=0,0)} -> 73800 | AO16: {=_xlfn.IFS(AND(Table3[[#This Row],[Scale]:[Scale]]="Large",Table3[[#This Row],[Energy Supply Forecasts]]=1),INDEX(Definitions!$C$21:$C$37,MATCH(Table3[[#Headers],[Energy Supply Forecasts]],Definitions!$A$21:$A$37,0)),AND(Table3[[#This Row],[Scale]:[Scale]]="Small",Table3[[#This Row],[Energy Supply Forecasts]]=1),INDEX(Definitions!$B$21:$B$37,MATCH(Table3[[#Headers],[Energy Supply Forecasts]],Definitions!$A$21:$A$37,0)),Table3[[#This Row],[Energy Supply Forecasts]]=0,0)} -> 48600 | AP16: {=_xlfn.IFS(AND(Table3[[#This Row],[Scale]:[Scale]]="Large",Table3[[#This Row],[Energy Supply Regulation]]=1),INDEX(Definitions!$C$21:$C$37,MATCH(Table3[[#Headers],[Energy Supply Regulation]],Definitions!$A$21:$A$37,0)),AND(Table3[[#This Row],[Scale]:[Scale]]="Small",Table3[[#This Row],[Energy Supply Regulation]]=1),INDEX(Definitions!$B$21:$B$37,MATCH(Table3[[#Headers],[Energy Supply Regulation]],Definitions!$A$21:$A$37,0)),Table3[[#This Row],[Energy Supply Regulation]]=0,0)} -> 55800 | AQ16: {=_xlfn.IFS(AND(Table3[[#This Row],[Scale]:[Scale]]="Large",Table3[[#This Row],[Renewables Market Intelligence]]=1),INDEX(Definitions!$C$21:$C$37,MATCH(Table3[[#Headers],[Renewables Market Intelligence]],Definitions!$A$21:$A$37,0)),AND(Table3[[#This Row],[Scale]:[Scale]]="Small",Table3[[#This Row],[Renewables Market Intelligence]]=1),INDEX(Definitions!$B$21:$B$37,MATCH(Table3[[#Headers],[Renewables Market Intelligence]],Definitions!$A$21:$A$37,0)),Table3[[#This Row],[Renewables Market Intelligence]]=0,0)} -> 23400 | AR16: {=_xlfn.IFS(AND(Table3[[#This Row],[Scale]:[Scale]]="Large",Table3[[#This Row],[Renewables RTM Analysis]]=1),INDEX(Definitions!$C$21:$C$37,MATCH(Table3[[#Headers],[Renewables RTM Analysis]],Definitions!$A$21:$A$37,0)),AND(Table3[[#This Row],[Scale]:[Scale]]="Small",Table3[[#This Row],[Renewables RTM Analysis]]=1),INDEX(Definitions!$B$21:$B$37,MATCH(Table3[[#Headers],[Renewables RTM Analysis]],Definitions!$A$21:$A$37,0)),Table3[[#This Row],[Renewables RTM Analysis]]=0,0)} -> 20700 | AS16: {=_xlfn.IFS(AND(Table3[[#This Row],[Scale]:[Scale]]="Large",Table3[[#This Row],[Renewables Forecasts]]=1),INDEX(Definitions!$C$21:$C$37,MATCH(Table3[[#Headers],[Renewables Forecasts]],Definitions!$A$21:$A$37,0)),AND(Table3[[#This Row],[Scale]:[Scale]]="Small",Table3[[#This Row],[Renewables Forecasts]]=1),INDEX(Definitions!$B$21:$B$37,MATCH(Table3[[#Headers],[Renewables Forecasts]],Definitions!$A$21:$A$37,0)),Table3[[#This Row],[Renewables Forecasts]]=0,0)} -> 59400 | AT16: {=_xlfn.IFS(AND(Table3[[#This Row],[Scale]:[Scale]]="Large",Table3[[#This Row],[Renewables Regulation]]=1),INDEX(Definitions!$C$21:$C$37,MATCH(Table3[[#Headers],[Renewables Regulation]],Definitions!$A$21:$A$37,0)),AND(Table3[[#This Row],[Scale]:[Scale]]="Small",Table3[[#This Row],[Renewables Regulation]]=1),INDEX(Definitions!$B$21:$B$37,MATCH(Table3[[#Headers],[Renewables Regulation]],Definitions!$A$21:$A$37,0)),Table3[[#This Row],[Renewables Regulation]]=0,0)} -> 26100 | AU16: {=_xlfn.IFS(AND(Table3[[#This Row],[Scale]:[Scale]]="Large",Table3[[#This Row],[Flexibility Market Intelligence]]=1),INDEX(Definitions!$C$21:$C$37,MATCH(Table3[[#Headers],[Flexibility Market Intelligence]],Definitions!$A$21:$A$37,0)),AND(Table3[[#This Row],[Scale]:[Scale]]="Small",Table3[[#This Row],[Flexibility Market Intelligence]]=1),INDEX(Definitions!$B$21:$B$37,MATCH(Table3[[#Headers],[Flexibility Market Intelligence]],Definitions!$A$21:$A$37,0)),Table3[[#This Row],[Flexibility Market Intelligence]]=0,0)} -> 29700 | AV16: {=_xlfn.IFS(AND(Table3[[#This Row],[Scale]:[Scale]]="Large",Table3[[#This Row],[Flexibility RTM Analysis]]=1),INDEX(Definitions!$C$21:$C$37,MATCH(Table3[[#Headers],[Flexibility RTM Analysis]],Definitions!$A$21:$A$37,0)),AND(Table3[[#This Row],[Scale]:[Scale]]="Small",Table3[[#This Row],[Flexibility RTM Analysis]]=1),INDEX(Definitions!$B$21:$B$37,MATCH(Table3[[#Headers],[Flexibility RTM Analysis]],Definitions!$A$21:$A$37,0)),Table3[[#This Row],[Flexibility RTM Analysis]]=0,0)} -> 10800 | AW16: {=_xlfn.IFS(AND(Table3[[#This Row],[Scale]:[Scale]]="Large",Table3[[#This Row],[Flexibility Forecasts]]=1),INDEX(Definitions!$C$21:$C$37,MATCH(Table3[[#Headers],[Flexibility Forecasts]],Definitions!$A$21:$A$37,0)),AND(Table3[[#This Row],[Scale]:[Scale]]="Small",Table3[[#This Row],[Flexibility Forecasts]]=1),INDEX(Definitions!$B$21:$B$37,MATCH(Table3[[#Headers],[Flexibility Forecasts]],Definitions!$A$21:$A$37,0)),Table3[[#This Row],[Flexibility Forecasts]]=0,0)} -> 44100 | AX16: {=_xlfn.IFS(AND(Table3[[#This Row],[Scale]:[Scale]]="Large",Table3[[#This Row],[Flexibility Regulation]]=1),INDEX(Definitions!$C$21:$C$37,MATCH(Table3[[#Headers],[Flexibility Regulation]],Definitions!$A$21:$A$37,0)),AND(Table3[[#This Row],[Scale]:[Scale]]="Small",Table3[[#This Row],[Flexibility Regulation]]=1),INDEX(Definitions!$B$21:$B$37,MATCH(Table3[[#Headers],[Flexibility Regulation]],Definitions!$A$21:$A$37,0)),Table3[[#This Row],[Flexibility Regulation]]=0,0)} -> 0 | AY16: {=_xlfn.IFS(AND(Table3[[#This Row],[Scale]:[Scale]]="Large",Table3[[#This Row],[Business Energy Essentials]]=1),INDEX(Definitions!$C$21:$C$37,MATCH(Table3[[#Headers],[Business Energy Essentials]],Definitions!$A$21:$A$37,0)),AND(Table3[[#This Row],[Scale]:[Scale]]="Small",Table3[[#This Row],[Business Energy Essentials]]=1),INDEX(Definitions!$B$21:$B$37,MATCH(Table3[[#Headers],[Business Energy Essentials]],Definitions!$A$21:$A$37,0)),Table3[[#This Row],[Business Energy Essentials]]=0,0)} -> 15300 | AZ16: {=_xlfn.IFS(AND(Table3[[#This Row],[Scale]:[Scale]]="Large",Table3[[#This Row],[Energy User RTM Analysis]]=1),INDEX(Definitions!$C$21:$C$37,MATCH(Table3[[#Headers],[Energy User RTM Analysis]],Definitions!$A$21:$A$37,0)),AND(Table3[[#This Row],[Scale]:[Scale]]="Small",Table3[[#This Row],[Energy User RTM Analysis]]=1),INDEX(Definitions!$B$21:$B$37,MATCH(Table3[[#Headers],[Energy User RTM Analysis]],Definitions!$A$21:$A$37,0)),Table3[[#This Row],[Energy User RTM Analysis]]=0,0)} -> 0 | BA16: {=_xlfn.IFS(AND(Table3[[#This Row],[Scale]:[Scale]]="Large",Table3[[#This Row],[Energy User Forecasts]]=1),INDEX(Definitions!$C$21:$C$37,MATCH(Table3[[#Headers],[Energy User Forecasts]],Definitions!$A$21:$A$37,0)),AND(Table3[[#This Row],[Scale]:[Scale]]="Small",Table3[[#This Row],[Energy User Forecasts]]=1),INDEX(Definitions!$B$21:$B$37,MATCH(Table3[[#Headers],[Energy User Forecasts]],Definitions!$A$21:$A$37,0)),Table3[[#This Row],[Energy User Forecasts]]=0,0)} -> 27000 | BB16: {=_xlfn.IFS(AND(Table3[[#This Row],[Scale]:[Scale]]="Large",Table3[[#This Row],[Energy User Regulation]]=1),INDEX(Definitions!$C$21:$C$37,MATCH(Table3[[#Headers],[Energy User Regulation]],Definitions!$A$21:$A$37,0)),AND(Table3[[#This Row],[Scale]:[Scale]]="Small",Table3[[#This Row],[Energy User Regulation]]=1),INDEX(Definitions!$B$21:$B$37,MATCH(Table3[[#Headers],[Energy User Regulation]],Definitions!$A$21:$A$37,0)),Table3[[#This Row],[Energy User Regulation]]=0,0)} -> 0 | BC16: =IF(SUM(Table3[[#This Row],[Column2]:[Column18]])>Table3[[#This Row],[Column19]],Table3[[#This Row],[Column19]],SUM(Table3[[#This Row],[Column2]:[Column18]])) -> 250000 | BD16: =Table3[[#This Row],[Total Spend]]/SUM(Table3[[#This Row],[Column2]:[Column18]]) -> 0.51156129
A17: RWE Supply & Trading GmbH | B17: Yes | D17: 45566 | E17: Large | F17: =INDEX(Definitions!$G$13:$G$17,MATCH(Table3[[#This Row],[Propensity to buy/ buyer readiness]],Definitions!$A$13:$A$17,0)) -> 250000 | G17: 5 | H17: 5 | I17: 5 | J17: 5 | K17: 5 | L17: =SUM(Table3[[#This Row],[Strategic priority segment]:[Propensity to buy/ buyer readiness]]) -> 25 | M17: Energy Supply | N17: Energy supplier | O17: Energy traders | U17: 1 | V17: 1 | W17: 1 | X17: 1 | Y17: 1 | Z17: 0 | AA17: 1 | AB17: 0 | AC17: 0 | AD17: 1 | AE17: 1 | AF17: 1 | AG17: 0 | AH17: 0 | AI17: 0 | AJ17: 0 | AK17: 0 | AL17: {=_xlfn.IFS(AND(Table3[[#This Row],[Scale]:[Scale]]="Large",Table3[[#This Row],[Industry Essentials]]=1),INDEX(Definitions!$C$21:$C$37,MATCH(Table3[[#Headers],[Industry Essentials]],Definitions!$A$21:$A$37,0)),AND(Table3[[#This Row],[Scale]:[Scale]]="Small",Table3[[#This Row],[Industry Essentials]]=1),INDEX(Definitions!$B$21:$B$37,MATCH(Table3[[#Headers],[Industry Essentials]],Definitions!$A$21:$A$37,0)),Table3[[#This Row],[Industry Essentials]]=0,0)} -> 10800 | AM17: {=_xlfn.IFS(AND(Table3[[#This Row],[Scale]:[Scale]]="Large",Table3[[#This Row],[Energy Supply Market Intelligence]]=1),INDEX(Definitions!$C$21:$C$37,MATCH(Table3[[#Headers],[Energy Supply Market Intelligence]],Definitions!$A$21:$A$37,0)),AND(Table3[[#This Row],[Scale]:[Scale]]="Small",Table3[[#This Row],[Energy Supply Market Intelligence]]=1),INDEX(Definitions!$B$21:$B$37,MATCH(Table3[[#Headers],[Energy Supply Market Intelligence]],Definitions!$A$21:$A$37,0)),Table3[[#This Row],[Energy Supply Market Intelligence]]=0,0)} -> 43200 | AN17: {=_xlfn.IFS(AND(Table3[[#This Row],[Scale]:[Scale]]="Large",Table3[[#This Row],[Energy Supply RTM Analysis]]=1),INDEX(Definitions!$C$21:$C$37,MATCH(Table3[[#Headers],[Energy Supply RTM Analysis]],Definitions!$A$21:$A$37,0)),AND(Table3[[#This Row],[Scale]:[Scale]]="Small",Table3[[#This Row],[Energy Supply RTM Analysis]]=1),INDEX(Definitions!$B$21:$B$37,MATCH(Table3[[#Headers],[Energy Supply RTM Analysis]],Definitions!$A$21:$A$37,0)),Table3[[#This Row],[Energy Supply RTM Analysis]]=0,0)} -> 73800 | AO17: {=_xlfn.IFS(AND(Table3[[#This Row],[Scale]:[Scale]]="Large",Table3[[#This Row],[Energy Supply Forecasts]]=1),INDEX(Definitions!$C$21:$C$37,MATCH(Table3[[#Headers],[Energy Supply Forecasts]],Definitions!$A$21:$A$37,0)),AND(Table3[[#This Row],[Scale]:[Scale]]="Small",Table3[[#This Row],[Energy Supply Forecasts]]=1),INDEX(Definitions!$B$21:$B$37,MATCH(Table3[[#Headers],[Energy Supply Forecasts]],Definitions!$A$21:$A$37,0)),Table3[[#This Row],[Energy Supply Forecasts]]=0,0)} -> 48600 | AP17: {=_xlfn.IFS(AND(Table3[[#This Row],[Scale]:[Scale]]="Large",Table3[[#This Row],[Energy Supply Regulation]]=1),INDEX(Definitions!$C$21:$C$37,MATCH(Table3[[#Headers],[Energy Supply Regulation]],Definitions!$A$21:$A$37,0)),AND(Table3[[#This Row],[Scale]:[Scale]]="Small",Table3[[#This Row],[Energy Supply Regulation]]=1),INDEX(Definitions!$B$21:$B$37,MATCH(Table3[[#Headers],[Energy Supply Regulation]],Definitions!$A$21:$A$37,0)),Table3[[#This Row],[Energy Supply Regulation]]=0,0)} -> 55800 | AQ17: {=_xlfn.IFS(AND(Table3[[#This Row],[Scale]:[Scale]]="Large",Table3[[#This Row],[Renewables Market Intelligence]]=1),INDEX(Definitions!$C$21:$C$37,MATCH(Table3[[#Headers],[Renewables Market Intelligence]],Definitions!$A$21:$A$37,0)),AND(Table3[[#This Row],[Scale]:[Scale]]="Small",Table3[[#This Row],[Renewables Market Intelligence]]=1),INDEX(Definitions!$B$21:$B$37,MATCH(Table3[[#Headers],[Renewables Market Intelligence]],Definitions!$A$21:$A$37,0)),Table3[[#This Row],[Renewables Market Intelligence]]=0,0)} -> 0 | AR17: {=_xlfn.IFS(AND(Table3[[#This Row],[Scale]:[Scale]]="Large",Table3[[#This Row],[Renewables RTM Analysis]]=1),INDEX(Definitions!$C$21:$C$37,MATCH(Table3[[#Headers],[Renewables RTM Analysis]],Definitions!$A$21:$A$37,0)),AND(Table3[[#This Row],[Scale]:[Scale]]="Small",Table3[[#This Row],[Renewables RTM Analysis]]=1),INDEX(Definitions!$B$21:$B$37,MATCH(Table3[[#Headers],[Renewables RTM Analysis]],Definitions!$A$21:$A$37,0)),Table3[[#This Row],[Renewables RTM Analysis]]=0,0)} -> 20700 | AS17: {=_xlfn.IFS(AND(Table3[[#This Row],[Scale]:[Scale]]="Large",Table3[[#This Row],[Renewables Forecasts]]=1),INDEX(Definitions!$C$21:$C$37,MATCH(Table3[[#Headers],[Renewables Forecasts]],Definitions!$A$21:$A$37,0)),AND(Table3[[#This Row],[Scale]:[Scale]]="Small",Table3[[#This Row],[Renewables Forecasts]]=1),INDEX(Definitions!$B$21:$B$37,MATCH(Table3[[#Headers],[Renewables Forecasts]],Definitions!$A$21:$A$37,0)),Table3[[#This Row],[Renewables Forecasts]]=0,0)} -> 0 | AT17: {=_xlfn.IFS(AND(Table3[[#This Row],[Scale]:[Scale]]="Large",Table3[[#This Row],[Renewables Regulation]]=1),INDEX(Definitions!$C$21:$C$37,MATCH(Table3[[#Headers],[Renewables Regulation]],Definitions!$A$21:$A$37,0)),AND(Table3[[#This Row],[Scale]:[Scale]]="Small",Table3[[#This Row],[Renewables Regulation]]=1),INDEX(Definitions!$B$21:$B$37,MATCH(Table3[[#Headers],[Renewables Regulation]],Definitions!$A$21:$A$37,0)),Table3[[#This Row],[Renewables Regulation]]=0,0)} -> 0 | AU17: {=_xlfn.IFS(AND(Table3[[#This Row],[Scale]:[Scale]]="Large",Table3[[#This Row],[Flexibility Market Intelligence]]=1),INDEX(Definitions!$C$21:$C$37,MATCH(Table3[[#Headers],[Flexibility Market Intelligence]],Definitions!$A$21:$A$37,0)),AND(Table3[[#This Row],[Scale]:[Scale]]="Small",Table3[[#This Row],[Flexibility Market Intelligence]]=1),INDEX(Definitions!$B$21:$B$37,MATCH(Table3[[#Headers],[Flexibility Market Intelligence]],Definitions!$A$21:$A$37,0)),Table3[[#This Row],[Flexibility Market Intelligence]]=0,0)} -> 29700 | AV17: {=_xlfn.IFS(AND(Table3[[#This Row],[Scale]:[Scale]]="Large",Table3[[#This Row],[Flexibility RTM Analysis]]=1),INDEX(Definitions!$C$21:$C$37,MATCH(Table3[[#Headers],[Flexibility RTM Analysis]],Definitions!$A$21:$A$37,0)),AND(Table3[[#This Row],[Scale]:[Scale]]="Small",Table3[[#This Row],[Flexibility RTM Analysis]]=1),INDEX(Definitions!$B$21:$B$37,MATCH(Table3[[#Headers],[Flexibility RTM Analysis]],Definitions!$A$21:$A$37,0)),Table3[[#This Row],[Flexibility RTM Analysis]]=0,0)} -> 10800 | AW17: {=_xlfn.IFS(AND(Table3[[#This Row],[Scale]:[Scale]]="Large",Table3[[#This Row],[Flexibility Forecasts]]=1),INDEX(Definitions!$C$21:$C$37,MATCH(Table3[[#Headers],[Flexibility Forecasts]],Definitions!$A$21:$A$37,0)),AND(Table3[[#This Row],[Scale]:[Scale]]="Small",Table3[[#This Row],[Flexibility Forecasts]]=1),INDEX(Definitions!$B$21:$B$37,MATCH(Table3[[#Headers],[Flexibility Forecasts]],Definitions!$A$21:$A$37,0)),Table3[[#This Row],[Flexibility Forecasts]]=0,0)} -> 44100 | AX17: {=_xlfn.IFS(AND(Table3[[#This Row],[Scale]:[Scale]]="Large",Table3[[#This Row],[Flexibility Regulation]]=1),INDEX(Definitions!$C$21:$C$37,MATCH(Table3[[#Headers],[Flexibility Regulation]],Definitions!$A$21:$A$37,0)),AND(Table3[[#This Row],[Scale]:[Scale]]="Small",Table3[[#This Row],[Flexibility Regulation]]=1),INDEX(Definitions!$B$21:$B$37,MATCH(Table3[[#Headers],[Flexibility Regulation]],Definitions!$A$21:$A$37,0)),Table3[[#This Row],[Flexibility Regulation]]=0,0)} -> 0 | AY17: {=_xlfn.IFS(AND(Table3[[#This Row],[Scale]:[Scale]]="Large",Table3[[#This Row],[Business Energy Essentials]]=1),INDEX(Definitions!$C$21:$C$37,MATCH(Table3[[#Headers],[Business Energy Essentials]],Definitions!$A$21:$A$37,0)),AND(Table3[[#This Row],[Scale]:[Scale]]="Small",Table3[[#This Row],[Business Energy Essentials]]=1),INDEX(Definitions!$B$21:$B$37,MATCH(Table3[[#Headers],[Business Energy Essentials]],Definitions!$A$21:$A$37,0)),Table3[[#This Row],[Business Energy Essentials]]=0,0)} -> 0 | AZ17: {=_xlfn.IFS(AND(Table3[[#This Row],[Scale]:[Scale]]="Large",Table3[[#This Row],[Energy User RTM Analysis]]=1),INDEX(Definitions!$C$21:$C$37,MATCH(Table3[[#Headers],[Energy User RTM Analysis]],Definitions!$A$21:$A$37,0)),AND(Table3[[#This Row],[Scale]:[Scale]]="Small",Table3[[#This Row],[Energy User RTM Analysis]]=1),INDEX(Definitions!$B$21:$B$37,MATCH(Table3[[#Headers],[Energy User RTM Analysis]],Definitions!$A$21:$A$37,0)),Table3[[#This Row],[Energy User RTM Analysis]]=0,0)} -> 0 | BA17: {=_xlfn.IFS(AND(Table3[[#This Row],[Scale]:[Scale]]="Large",Table3[[#This Row],[Energy User Forecasts]]=1),INDEX(Definitions!$C$21:$C$37,MATCH(Table3[[#Headers],[Energy User Forecasts]],Definitions!$A$21:$A$37,0)),AND(Table3[[#This Row],[Scale]:[Scale]]="Small",Table3[[#This Row],[Energy User Forecasts]]=1),INDEX(Definitions!$B$21:$B$37,MATCH(Table3[[#Headers],[Energy User Forecasts]],Definitions!$A$21:$A$37,0)),Table3[[#This Row],[Energy User Forecasts]]=0,0)} -> 0 | BB17: {=_xlfn.IFS(AND(Table3[[#This Row],[Scale]:[Scale]]="Large",Table3[[#This Row],[Energy User Regulation]]=1),INDEX(Definitions!$C$21:$C$37,MATCH(Table3[[#Headers],[Energy User Regulation]],Definitions!$A$21:$A$37,0)),AND(Table3[[#This Row],[Scale]:[Scale]]="Small",Table3[[#This Row],[Energy User Regulation]]=1),INDEX(Definitions!$B$21:$B$37,MATCH(Table3[[#Headers],[Energy User Regulation]],Definitions!$A$21:$A$37,0)),Table3[[#This Row],[Energy User Regulation]]=0,0)} -> 0 | BC17: =IF(SUM(Table3[[#This Row],[Column2]:[Column18]])>Table3[[#This Row],[Column19]],Table3[[#This Row],[Column19]],SUM(Table3[[#This Row],[Column2]:[Column18]])) -> 250000 | BD17: =Table3[[#This Row],[Total Spend]]/SUM(Table3[[#This Row],[Column2]:[Column18]]) -> 0.74074074
A18: ScottishPower Limited | B18: Yes | D18: 45566 | E18: Large | F18: =INDEX(Definitions!$G$13:$G$17,MATCH(Table3[[#This Row],[Propensity to buy/ buyer readiness]],Definitions!$A$13:$A$17,0)) -> 250000 | G18: 5 | H18: 5 | I18: 5 | J18: 5 | K18: 5 | L18: =SUM(Table3[[#This Row],[Strategic priority segment]:[Propensity to buy/ buyer readiness]]) -> 25 | M18: Energy Supply | N18: Energy supplier | U18: 1 | V18: 1 | W18: 1 | X18: 1 | Y18: 1 | Z18: 0 | AA18: 0 | AB18: 0 | AC18: 0 | AD18: 1 | AE18: 0 | AF18: 0 | AG18: 0 | AH18: 0 | AI18: 0 | AJ18: 0 | AK18: 0 | AL18: {=_xlfn.IFS(AND(Table3[[#This Row],[Scale]:[Scale]]="Large",Table3[[#This Row],[Industry Essentials]]=1),INDEX(Definitions!$C$21:$C$37,MATCH(Table3[[#Headers],[Industry Essentials]],Definitions!$A$21:$A$37,0)),AND(Table3[[#This Row],[Scale]:[Scale]]="Small",Table3[[#This Row],[Industry Essentials]]=1),INDEX(Definitions!$B$21:$B$37,MATCH(Table3[[#Headers],[Industry Essentials]],Definitions!$A$21:$A$37,0)),Table3[[#This Row],[Industry Essentials]]=0,0)} -> 10800 | AM18: {=_xlfn.IFS(AND(Table3[[#This Row],[Scale]:[Scale]]="Large",Table3[[#This Row],[Energy Supply Market Intelligence]]=1),INDEX(Definitions!$C$21:$C$37,MATCH(Table3[[#Headers],[Energy Supply Market Intelligence]],Definitions!$A$21:$A$37,0)),AND(Table3[[#This Row],[Scale]:[Scale]]="Small",Table3[[#This Row],[Energy Supply Market Intelligence]]=1),INDEX(Definitions!$B$21:$B$37,MATCH(Table3[[#Headers],[Energy Supply Market Intelligence]],Definitions!$A$21:$A$37,0)),Table3[[#This Row],[Energy Supply Market Intelligence]]=0,0)} -> 43200 | AN18: {=_xlfn.IFS(AND(Table3[[#This Row],[Scale]:[Scale]]="Large",Table3[[#This Row],[Energy Supply RTM Analysis]]=1),INDEX(Definitions!$C$21:$C$37,MATCH(Table3[[#Headers],[Energy Supply RTM Analysis]],Definitions!$A$21:$A$37,0)),AND(Table3[[#This Row],[Scale]:[Scale]]="Small",Table3[[#This Row],[Energy Supply RTM Analysis]]=1),INDEX(Definitions!$B$21:$B$37,MATCH(Table3[[#Headers],[Energy Supply RTM Analysis]],Definitions!$A$21:$A$37,0)),Table3[[#This Row],[Energy Supply RTM Analysis]]=0,0)} -> 73800 | AO18: {=_xlfn.IFS(AND(Table3[[#This Row],[Scale]:[Scale]]="Large",Table3[[#This Row],[Energy Supply Forecasts]]=1),INDEX(Definitions!$C$21:$C$37,MATCH(Table3[[#Headers],[Energy Supply Forecasts]],Definitions!$A$21:$A$37,0)),AND(Table3[[#This Row],[Scale]:[Scale]]="Small",Table3[[#This Row],[Energy Supply Forecasts]]=1),INDEX(Definitions!$B$21:$B$37,MATCH(Table3[[#Headers],[Energy Supply Forecasts]],Definitions!$A$21:$A$37,0)),Table3[[#This Row],[Energy Supply Forecasts]]=0,0)} -> 48600 | AP18: {=_xlfn.IFS(AND(Table3[[#This Row],[Scale]:[Scale]]="Large",Table3[[#This Row],[Energy Supply Regulation]]=1),INDEX(Definitions!$C$21:$C$37,MATCH(Table3[[#Headers],[Energy Supply Regulation]],Definitions!$A$21:$A$37,0)),AND(Table3[[#This Row],[Scale]:[Scale]]="Small",Table3[[#This Row],[Energy Supply Regulation]]=1),INDEX(Definitions!$B$21:$B$37,MATCH(Table3[[#Headers],[Energy Supply Regulation]],Definitions!$A$21:$A$37,0)),Table3[[#This Row],[Energy Supply Regulation]]=0,0)} -> 55800 | AQ18: {=_xlfn.IFS(AND(Table3[[#This Row],[Scale]:[Scale]]="Large",Table3[[#This Row],[Renewables Market Intelligence]]=1),INDEX(Definitions!$C$21:$C$37,MATCH(Table3[[#Headers],[Renewables Market Intelligence]],Definitions!$A$21:$A$37,0)),AND(Table3[[#This Row],[Scale]:[Scale]]="Small",Table3[[#This Row],[Renewables Market Intelligence]]=1),INDEX(Definitions!$B$21:$B$37,MATCH(Table3[[#Headers],[Renewables Market Intelligence]],Definitions!$A$21:$A$37,0)),Table3[[#This Row],[Renewables Market Intelligence]]=0,0)} -> 0 | AR18: {=_xlfn.IFS(AND(Table3[[#This Row],[Scale]:[Scale]]="Large",Table3[[#This Row],[Renewables RTM Analysis]]=1),INDEX(Definitions!$C$21:$C$37,MATCH(Table3[[#Headers],[Renewables RTM Analysis]],Definitions!$A$21:$A$37,0)),AND(Table3[[#This Row],[Scale]:[Scale]]="Small",Table3[[#This Row],[Renewables RTM Analysis]]=1),INDEX(Definitions!$B$21:$B$37,MATCH(Table3[[#Headers],[Renewables RTM Analysis]],Definitions!$A$21:$A$37,0)),Table3[[#This Row],[Renewables RTM Analysis]]=0,0)} -> 0 | AS18: {=_xlfn.IFS(AND(Table3[[#This Row],[Scale]:[Scale]]="Large",Table3[[#This Row],[Renewables Forecasts]]=1),INDEX(Definitions!$C$21:$C$37,MATCH(Table3[[#Headers],[Renewables Forecasts]],Definitions!$A$21:$A$37,0)),AND(Table3[[#This Row],[Scale]:[Scale]]="Small",Table3[[#This Row],[Renewables Forecasts]]=1),INDEX(Definitions!$B$21:$B$37,MATCH(Table3[[#Headers],[Renewables Forecasts]],Definitions!$A$21:$A$37,0)),Table3[[#This Row],[Renewables Forecasts]]=0,0)} -> 0 | AT18: {=_xlfn.IFS(AND(Table3[[#This Row],[Scale]:[Scale]]="Large",Table3[[#This Row],[Renewables Regulation]]=1),INDEX(Definitions!$C$21:$C$37,MATCH(Table3[[#Headers],[Renewables Regulation]],Definitions!$A$21:$A$37,0)),AND(Table3[[#This Row],[Scale]:[Scale]]="Small",Table3[[#This Row],[Renewables Regulation]]=1),INDEX(Definitions!$B$21:$B$37,MATCH(Table3[[#Headers],[Renewables Regulation]],Definitions!$A$21:$A$37,0)),Table3[[#This Row],[Renewables Regulation]]=0,0)} -> 0 | AU18: {=_xlfn.IFS(AND(Table3[[#This Row],[Scale]:[Scale]]="Large",Table3[[#This Row],[Flexibility Market Intelligence]]=1),INDEX(Definitions!$C$21:$C$37,MATCH(Table3[[#Headers],[Flexibility Market Intelligence]],Definitions!$A$21:$A$37,0)),AND(Table3[[#This Row],[Scale]:[Scale]]="Small",Table3[[#This Row],[Flexibility Market Intelligence]]=1),INDEX(Definitions!$B$21:$B$37,MATCH(Table3[[#Headers],[Flexibility Market Intelligence]],Definitions!$A$21:$A$37,0)),Table3[[#This Row],[Flexibility Market Intelligence]]=0,0)} -> 29700 | AV18: {=_xlfn.IFS(AND(Table3[[#This Row],[Scale]:[Scale]]="Large",Table3[[#This Row],[Flexibility RTM Analysis]]=1),INDEX(Definitions!$C$21:$C$37,MATCH(Table3[[#Headers],[Flexibility RTM Analysis]],Definitions!$A$21:$A$37,0)),AND(Table3[[#This Row],[Scale]:[Scale]]="Small",Table3[[#This Row],[Flexibility RTM Analysis]]=1),INDEX(Definitions!$B$21:$B$37,MATCH(Table3[[#Headers],[Flexibility RTM Analysis]],Definitions!$A$21:$A$37,0)),Table3[[#This Row],[Flexibility RTM Analysis]]=0,0)} -> 0 | AW18: {=_xlfn.IFS(AND(Table3[[#This Row],[Scale]:[Scale]]="Large",Table3[[#This Row],[Flexibility Forecasts]]=1),INDEX(Definitions!$C$21:$C$37,MATCH(Table3[[#Headers],[Flexibility Forecasts]],Definitions!$A$21:$A$37,0)),AND(Table3[[#This Row],[Scale]:[Scale]]="Small",Table3[[#This Row],[Flexibility Forecasts]]=1),INDEX(Definitions!$B$21:$B$37,MATCH(Table3[[#Headers],[Flexibility Forecasts]],Definitions!$A$21:$A$37,0)),Table3[[#This Row],[Flexibility Forecasts]]=0,0)} -> 0 | AX18: {=_xlfn.IFS(AND(Table3[[#This Row],[Scale]:[Scale]]="Large",Table3[[#This Row],[Flexibility Regulation]]=1),INDEX(Definitions!$C$21:$C$37,MATCH(Table3[[#Headers],[Flexibility Regulation]],Definitions!$A$21:$A$37,0)),AND(Table3[[#This Row],[Scale]:[Scale]]="Small",Table3[[#This Row],[Flexibility Regulation]]=1),INDEX(Definitions!$B$21:$B$37,MATCH(Table3[[#Headers],[Flexibility Regulation]],Definitions!$A$21:$A$37,0)),Table3[[#This Row],[Flexibility Regulation]]=0,0)} -> 0 | AY18: {=_xlfn.IFS(AND(Table3[[#This Row],[Scale]:[Scale]]="Large",Table3[[#This Row],[Business Energy Essentials]]=1),INDEX(Definitions!$C$21:$C$37,MATCH(Table3[[#Headers],[Business Energy Essentials]],Definitions!$A$21:$A$37,0)),AND(Table3[[#This Row],[Scale]:[Scale]]="Small",Table3[[#This Row],[Business Energy Essentials]]=1),INDEX(Definitions!$B$21:$B$37,MATCH(Table3[[#Headers],[Business Energy Essentials]],Definitions!$A$21:$A$37,0)),Table3[[#This Row],[Business Energy Essentials]]=0,0)} -> 0 | AZ18: {=_xlfn.IFS(AND(Table3[[#This Row],[Scale]:[Scale]]="Large",Table3[[#This Row],[Energy User RTM Analysis]]=1),INDEX(Definitions!$C$21:$C$37,MATCH(Table3[[#Headers],[Energy User RTM Analysis]],Definitions!$A$21:$A$37,0)),AND(Table3[[#This Row],[Scale]:[Scale]]="Small",Table3[[#This Row],[Energy User RTM Analysis]]=1),INDEX(Definitions!$B$21:$B$37,MATCH(Table3[[#Headers],[Energy User RTM Analysis]],Definitions!$A$21:$A$37,0)),Table3[[#This Row],[Energy User RTM Analysis]]=0,0)} -> 0 | BA18: {=_xlfn.IFS(AND(Table3[[#This Row],[Scale]:[Scale]]="Large",Table3[[#This Row],[Energy User Forecasts]]=1),INDEX(Definitions!$C$21:$C$37,MATCH(Table3[[#Headers],[Energy User Forecasts]],Definitions!$A$21:$A$37,0)),AND(Table3[[#This Row],[Scale]:[Scale]]="Small",Table3[[#This Row],[Energy User Forecasts]]=1),INDEX(Definitions!$B$21:$B$37,MATCH(Table3[[#Headers],[Energy User Forecasts]],Definitions!$A$21:$A$37,0)),Table3[[#This Row],[Energy User Forecasts]]=0,0)} -> 0 | BB18: {=_xlfn.IFS(AND(Table3[[#This Row],[Scale]:[Scale]]="Large",Table3[[#This Row],[Energy User Regulation]]=1),INDEX(Definitions!$C$21:$C$37,MATCH(Table3[[#Headers],[Energy User Regulation]],Definitions!$A$21:$A$37,0)),AND(Table3[[#This Row],[Scale]:[Scale]]="Small",Table3[[#This Row],[Energy User Regulation]]=1),INDEX(Definitions!$B$21:$B$37,MATCH(Table3[[#Headers],[Energy User Regulation]],Definitions!$A$21:$A$37,0)),Table3[[#This Row],[Energy User Regulation]]=0,0)} -> 0 | BC18: =IF(SUM(Table3[[#This Row],[Column2]:[Column18]])>Table3[[#This Row],[Column19]],Table3[[#This Row],[Column19]],SUM(Table3[[#This Row],[Column2]:[Column18]])) -> 250000 | BD18: =Table3[[#This Row],[Total Spend]]/SUM(Table3[[#This Row],[Column2]:[Column18]]) -> 0.95456281
A19: SEFE Energy Ltd | B19: Yes | D19: 45566 | E19: Large | F19: =INDEX(Definitions!$G$13:$G$17,MATCH(Table3[[#This Row],[Propensity to buy/ buyer readiness]],Definitions!$A$13:$A$17,0)) -> 250000 | G19: 5 | H19: 5 | I19: 5 | J19: 5 | K19: 5 | L19: =SUM(Table3[[#This Row],[Strategic priority segment]:[Propensity to buy/ buyer readiness]]) -> 25 | M19: Energy Supply | N19: Energy supplier | O19: Energy traders | U19: 1 | V19: 1 | W19: 1 | X19: 1 | Y19: 1 | Z19: 0 | AA19: 1 | AB19: 0 | AC19: 0 | AD19: 1 | AE19: 1 | AF19: 1 | AG19: 0 | AH19: 0 | AI19: 0 | AJ19: 0 | AK19: 0 | AL19: {=_xlfn.IFS(AND(Table3[[#This Row],[Scale]:[Scale]]="Large",Table3[[#This Row],[Industry Essentials]]=1),INDEX(Definitions!$C$21:$C$37,MATCH(Table3[[#Headers],[Industry Essentials]],Definitions!$A$21:$A$37,0)),AND(Table3[[#This Row],[Scale]:[Scale]]="Small",Table3[[#This Row],[Industry Essentials]]=1),INDEX(Definitions!$B$21:$B$37,MATCH(Table3[[#Headers],[Industry Essentials]],Definitions!$A$21:$A$37,0)),Table3[[#This Row],[Industry Essentials]]=0,0)} -> 10800 | AM19: {=_xlfn.IFS(AND(Table3[[#This Row],[Scale]:[Scale]]="Large",Table3[[#This Row],[Energy Supply Market Intelligence]]=1),INDEX(Definitions!$C$21:$C$37,MATCH(Table3[[#Headers],[Energy Supply Market Intelligence]],Definitions!$A$21:$A$37,0)),AND(Table3[[#This Row],[Scale]:[Scale]]="Small",Table3[[#This Row],[Energy Supply Market Intelligence]]=1),INDEX(Definitions!$B$21:$B$37,MATCH(Table3[[#Headers],[Energy Supply Market Intelligence]],Definitions!$A$21:$A$37,0)),Table3[[#This Row],[Energy Supply Market Intelligence]]=0,0)} -> 43200 | AN19: {=_xlfn.IFS(AND(Table3[[#This Row],[Scale]:[Scale]]="Large",Table3[[#This Row],[Energy Supply RTM Analysis]]=1),INDEX(Definitions!$C$21:$C$37,MATCH(Table3[[#Headers],[Energy Supply RTM Analysis]],Definitions!$A$21:$A$37,0)),AND(Table3[[#This Row],[Scale]:[Scale]]="Small",Table3[[#This Row],[Energy Supply RTM Analysis]]=1),INDEX(Definitions!$B$21:$B$37,MATCH(Table3[[#Headers],[Energy Supply RTM Analysis]],Definitions!$A$21:$A$37,0)),Table3[[#This Row],[Energy Supply RTM Analysis]]=0,0)} -> 73800 | AO19: {=_xlfn.IFS(AND(Table3[[#This Row],[Scale]:[Scale]]="Large",Table3[[#This Row],[Energy Supply Forecasts]]=1),INDEX(Definitions!$C$21:$C$37,MATCH(Table3[[#Headers],[Energy Supply Forecasts]],Definitions!$A$21:$A$37,0)),AND(Table3[[#This Row],[Scale]:[Scale]]="Small",Table3[[#This Row],[Energy Supply Forecasts]]=1),INDEX(Definitions!$B$21:$B$37,MATCH(Table3[[#Headers],[Energy Supply Forecasts]],Definitions!$A$21:$A$37,0)),Table3[[#This Row],[Energy Supply Forecasts]]=0,0)} -> 48600 | AP19: {=_xlfn.IFS(AND(Table3[[#This Row],[Scale]:[Scale]]="Large",Table3[[#This Row],[Energy Supply Regulation]]=1),INDEX(Definitions!$C$21:$C$37,MATCH(Table3[[#Headers],[Energy Supply Regulation]],Definitions!$A$21:$A$37,0)),AND(Table3[[#This Row],[Scale]:[Scale]]="Small",Table3[[#This Row],[Energy Supply Regulation]]=1),INDEX(Definitions!$B$21:$B$37,MATCH(Table3[[#Headers],[Energy Supply Regulation]],Definitions!$A$21:$A$37,0)),Table3[[#This Row],[Energy Supply Regulation]]=0,0)} -> 55800 | AQ19: {=_xlfn.IFS(AND(Table3[[#This Row],[Scale]:[Scale]]="Large",Table3[[#This Row],[Renewables Market Intelligence]]=1),INDEX(Definitions!$C$21:$C$37,MATCH(Table3[[#Headers],[Renewables Market Intelligence]],Definitions!$A$21:$A$37,0)),AND(Table3[[#This Row],[Scale]:[Scale]]="Small",Table3[[#This Row],[Renewables Market Intelligence]]=1),INDEX(Definitions!$B$21:$B$37,MATCH(Table3[[#Headers],[Renewables Market Intelligence]],Definitions!$A$21:$A$37,0)),Table3[[#This Row],[Renewables Market Intelligence]]=0,0)} -> 0 | AR19: {=_xlfn.IFS(AND(Table3[[#This Row],[Scale]:[Scale]]="Large",Table3[[#This Row],[Renewables RTM Analysis]]=1),INDEX(Definitions!$C$21:$C$37,MATCH(Table3[[#Headers],[Renewables RTM Analysis]],Definitions!$A$21:$A$37,0)),AND(Table3[[#This Row],[Scale]:[Scale]]="Small",Table3[[#This Row],[Renewables RTM Analysis]]=1),INDEX(Definitions!$B$21:$B$37,MATCH(Table3[[#Headers],[Renewables RTM Analysis]],Definitions!$A$21:$A$37,0)),Table3[[#This Row],[Renewables RTM Analysis]]=0,0)} -> 20700 | AS19: {=_xlfn.IFS(AND(Table3[[#This Row],[Scale]:[Scale]]="Large",Table3[[#This Row],[Renewables Forecasts]]=1),INDEX(Definitions!$C$21:$C$37,MATCH(Table3[[#Headers],[Renewables Forecasts]],Definitions!$A$21:$A$37,0)),AND(Table3[[#This Row],[Scale]:[Scale]]="Small",Table3[[#This Row],[Renewables Forecasts]]=1),INDEX(Definitions!$B$21:$B$37,MATCH(Table3[[#Headers],[Renewables Forecasts]],Definitions!$A$21:$A$37,0)),Table3[[#This Row],[Renewables Forecasts]]=0,0)} -> 0 | AT19: {=_xlfn.IFS(AND(Table3[[#This Row],[Scale]:[Scale]]="Large",Table3[[#This Row],[Renewables Regulation]]=1),INDEX(Definitions!$C$21:$C$37,MATCH(Table3[[#Headers],[Renewables Regulation]],Definitions!$A$21:$A$37,0)),AND(Table3[[#This Row],[Scale]:[Scale]]="Small",Table3[[#This Row],[Renewables Regulation]]=1),INDEX(Definitions!$B$21:$B$37,MATCH(Table3[[#Headers],[Renewables Regulation]],Definitions!$A$21:$A$37,0)),Table3[[#This Row],[Renewables Regulation]]=0,0)} -> 0 | AU19: {=_xlfn.IFS(AND(Table3[[#This Row],[Scale]:[Scale]]="Large",Table3[[#This Row],[Flexibility Market Intelligence]]=1),INDEX(Definitions!$C$21:$C$37,MATCH(Table3[[#Headers],[Flexibility Market Intelligence]],Definitions!$A$21:$A$37,0)),AND(Table3[[#This Row],[Scale]:[Scale]]="Small",Table3[[#This Row],[Flexibility Market Intelligence]]=1),INDEX(Definitions!$B$21:$B$37,MATCH(Table3[[#Headers],[Flexibility Market Intelligence]],Definitions!$A$21:$A$37,0)),Table3[[#This Row],[Flexibility Market Intelligence]]=0,0)} -> 29700 | AV19: {=_xlfn.IFS(AND(Table3[[#This Row],[Scale]:[Scale]]="Large",Table3[[#This Row],[Flexibility RTM Analysis]]=1),INDEX(Definitions!$C$21:$C$37,MATCH(Table3[[#Headers],[Flexibility RTM Analysis]],Definitions!$A$21:$A$37,0)),AND(Table3[[#This Row],[Scale]:[Scale]]="Small",Table3[[#This Row],[Flexibility RTM Analysis]]=1),INDEX(Definitions!$B$21:$B$37,MATCH(Table3[[#Headers],[Flexibility RTM Analysis]],Definitions!$A$21:$A$37,0)),Table3[[#This Row],[Flexibility RTM Analysis]]=0,0)} -> 10800 | AW19: {=_xlfn.IFS(AND(Table3[[#This Row],[Scale]:[Scale]]="Large",Table3[[#This Row],[Flexibility Forecasts]]=1),INDEX(Definitions!$C$21:$C$37,MATCH(Table3[[#Headers],[Flexibility Forecasts]],Definitions!$A$21:$A$37,0)),AND(Table3[[#This Row],[Scale]:[Scale]]="Small",Table3[[#This Row],[Flexibility Forecasts]]=1),INDEX(Definitions!$B$21:$B$37,MATCH(Table3[[#Headers],[Flexibility Forecasts]],Definitions!$A$21:$A$37,0)),Table3[[#This Row],[Flexibility Forecasts]]=0,0)} -> 44100 | AX19: {=_xlfn.IFS(AND(Table3[[#This Row],[Scale]:[Scale]]="Large",Table3[[#This Row],[Flexibility Regulation]]=1),INDEX(Definitions!$C$21:$C$37,MATCH(Table3[[#Headers],[Flexibility Regulation]],Definitions!$A$21:$A$37,0)),AND(Table3[[#This Row],[Scale]:[Scale]]="Small",Table3[[#This Row],[Flexibility Regulation]]=1),INDEX(Definitions!$B$21:$B$37,MATCH(Table3[[#Headers],[Flexibility Regulation]],Definitions!$A$21:$A$37,0)),Table3[[#This Row],[Flexibility Regulation]]=0,0)} -> 0 | AY19: {=_xlfn.IFS(AND(Table3[[#This Row],[Scale]:[Scale]]="Large",Table3[[#This Row],[Business Energy Essentials]]=1),INDEX(Definitions!$C$21:$C$37,MATCH(Table3[[#Headers],[Business Energy Essentials]],Definitions!$A$21:$A$37,0)),AND(Table3[[#This Row],[Scale]:[Scale]]="Small",Table3[[#This Row],[Business Energy Essentials]]=1),INDEX(Definitions!$B$21:$B$37,MATCH(Table3[[#Headers],[Business Energy Essentials]],Definitions!$A$21:$A$37,0)),Table3[[#This Row],[Business Energy Essentials]]=0,0)} -> 0 | AZ19: {=_xlfn.IFS(AND(Table3[[#This Row],[Scale]:[Scale]]="Large",Table3[[#This Row],[Energy User RTM Analysis]]=1),INDEX(Definitions!$C$21:$C$37,MATCH(Table3[[#Headers],[Energy User RTM Analysis]],Definitions!$A$21:$A$37,0)),AND(Table3[[#This Row],[Scale]:[Scale]]="Small",Table3[[#This Row],[Energy User RTM Analysis]]=1),INDEX(Definitions!$B$21:$B$37,MATCH(Table3[[#Headers],[Energy User RTM Analysis]],Definitions!$A$21:$A$37,0)),Table3[[#This Row],[Energy User RTM Analysis]]=0,0)} -> 0 | BA19: {=_xlfn.IFS(AND(Table3[[#This Row],[Scale]:[Scale]]="Large",Table3[[#This Row],[Energy User Forecasts]]=1),INDEX(Definitions!$C$21:$C$37,MATCH(Table3[[#Headers],[Energy User Forecasts]],Definitions!$A$21:$A$37,0)),AND(Table3[[#This Row],[Scale]:[Scale]]="Small",Table3[[#This Row],[Energy User Forecasts]]=1),INDEX(Definitions!$B$21:$B$37,MATCH(Table3[[#Headers],[Energy User Forecasts]],Definitions!$A$21:$A$37,0)),Table3[[#This Row],[Energy User Forecasts]]=0,0)} -> 0 | BB19: {=_xlfn.IFS(AND(Table3[[#This Row],[Scale]:[Scale]]="Large",Table3[[#This Row],[Energy User Regulation]]=1),INDEX(Definitions!$C$21:$C$37,MATCH(Table3[[#Headers],[Energy User Regulation]],Definitions!$A$21:$A$37,0)),AND(Table3[[#This Row],[Scale]:[Scale]]="Small",Table3[[#This Row],[Energy User Regulation]]=1),INDEX(Definitions!$B$21:$B$37,MATCH(Table3[[#Headers],[Energy User Regulation]],Definitions!$A$21:$A$37,0)),Table3[[#This Row],[Energy User Regulation]]=0,0)} -> 0 | BC19: =IF(SUM(Table3[[#This Row],[Column2]:[Column18]])>Table3[[#This Row],[Column19]],Table3[[#This Row],[Column19]],SUM(Table3[[#This Row],[Column2]:[Column18]])) -> 250000 | BD19: =Table3[[#This Row],[Total Spend]]/SUM(Table3[[#This Row],[Column2]:[Column18]]) -> 0.74074074
A20: Shell Energy Retail Ltd | B20: Yes | D20: 45566 | E20: Large | F20: =INDEX(Definitions!$G$13:$G$17,MATCH(Table3[[#This Row],[Propensity to buy/ buyer readiness]],Definitions!$A$13:$A$17,0)) -> 250000 | G20: 5 | H20: 5 | I20: 5 | J20: 5 | K20: 5 | L20: =SUM(Table3[[#This Row],[Strategic priority segment]:[Propensity to buy/ buyer readiness]]) -> 25 | M20: Energy Supply | N20: Energy supplier | U20: 1 | V20: 1 | W20: 1 | X20: 1 | Y20: 1 | Z20: 0 | AA20: 0 | AB20: 0 | AC20: 0 | AD20: 1 | AE20: 0 | AF20: 0 | AG20: 0 | AH20: 0 | AI20: 0 | AJ20: 0 | AK20: 0 | AL20: {=_xlfn.IFS(AND(Table3[[#This Row],[Scale]:[Scale]]="Large",Table3[[#This Row],[Industry Essentials]]=1),INDEX(Definitions!$C$21:$C$37,MATCH(Table3[[#Headers],[Industry Essentials]],Definitions!$A$21:$A$37,0)),AND(Table3[[#This Row],[Scale]:[Scale]]="Small",Table3[[#This Row],[Industry Essentials]]=1),INDEX(Definitions!$B$21:$B$37,MATCH(Table3[[#Headers],[Industry Essentials]],Definitions!$A$21:$A$37,0)),Table3[[#This Row],[Industry Essentials]]=0,0)} -> 10800 | AM20: {=_xlfn.IFS(AND(Table3[[#This Row],[Scale]:[Scale]]="Large",Table3[[#This Row],[Energy Supply Market Intelligence]]=1),INDEX(Definitions!$C$21:$C$37,MATCH(Table3[[#Headers],[Energy Supply Market Intelligence]],Definitions!$A$21:$A$37,0)),AND(Table3[[#This Row],[Scale]:[Scale]]="Small",Table3[[#This Row],[Energy Supply Market Intelligence]]=1),INDEX(Definitions!$B$21:$B$37,MATCH(Table3[[#Headers],[Energy Supply Market Intelligence]],Definitions!$A$21:$A$37,0)),Table3[[#This Row],[Energy Supply Market Intelligence]]=0,0)} -> 43200 | AN20: {=_xlfn.IFS(AND(Table3[[#This Row],[Scale]:[Scale]]="Large",Table3[[#This Row],[Energy Supply RTM Analysis]]=1),INDEX(Definitions!$C$21:$C$37,MATCH(Table3[[#Headers],[Energy Supply RTM Analysis]],Definitions!$A$21:$A$37,0)),AND(Table3[[#This Row],[Scale]:[Scale]]="Small",Table3[[#This Row],[Energy Supply RTM Analysis]]=1),INDEX(Definitions!$B$21:$B$37,MATCH(Table3[[#Headers],[Energy Supply RTM Analysis]],Definitions!$A$21:$A$37,0)),Table3[[#This Row],[Energy Supply RTM Analysis]]=0,0)} -> 73800 | AO20: {=_xlfn.IFS(AND(Table3[[#This Row],[Scale]:[Scale]]="Large",Table3[[#This Row],[Energy Supply Forecasts]]=1),INDEX(Definitions!$C$21:$C$37,MATCH(Table3[[#Headers],[Energy Supply Forecasts]],Definitions!$A$21:$A$37,0)),AND(Table3[[#This Row],[Scale]:[Scale]]="Small",Table3[[#This Row],[Energy Supply Forecasts]]=1),INDEX(Definitions!$B$21:$B$37,MATCH(Table3[[#Headers],[Energy Supply Forecasts]],Definitions!$A$21:$A$37,0)),Table3[[#This Row],[Energy Supply Forecasts]]=0,0)} -> 48600 | AP20: {=_xlfn.IFS(AND(Table3[[#This Row],[Scale]:[Scale]]="Large",Table3[[#This Row],[Energy Supply Regulation]]=1),INDEX(Definitions!$C$21:$C$37,MATCH(Table3[[#Headers],[Energy Supply Regulation]],Definitions!$A$21:$A$37,0)),AND(Table3[[#This Row],[Scale]:[Scale]]="Small",Table3[[#This Row],[Energy Supply Regulation]]=1),INDEX(Definitions!$B$21:$B$37,MATCH(Table3[[#Headers],[Energy Supply Regulation]],Definitions!$A$21:$A$37,0)),Table3[[#This Row],[Energy Supply Regulation]]=0,0)} -> 55800 | AQ20: {=_xlfn.IFS(AND(Table3[[#This Row],[Scale]:[Scale]]="Large",Table3[[#This Row],[Renewables Market Intelligence]]=1),INDEX(Definitions!$C$21:$C$37,MATCH(Table3[[#Headers],[Renewables Market Intelligence]],Definitions!$A$21:$A$37,0)),AND(Table3[[#This Row],[Scale]:[Scale]]="Small",Table3[[#This Row],[Renewables Market Intelligence]]=1),INDEX(Definitions!$B$21:$B$37,MATCH(Table3[[#Headers],[Renewables Market Intelligence]],Definitions!$A$21:$A$37,0)),Table3[[#This Row],[Renewables Market Intelligence]]=0,0)} -> 0 | AR20: {=_xlfn.IFS(AND(Table3[[#This Row],[Scale]:[Scale]]="Large",Table3[[#This Row],[Renewables RTM Analysis]]=1),INDEX(Definitions!$C$21:$C$37,MATCH(Table3[[#Headers],[Renewables RTM Analysis]],Definitions!$A$21:$A$37,0)),AND(Table3[[#This Row],[Scale]:[Scale]]="Small",Table3[[#This Row],[Renewables RTM Analysis]]=1),INDEX(Definitions!$B$21:$B$37,MATCH(Table3[[#Headers],[Renewables RTM Analysis]],Definitions!$A$21:$A$37,0)),Table3[[#This Row],[Renewables RTM Analysis]]=0,0)} -> 0 | AS20: {=_xlfn.IFS(AND(Table3[[#This Row],[Scale]:[Scale]]="Large",Table3[[#This Row],[Renewables Forecasts]]=1),INDEX(Definitions!$C$21:$C$37,MATCH(Table3[[#Headers],[Renewables Forecasts]],Definitions!$A$21:$A$37,0)),AND(Table3[[#This Row],[Scale]:[Scale]]="Small",Table3[[#This Row],[Renewables Forecasts]]=1),INDEX(Definitions!$B$21:$B$37,MATCH(Table3[[#Headers],[Renewables Forecasts]],Definitions!$A$21:$A$37,0)),Table3[[#This Row],[Renewables Forecasts]]=0,0)} -> 0 | AT20: {=_xlfn.IFS(AND(Table3[[#This Row],[Scale]:[Scale]]="Large",Table3[[#This Row],[Renewables Regulation]]=1),INDEX(Definitions!$C$21:$C$37,MATCH(Table3[[#Headers],[Renewables Regulation]],Definitions!$A$21:$A$37,0)),AND(Table3[[#This Row],[Scale]:[Scale]]="Small",Table3[[#This Row],[Renewables Regulation]]=1),INDEX(Definitions!$B$21:$B$37,MATCH(Table3[[#Headers],[Renewables Regulation]],Definitions!$A$21:$A$37,0)),Table3[[#This Row],[Renewables Regulation]]=0,0)} -> 0 | AU20: {=_xlfn.IFS(AND(Table3[[#This Row],[Scale]:[Scale]]="Large",Table3[[#This Row],[Flexibility Market Intelligence]]=1),INDEX(Definitions!$C$21:$C$37,MATCH(Table3[[#Headers],[Flexibility Market Intelligence]],Definitions!$A$21:$A$37,0)),AND(Table3[[#This Row],[Scale]:[Scale]]="Small",Table3[[#This Row],[Flexibility Market Intelligence]]=1),INDEX(Definitions!$B$21:$B$37,MATCH(Table3[[#Headers],[Flexibility Market Intelligence]],Definitions!$A$21:$A$37,0)),Table3[[#This Row],[Flexibility Market Intelligence]]=0,0)} -> 29700 | AV20: {=_xlfn.IFS(AND(Table3[[#This Row],[Scale]:[Scale]]="Large",Table3[[#This Row],[Flexibility RTM Analysis]]=1),INDEX(Definitions!$C$21:$C$37,MATCH(Table3[[#Headers],[Flexibility RTM Analysis]],Definitions!$A$21:$A$37,0)),AND(Table3[[#This Row],[Scale]:[Scale]]="Small",Table3[[#This Row],[Flexibility RTM Analysis]]=1),INDEX(Definitions!$B$21:$B$37,MATCH(Table3[[#Headers],[Flexibility RTM Analysis]],Definitions!$A$21:$A$37,0)),Table3[[#This Row],[Flexibility RTM Analysis]]=0,0)} -> 0 | AW20: {=_xlfn.IFS(AND(Table3[[#This Row],[Scale]:[Scale]]="Large",Table3[[#This Row],[Flexibility Forecasts]]=1),INDEX(Definitions!$C$21:$C$37,MATCH(Table3[[#Headers],[Flexibility Forecasts]],Definitions!$A$21:$A$37,0)),AND(Table3[[#This Row],[Scale]:[Scale]]="Small",Table3[[#This Row],[Flexibility Forecasts]]=1),INDEX(Definitions!$B$21:$B$37,MATCH(Table3[[#Headers],[Flexibility Forecasts]],Definitions!$A$21:$A$37,0)),Table3[[#This Row],[Flexibility Forecasts]]=0,0)} -> 0 | AX20: {=_xlfn.IFS(AND(Table3[[#This Row],[Scale]:[Scale]]="Large",Table3[[#This Row],[Flexibility Regulation]]=1),INDEX(Definitions!$C$21:$C$37,MATCH(Table3[[#Headers],[Flexibility Regulation]],Definitions!$A$21:$A$37,0)),AND(Table3[[#This Row],[Scale]:[Scale]]="Small",Table3[[#This Row],[Flexibility Regulation]]=1),INDEX(Definitions!$B$21:$B$37,MATCH(Table3[[#Headers],[Flexibility Regulation]],Definitions!$A$21:$A$37,0)),Table3[[#This Row],[Flexibility Regulation]]=0,0)} -> 0 | AY20: {=_xlfn.IFS(AND(Table3[[#This Row],[Scale]:[Scale]]="Large",Table3[[#This Row],[Business Energy Essentials]]=1),INDEX(Definitions!$C$21:$C$37,MATCH(Table3[[#Headers],[Business Energy Essentials]],Definitions!$A$21:$A$37,0)),AND(Table3[[#This Row],[Scale]:[Scale]]="Small",Table3[[#This Row],[Business Energy Essentials]]=1),INDEX(Definitions!$B$21:$B$37,MATCH(Table3[[#Headers],[Business Energy Essentials]],Definitions!$A$21:$A$37,0)),Table3[[#This Row],[Business Energy Essentials]]=0,0)} -> 0 | AZ20: {=_xlfn.IFS(AND(Table3[[#This Row],[Scale]:[Scale]]="Large",Table3[[#This Row],[Energy User RTM Analysis]]=1),INDEX(Definitions!$C$21:$C$37,MATCH(Table3[[#Headers],[Energy User RTM Analysis]],Definitions!$A$21:$A$37,0)),AND(Table3[[#This Row],[Scale]:[Scale]]="Small",Table3[[#This Row],[Energy User RTM Analysis]]=1),INDEX(Definitions!$B$21:$B$37,MATCH(Table3[[#Headers],[Energy User RTM Analysis]],Definitions!$A$21:$A$37,0)),Table3[[#This Row],[Energy User RTM Analysis]]=0,0)} -> 0 | BA20: {=_xlfn.IFS(AND(Table3[[#This Row],[Scale]:[Scale]]="Large",Table3[[#This Row],[Energy User Forecasts]]=1),INDEX(Definitions!$C$21:$C$37,MATCH(Table3[[#Headers],[Energy User Forecasts]],Definitions!$A$21:$A$37,0)),AND(Table3[[#This Row],[Scale]:[Scale]]="Small",Table3[[#This Row],[Energy User Forecasts]]=1),INDEX(Definitions!$B$21:$B$37,MATCH(Table3[[#Headers],[Energy User Forecasts]],Definitions!$A$21:$A$37,0)),Table3[[#This Row],[Energy User Forecasts]]=0,0)} -> 0 | BB20: {=_xlfn.IFS(AND(Table3[[#This Row],[Scale]:[Scale]]="Large",Table3[[#This Row],[Energy User Regulation]]=1),INDEX(Definitions!$C$21:$C$37,MATCH(Table3[[#Headers],[Energy User Regulation]],Definitions!$A$21:$A$37,0)),AND(Table3[[#This Row],[Scale]:[Scale]]="Small",Table3[[#This Row],[Energy User Regulation]]=1),INDEX(Definitions!$B$21:$B$37,MATCH(Table3[[#Headers],[Energy User Regulation]],Definitions!$A$21:$A$37,0)),Table3[[#This Row],[Energy User Regulation]]=0,0)} -> 0 | BC20: =IF(SUM(Table3[[#This Row],[Column2]:[Column18]])>Table3[[#This Row],[Column19]],Table3[[#This Row],[Column19]],SUM(Table3[[#This Row],[Column2]:[Column18]])) -> 250000 | BD20: =Table3[[#This Row],[Total Spend]]/SUM(Table3[[#This Row],[Column2]:[Column18]]) -> 0.95456281
A21: Smartest Energy Limited | B21: Yes | C21: Yes | D21: 45566 | E21: Large | F21: =INDEX(Definitions!$G$13:$G$17,MATCH(Table3[[#This Row],[Propensity to buy/ buyer readiness]],Definitions!$A$13:$A$17,0)) -> 250000 | G21: 5 | H21: 5 | I21: 5 | J21: 5 | K21: 5 | L21: =SUM(Table3[[#This Row],[Strategic priority segment]:[Propensity to buy/ buyer readiness]]) -> 25 | M21: Energy Supply | N21: Energy supplier | O21: Energy traders | U21: 1 | V21: 1 | W21: 1 | X21: 1 | Y21: 1 | Z21: 0 | AA21: 1 | AB21: 0 | AC21: 0 | AD21: 1 | AE21: 1 | AF21: 1 | AG21: 0 | AH21: 0 | AI21: 0 | AJ21: 0 | AK21: 0 | AL21: {=_xlfn.IFS(AND(Table3[[#This Row],[Scale]:[Scale]]="Large",Table3[[#This Row],[Industry Essentials]]=1),INDEX(Definitions!$C$21:$C$37,MATCH(Table3[[#Headers],[Industry Essentials]],Definitions!$A$21:$A$37,0)),AND(Table3[[#This Row],[Scale]:[Scale]]="Small",Table3[[#This Row],[Industry Essentials]]=1),INDEX(Definitions!$B$21:$B$37,MATCH(Table3[[#Headers],[Industry Essentials]],Definitions!$A$21:$A$37,0)),Table3[[#This Row],[Industry Essentials]]=0,0)} -> 10800 | AM21: {=_xlfn.IFS(AND(Table3[[#This Row],[Scale]:[Scale]]="Large",Table3[[#This Row],[Energy Supply Market Intelligence]]=1),INDEX(Definitions!$C$21:$C$37,MATCH(Table3[[#Headers],[Energy Supply Market Intelligence]],Definitions!$A$21:$A$37,0)),AND(Table3[[#This Row],[Scale]:[Scale]]="Small",Table3[[#This Row],[Energy Supply Market Intelligence]]=1),INDEX(Definitions!$B$21:$B$37,MATCH(Table3[[#Headers],[Energy Supply Market Intelligence]],Definitions!$A$21:$A$37,0)),Table3[[#This Row],[Energy Supply Market Intelligence]]=0,0)} -> 43200 | AN21: {=_xlfn.IFS(AND(Table3[[#This Row],[Scale]:[Scale]]="Large",Table3[[#This Row],[Energy Supply RTM Analysis]]=1),INDEX(Definitions!$C$21:$C$37,MATCH(Table3[[#Headers],[Energy Supply RTM Analysis]],Definitions!$A$21:$A$37,0)),AND(Table3[[#This Row],[Scale]:[Scale]]="Small",Table3[[#This Row],[Energy Supply RTM Analysis]]=1),INDEX(Definitions!$B$21:$B$37,MATCH(Table3[[#Headers],[Energy Supply RTM Analysis]],Definitions!$A$21:$A$37,0)),Table3[[#This Row],[Energy Supply RTM Analysis]]=0,0)} -> 73800 | AO21: {=_xlfn.IFS(AND(Table3[[#This Row],[Scale]:[Scale]]="Large",Table3[[#This Row],[Energy Supply Forecasts]]=1),INDEX(Definitions!$C$21:$C$37,MATCH(Table3[[#Headers],[Energy Supply Forecasts]],Definitions!$A$21:$A$37,0)),AND(Table3[[#This Row],[Scale]:[Scale]]="Small",Table3[[#This Row],[Energy Supply Forecasts]]=1),INDEX(Definitions!$B$21:$B$37,MATCH(Table3[[#Headers],[Energy Supply Forecasts]],Definitions!$A$21:$A$37,0)),Table3[[#This Row],[Energy Supply Forecasts]]=0,0)} -> 48600 | AP21: {=_xlfn.IFS(AND(Table3[[#This Row],[Scale]:[Scale]]="Large",Table3[[#This Row],[Energy Supply Regulation]]=1),INDEX(Definitions!$C$21:$C$37,MATCH(Table3[[#Headers],[Energy Supply Regulation]],Definitions!$A$21:$A$37,0)),AND(Table3[[#This Row],[Scale]:[Scale]]="Small",Table3[[#This Row],[Energy Supply Regulation]]=1),INDEX(Definitions!$B$21:$B$37,MATCH(Table3[[#Headers],[Energy Supply Regulation]],Definitions!$A$21:$A$37,0)),Table3[[#This Row],[Energy Supply Regulation]]=0,0)} -> 55800 | AQ21: {=_xlfn.IFS(AND(Table3[[#This Row],[Scale]:[Scale]]="Large",Table3[[#This Row],[Renewables Market Intelligence]]=1),INDEX(Definitions!$C$21:$C$37,MATCH(Table3[[#Headers],[Renewables Market Intelligence]],Definitions!$A$21:$A$37,0)),AND(Table3[[#This Row],[Scale]:[Scale]]="Small",Table3[[#This Row],[Renewables Market Intelligence]]=1),INDEX(Definitions!$B$21:$B$37,MATCH(Table3[[#Headers],[Renewables Market Intelligence]],Definitions!$A$21:$A$37,0)),Table3[[#This Row],[Renewables Market Intelligence]]=0,0)} -> 0 | AR21: {=_xlfn.IFS(AND(Table3[[#This Row],[Scale]:[Scale]]="Large",Table3[[#This Row],[Renewables RTM Analysis]]=1),INDEX(Definitions!$C$21:$C$37,MATCH(Table3[[#Headers],[Renewables RTM Analysis]],Definitions!$A$21:$A$37,0)),AND(Table3[[#This Row],[Scale]:[Scale]]="Small",Table3[[#This Row],[Renewables RTM Analysis]]=1),INDEX(Definitions!$B$21:$B$37,MATCH(Table3[[#Headers],[Renewables RTM Analysis]],Definitions!$A$21:$A$37,0)),Table3[[#This Row],[Renewables RTM Analysis]]=0,0)} -> 20700 | AS21: {=_xlfn.IFS(AND(Table3[[#This Row],[Scale]:[Scale]]="Large",Table3[[#This Row],[Renewables Forecasts]]=1),INDEX(Definitions!$C$21:$C$37,MATCH(Table3[[#Headers],[Renewables Forecasts]],Definitions!$A$21:$A$37,0)),AND(Table3[[#This Row],[Scale]:[Scale]]="Small",Table3[[#This Row],[Renewables Forecasts]]=1),INDEX(Definitions!$B$21:$B$37,MATCH(Table3[[#Headers],[Renewables Forecasts]],Definitions!$A$21:$A$37,0)),Table3[[#This Row],[Renewables Forecasts]]=0,0)} -> 0 | AT21: {=_xlfn.IFS(AND(Table3[[#This Row],[Scale]:[Scale]]="Large",Table3[[#This Row],[Renewables Regulation]]=1),INDEX(Definitions!$C$21:$C$37,MATCH(Table3[[#Headers],[Renewables Regulation]],Definitions!$A$21:$A$37,0)),AND(Table3[[#This Row],[Scale]:[Scale]]="Small",Table3[[#This Row],[Renewables Regulation]]=1),INDEX(Definitions!$B$21:$B$37,MATCH(Table3[[#Headers],[Renewables Regulation]],Definitions!$A$21:$A$37,0)),Table3[[#This Row],[Renewables Regulation]]=0,0)} -> 0 | AU21: {=_xlfn.IFS(AND(Table3[[#This Row],[Scale]:[Scale]]="Large",Table3[[#This Row],[Flexibility Market Intelligence]]=1),INDEX(Definitions!$C$21:$C$37,MATCH(Table3[[#Headers],[Flexibility Market Intelligence]],Definitions!$A$21:$A$37,0)),AND(Table3[[#This Row],[Scale]:[Scale]]="Small",Table3[[#This Row],[Flexibility Market Intelligence]]=1),INDEX(Definitions!$B$21:$B$37,MATCH(Table3[[#Headers],[Flexibility Market Intelligence]],Definitions!$A$21:$A$37,0)),Table3[[#This Row],[Flexibility Market Intelligence]]=0,0)} -> 29700 | AV21: {=_xlfn.IFS(AND(Table3[[#This Row],[Scale]:[Scale]]="Large",Table3[[#This Row],[Flexibility RTM Analysis]]=1),INDEX(Definitions!$C$21:$C$37,MATCH(Table3[[#Headers],[Flexibility RTM Analysis]],Definitions!$A$21:$A$37,0)),AND(Table3[[#This Row],[Scale]:[Scale]]="Small",Table3[[#This Row],[Flexibility RTM Analysis]]=1),INDEX(Definitions!$B$21:$B$37,MATCH(Table3[[#Headers],[Flexibility RTM Analysis]],Definitions!$A$21:$A$37,0)),Table3[[#This Row],[Flexibility RTM Analysis]]=0,0)} -> 10800 | AW21: {=_xlfn.IFS(AND(Table3[[#This Row],[Scale]:[Scale]]="Large",Table3[[#This Row],[Flexibility Forecasts]]=1),INDEX(Definitions!$C$21:$C$37,MATCH(Table3[[#Headers],[Flexibility Forecasts]],Definitions!$A$21:$A$37,0)),AND(Table3[[#This Row],[Scale]:[Scale]]="Small",Table3[[#This Row],[Flexibility Forecasts]]=1),INDEX(Definitions!$B$21:$B$37,MATCH(Table3[[#Headers],[Flexibility Forecasts]],Definitions!$A$21:$A$37,0)),Table3[[#This Row],[Flexibility Forecasts]]=0,0)} -> 44100 | AX21: {=_xlfn.IFS(AND(Table3[[#This Row],[Scale]:[Scale]]="Large",Table3[[#This Row],[Flexibility Regulation]]=1),INDEX(Definitions!$C$21:$C$37,MATCH(Table3[[#Headers],[Flexibility Regulation]],Definitions!$A$21:$A$37,0)),AND(Table3[[#This Row],[Scale]:[Scale]]="Small",Table3[[#This Row],[Flexibility Regulation]]=1),INDEX(Definitions!$B$21:$B$37,MATCH(Table3[[#Headers],[Flexibility Regulation]],Definitions!$A$21:$A$37,0)),Table3[[#This Row],[Flexibility Regulation]]=0,0)} -> 0 | AY21: {=_xlfn.IFS(AND(Table3[[#This Row],[Scale]:[Scale]]="Large",Table3[[#This Row],[Business Energy Essentials]]=1),INDEX(Definitions!$C$21:$C$37,MATCH(Table3[[#Headers],[Business Energy Essentials]],Definitions!$A$21:$A$37,0)),AND(Table3[[#This Row],[Scale]:[Scale]]="Small",Table3[[#This Row],[Business Energy Essentials]]=1),INDEX(Definitions!$B$21:$B$37,MATCH(Table3[[#Headers],[Business Energy Essentials]],Definitions!$A$21:$A$37,0)),Table3[[#This Row],[Business Energy Essentials]]=0,0)} -> 0 | AZ21: {=_xlfn.IFS(AND(Table3[[#This Row],[Scale]:[Scale]]="Large",Table3[[#This Row],[Energy User RTM Analysis]]=1),INDEX(Definitions!$C$21:$C$37,MATCH(Table3[[#Headers],[Energy User RTM Analysis]],Definitions!$A$21:$A$37,0)),AND(Table3[[#This Row],[Scale]:[Scale]]="Small",Table3[[#This Row],[Energy User RTM Analysis]]=1),INDEX(Definitions!$B$21:$B$37,MATCH(Table3[[#Headers],[Energy User RTM Analysis]],Definitions!$A$21:$A$37,0)),Table3[[#This Row],[Energy User RTM Analysis]]=0,0)} -> 0 | BA21: {=_xlfn.IFS(AND(Table3[[#This Row],[Scale]:[Scale]]="Large",Table3[[#This Row],[Energy User Forecasts]]=1),INDEX(Definitions!$C$21:$C$37,MATCH(Table3[[#Headers],[Energy User Forecasts]],Definitions!$A$21:$A$37,0)),AND(Table3[[#This Row],[Scale]:[Scale]]="Small",Table3[[#This Row],[Energy User Forecasts]]=1),INDEX(Definitions!$B$21:$B$37,MATCH(Table3[[#Headers],[Energy User Forecasts]],Definitions!$A$21:$A$37,0)),Table3[[#This Row],[Energy User Forecasts]]=0,0)} -> 0 | BB21: {=_xlfn.IFS(AND(Table3[[#This Row],[Scale]:[Scale]]="Large",Table3[[#This Row],[Energy User Regulation]]=1),INDEX(Definitions!$C$21:$C$37,MATCH(Table3[[#Headers],[Energy User Regulation]],Definitions!$A$21:$A$37,0)),AND(Table3[[#This Row],[Scale]:[Scale]]="Small",Table3[[#This Row],[Energy User Regulation]]=1),INDEX(Definitions!$B$21:$B$37,MATCH(Table3[[#Headers],[Energy User Regulation]],Definitions!$A$21:$A$37,0)),Table3[[#This Row],[Energy User Regulation]]=0,0)} -> 0 | BC21: =IF(SUM(Table3[[#This Row],[Column2]:[Column18]])>Table3[[#This Row],[Column19]],Table3[[#This Row],[Column19]],SUM(Table3[[#This Row],[Column2]:[Column18]])) -> 250000 | BD21: =Table3[[#This Row],[Total Spend]]/SUM(Table3[[#This Row],[Column2]:[Column18]]) -> 0.74074074
A22: SSE Energy Customer Solutions | B22: Yes | C22: Yes | D22: 45566 | E22: Large | F22: =INDEX(Definitions!$G$13:$G$17,MATCH(Table3[[#This Row],[Propensity to buy/ buyer readiness]],Definitions!$A$13:$A$17,0)) -> 250000 | G22: 5 | H22: 5 | I22: 5 | J22: 5 | K22: 5 | L22: =SUM(Table3[[#This Row],[Strategic priority segment]:[Propensity to buy/ buyer readiness]]) -> 25 | M22: Energy Supply | N22: Energy supplier | O22: Energy traders | P22: Metering | U22: 1 | V22: 1 | W22: 1 | X22: 1 | Y22: 1 | Z22: 0 | AA22: 1 | AB22: 0 | AC22: 0 | AD22: 1 | AE22: 1 | AF22: 1 | AG22: 0 | AH22: 0 | AI22: 0 | AJ22: 0 | AK22: 0 | AL22: {=_xlfn.IFS(AND(Table3[[#This Row],[Scale]:[Scale]]="Large",Table3[[#This Row],[Industry Essentials]]=1),INDEX(Definitions!$C$21:$C$37,MATCH(Table3[[#Headers],[Industry Essentials]],Definitions!$A$21:$A$37,0)),AND(Table3[[#This Row],[Scale]:[Scale]]="Small",Table3[[#This Row],[Industry Essentials]]=1),INDEX(Definitions!$B$21:$B$37,MATCH(Table3[[#Headers],[Industry Essentials]],Definitions!$A$21:$A$37,0)),Table3[[#This Row],[Industry Essentials]]=0,0)} -> 10800 | AM22: {=_xlfn.IFS(AND(Table3[[#This Row],[Scale]:[Scale]]="Large",Table3[[#This Row],[Energy Supply Market Intelligence]]=1),INDEX(Definitions!$C$21:$C$37,MATCH(Table3[[#Headers],[Energy Supply Market Intelligence]],Definitions!$A$21:$A$37,0)),AND(Table3[[#This Row],[Scale]:[Scale]]="Small",Table3[[#This Row],[Energy Supply Market Intelligence]]=1),INDEX(Definitions!$B$21:$B$37,MATCH(Table3[[#Headers],[Energy Supply Market Intelligence]],Definitions!$A$21:$A$37,0)),Table3[[#This Row],[Energy Supply Market Intelligence]]=0,0)} -> 43200 | AN22: {=_xlfn.IFS(AND(Table3[[#This Row],[Scale]:[Scale]]="Large",Table3[[#This Row],[Energy Supply RTM Analysis]]=1),INDEX(Definitions!$C$21:$C$37,MATCH(Table3[[#Headers],[Energy Supply RTM Analysis]],Definitions!$A$21:$A$37,0)),AND(Table3[[#This Row],[Scale]:[Scale]]="Small",Table3[[#This Row],[Energy Supply RTM Analysis]]=1),INDEX(Definitions!$B$21:$B$37,MATCH(Table3[[#Headers],[Energy Supply RTM Analysis]],Definitions!$A$21:$A$37,0)),Table3[[#This Row],[Energy Supply RTM Analysis]]=0,0)} -> 73800 | AO22: {=_xlfn.IFS(AND(Table3[[#This Row],[Scale]:[Scale]]="Large",Table3[[#This Row],[Energy Supply Forecasts]]=1),INDEX(Definitions!$C$21:$C$37,MATCH(Table3[[#Headers],[Energy Supply Forecasts]],Definitions!$A$21:$A$37,0)),AND(Table3[[#This Row],[Scale]:[Scale]]="Small",Table3[[#This Row],[Energy Supply Forecasts]]=1),INDEX(Definitions!$B$21:$B$37,MATCH(Table3[[#Headers],[Energy Supply Forecasts]],Definitions!$A$21:$A$37,0)),Table3[[#This Row],[Energy Supply Forecasts]]=0,0)} -> 48600 | AP22: {=_xlfn.IFS(AND(Table3[[#This Row],[Scale]:[Scale]]="Large",Table3[[#This Row],[Energy Supply Regulation]]=1),INDEX(Definitions!$C$21:$C$37,MATCH(Table3[[#Headers],[Energy Supply Regulation]],Definitions!$A$21:$A$37,0)),AND(Table3[[#This Row],[Scale]:[Scale]]="Small",Table3[[#This Row],[Energy Supply Regulation]]=1),INDEX(Definitions!$B$21:$B$37,MATCH(Table3[[#Headers],[Energy Supply Regulation]],Definitions!$A$21:$A$37,0)),Table3[[#This Row],[Energy Supply Regulation]]=0,0)} -> 55800 | AQ22: {=_xlfn.IFS(AND(Table3[[#This Row],[Scale]:[Scale]]="Large",Table3[[#This Row],[Renewables Market Intelligence]]=1),INDEX(Definitions!$C$21:$C$37,MATCH(Table3[[#Headers],[Renewables Market Intelligence]],Definitions!$A$21:$A$37,0)),AND(Table3[[#This Row],[Scale]:[Scale]]="Small",Table3[[#This Row],[Renewables Market Intelligence]]=1),INDEX(Definitions!$B$21:$B$37,MATCH(Table3[[#Headers],[Renewables Market Intelligence]],Definitions!$A$21:$A$37,0)),Table3[[#This Row],[Renewables Market Intelligence]]=0,0)} -> 0 | AR22: {=_xlfn.IFS(AND(Table3[[#This Row],[Scale]:[Scale]]="Large",Table3[[#This Row],[Renewables RTM Analysis]]=1),INDEX(Definitions!$C$21:$C$37,MATCH(Table3[[#Headers],[Renewables RTM Analysis]],Definitions!$A$21:$A$37,0)),AND(Table3[[#This Row],[Scale]:[Scale]]="Small",Table3[[#This Row],[Renewables RTM Analysis]]=1),INDEX(Definitions!$B$21:$B$37,MATCH(Table3[[#Headers],[Renewables RTM Analysis]],Definitions!$A$21:$A$37,0)),Table3[[#This Row],[Renewables RTM Analysis]]=0,0)} -> 20700 | AS22: {=_xlfn.IFS(AND(Table3[[#This Row],[Scale]:[Scale]]="Large",Table3[[#This Row],[Renewables Forecasts]]=1),INDEX(Definitions!$C$21:$C$37,MATCH(Table3[[#Headers],[Renewables Forecasts]],Definitions!$A$21:$A$37,0)),AND(Table3[[#This Row],[Scale]:[Scale]]="Small",Table3[[#This Row],[Renewables Forecasts]]=1),INDEX(Definitions!$B$21:$B$37,MATCH(Table3[[#Headers],[Renewables Forecasts]],Definitions!$A$21:$A$37,0)),Table3[[#This Row],[Renewables Forecasts]]=0,0)} -> 0 | AT22: {=_xlfn.IFS(AND(Table3[[#This Row],[Scale]:[Scale]]="Large",Table3[[#This Row],[Renewables Regulation]]=1),INDEX(Definitions!$C$21:$C$37,MATCH(Table3[[#Headers],[Renewables Regulation]],Definitions!$A$21:$A$37,0)),AND(Table3[[#This Row],[Scale]:[Scale]]="Small",Table3[[#This Row],[Renewables Regulation]]=1),INDEX(Definitions!$B$21:$B$37,MATCH(Table3[[#Headers],[Renewables Regulation]],Definitions!$A$21:$A$37,0)),Table3[[#This Row],[Renewables Regulation]]=0,0)} -> 0 | AU22: {=_xlfn.IFS(AND(Table3[[#This Row],[Scale]:[Scale]]="Large",Table3[[#This Row],[Flexibility Market Intelligence]]=1),INDEX(Definitions!$C$21:$C$37,MATCH(Table3[[#Headers],[Flexibility Market Intelligence]],Definitions!$A$21:$A$37,0)),AND(Table3[[#This Row],[Scale]:[Scale]]="Small",Table3[[#This Row],[Flexibility Market Intelligence]]=1),INDEX(Definitions!$B$21:$B$37,MATCH(Table3[[#Headers],[Flexibility Market Intelligence]],Definitions!$A$21:$A$37,0)),Table3[[#This Row],[Flexibility Market Intelligence]]=0,0)} -> 29700 | AV22: {=_xlfn.IFS(AND(Table3[[#This Row],[Scale]:[Scale]]="Large",Table3[[#This Row],[Flexibility RTM Analysis]]=1),INDEX(Definitions!$C$21:$C$37,MATCH(Table3[[#Headers],[Flexibility RTM Analysis]],Definitions!$A$21:$A$37,0)),AND(Table3[[#This Row],[Scale]:[Scale]]="Small",Table3[[#This Row],[Flexibility RTM Analysis]]=1),INDEX(Definitions!$B$21:$B$37,MATCH(Table3[[#Headers],[Flexibility RTM Analysis]],Definitions!$A$21:$A$37,0)),Table3[[#This Row],[Flexibility RTM Analysis]]=0,0)} -> 10800 | AW22: {=_xlfn.IFS(AND(Table3[[#This Row],[Scale]:[Scale]]="Large",Table3[[#This Row],[Flexibility Forecasts]]=1),INDEX(Definitions!$C$21:$C$37,MATCH(Table3[[#Headers],[Flexibility Forecasts]],Definitions!$A$21:$A$37,0)),AND(Table3[[#This Row],[Scale]:[Scale]]="Small",Table3[[#This Row],[Flexibility Forecasts]]=1),INDEX(Definitions!$B$21:$B$37,MATCH(Table3[[#Headers],[Flexibility Forecasts]],Definitions!$A$21:$A$37,0)),Table3[[#This Row],[Flexibility Forecasts]]=0,0)} -> 44100 | AX22: {=_xlfn.IFS(AND(Table3[[#This Row],[Scale]:[Scale]]="Large",Table3[[#This Row],[Flexibility Regulation]]=1),INDEX(Definitions!$C$21:$C$37,MATCH(Table3[[#Headers],[Flexibility Regulation]],Definitions!$A$21:$A$37,0)),AND(Table3[[#This Row],[Scale]:[Scale]]="Small",Table3[[#This Row],[Flexibility Regulation]]=1),INDEX(Definitions!$B$21:$B$37,MATCH(Table3[[#Headers],[Flexibility Regulation]],Definitions!$A$21:$A$37,0)),Table3[[#This Row],[Flexibility Regulation]]=0,0)} -> 0 | AY22: {=_xlfn.IFS(AND(Table3[[#This Row],[Scale]:[Scale]]="Large",Table3[[#This Row],[Business Energy Essentials]]=1),INDEX(Definitions!$C$21:$C$37,MATCH(Table3[[#Headers],[Business Energy Essentials]],Definitions!$A$21:$A$37,0)),AND(Table3[[#This Row],[Scale]:[Scale]]="Small",Table3[[#This Row],[Business Energy Essentials]]=1),INDEX(Definitions!$B$21:$B$37,MATCH(Table3[[#Headers],[Business Energy Essentials]],Definitions!$A$21:$A$37,0)),Table3[[#This Row],[Business Energy Essentials]]=0,0)} -> 0 | AZ22: {=_xlfn.IFS(AND(Table3[[#This Row],[Scale]:[Scale]]="Large",Table3[[#This Row],[Energy User RTM Analysis]]=1),INDEX(Definitions!$C$21:$C$37,MATCH(Table3[[#Headers],[Energy User RTM Analysis]],Definitions!$A$21:$A$37,0)),AND(Table3[[#This Row],[Scale]:[Scale]]="Small",Table3[[#This Row],[Energy User RTM Analysis]]=1),INDEX(Definitions!$B$21:$B$37,MATCH(Table3[[#Headers],[Energy User RTM Analysis]],Definitions!$A$21:$A$37,0)),Table3[[#This Row],[Energy User RTM Analysis]]=0,0)} -> 0 | BA22: {=_xlfn.IFS(AND(Table3[[#This Row],[Scale]:[Scale]]="Large",Table3[[#This Row],[Energy User Forecasts]]=1),INDEX(Definitions!$C$21:$C$37,MATCH(Table3[[#Headers],[Energy User Forecasts]],Definitions!$A$21:$A$37,0)),AND(Table3[[#This Row],[Scale]:[Scale]]="Small",Table3[[#This Row],[Energy User Forecasts]]=1),INDEX(Definitions!$B$21:$B$37,MATCH(Table3[[#Headers],[Energy User Forecasts]],Definitions!$A$21:$A$37,0)),Table3[[#This Row],[Energy User Forecasts]]=0,0)} -> 0 | BB22: {=_xlfn.IFS(AND(Table3[[#This Row],[Scale]:[Scale]]="Large",Table3[[#This Row],[Energy User Regulation]]=1),INDEX(Definitions!$C$21:$C$37,MATCH(Table3[[#Headers],[Energy User Regulation]],Definitions!$A$21:$A$37,0)),AND(Table3[[#This Row],[Scale]:[Scale]]="Small",Table3[[#This Row],[Energy User Regulation]]=1),INDEX(Definitions!$B$21:$B$37,MATCH(Table3[[#Headers],[Energy User Regulation]],Definitions!$A$21:$A$37,0)),Table3[[#This Row],[Energy User Regulation]]=0,0)} -> 0 | BC22: =IF(SUM(Table3[[#This Row],[Column2]:[Column18]])>Table3[[#This Row],[Column19]],Table3[[#This Row],[Column19]],SUM(Table3[[#This Row],[Column2]:[Column18]])) -> 250000 | BD22: =Table3[[#This Row],[Total Spend]]/SUM(Table3[[#This Row],[Column2]:[Column18]]) -> 0.74074074
A23: SSE Energy Supply Ltd | B23: Yes | C23: Yes | D23: 45566 | E23: Large | F23: =INDEX(Definitions!$G$13:$G$17,MATCH(Table3[[#This Row],[Propensity to buy/ buyer readiness]],Definitions!$A$13:$A$17,0)) -> 250000 | G23: 5 | H23: 5 | I23: 5 | J23: 5 | K23: 5 | L23: =SUM(Table3[[#This Row],[Strategic priority segment]:[Propensity to buy/ buyer readiness]]) -> 25 | M23: Energy Supply | N23: Energy supplier | O23: Energy traders | U23: 1 | V23: 1 | W23: 1 | X23: 1 | Y23: 1 | Z23: 0 | AA23: 1 | AB23: 0 | AC23: 0 | AD23: 1 | AE23: 1 | AF23: 1 | AG23: 0 | AH23: 0 | AI23: 0 | AJ23: 0 | AK23: 0 | AL23: {=_xlfn.IFS(AND(Table3[[#This Row],[Scale]:[Scale]]="Large",Table3[[#This Row],[Industry Essentials]]=1),INDEX(Definitions!$C$21:$C$37,MATCH(Table3[[#Headers],[Industry Essentials]],Definitions!$A$21:$A$37,0)),AND(Table3[[#This Row],[Scale]:[Scale]]="Small",Table3[[#This Row],[Industry Essentials]]=1),INDEX(Definitions!$B$21:$B$37,MATCH(Table3[[#Headers],[Industry Essentials]],Definitions!$A$21:$A$37,0)),Table3[[#This Row],[Industry Essentials]]=0,0)} -> 10800 | AM23: {=_xlfn.IFS(AND(Table3[[#This Row],[Scale]:[Scale]]="Large",Table3[[#This Row],[Energy Supply Market Intelligence]]=1),INDEX(Definitions!$C$21:$C$37,MATCH(Table3[[#Headers],[Energy Supply Market Intelligence]],Definitions!$A$21:$A$37,0)),AND(Table3[[#This Row],[Scale]:[Scale]]="Small",Table3[[#This Row],[Energy Supply Market Intelligence]]=1),INDEX(Definitions!$B$21:$B$37,MATCH(Table3[[#Headers],[Energy Supply Market Intelligence]],Definitions!$A$21:$A$37,0)),Table3[[#This Row],[Energy Supply Market Intelligence]]=0,0)} -> 43200 | AN23: {=_xlfn.IFS(AND(Table3[[#This Row],[Scale]:[Scale]]="Large",Table3[[#This Row],[Energy Supply RTM Analysis]]=1),INDEX(Definitions!$C$21:$C$37,MATCH(Table3[[#Headers],[Energy Supply RTM Analysis]],Definitions!$A$21:$A$37,0)),AND(Table3[[#This Row],[Scale]:[Scale]]="Small",Table3[[#This Row],[Energy Supply RTM Analysis]]=1),INDEX(Definitions!$B$21:$B$37,MATCH(Table3[[#Headers],[Energy Supply RTM Analysis]],Definitions!$A$21:$A$37,0)),Table3[[#This Row],[Energy Supply RTM Analysis]]=0,0)} -> 73800 | AO23: {=_xlfn.IFS(AND(Table3[[#This Row],[Scale]:[Scale]]="Large",Table3[[#This Row],[Energy Supply Forecasts]]=1),INDEX(Definitions!$C$21:$C$37,MATCH(Table3[[#Headers],[Energy Supply Forecasts]],Definitions!$A$21:$A$37,0)),AND(Table3[[#This Row],[Scale]:[Scale]]="Small",Table3[[#This Row],[Energy Supply Forecasts]]=1),INDEX(Definitions!$B$21:$B$37,MATCH(Table3[[#Headers],[Energy Supply Forecasts]],Definitions!$A$21:$A$37,0)),Table3[[#This Row],[Energy Supply Forecasts]]=0,0)} -> 48600 | AP23: {=_xlfn.IFS(AND(Table3[[#This Row],[Scale]:[Scale]]="Large",Table3[[#This Row],[Energy Supply Regulation]]=1),INDEX(Definitions!$C$21:$C$37,MATCH(Table3[[#Headers],[Energy Supply Regulation]],Definitions!$A$21:$A$37,0)),AND(Table3[[#This Row],[Scale]:[Scale]]="Small",Table3[[#This Row],[Energy Supply Regulation]]=1),INDEX(Definitions!$B$21:$B$37,MATCH(Table3[[#Headers],[Energy Supply Regulation]],Definitions!$A$21:$A$37,0)),Table3[[#This Row],[Energy Supply Regulation]]=0,0)} -> 55800 | AQ23: {=_xlfn.IFS(AND(Table3[[#This Row],[Scale]:[Scale]]="Large",Table3[[#This Row],[Renewables Market Intelligence]]=1),INDEX(Definitions!$C$21:$C$37,MATCH(Table3[[#Headers],[Renewables Market Intelligence]],Definitions!$A$21:$A$37,0)),AND(Table3[[#This Row],[Scale]:[Scale]]="Small",Table3[[#This Row],[Renewables Market Intelligence]]=1),INDEX(Definitions!$B$21:$B$37,MATCH(Table3[[#Headers],[Renewables Market Intelligence]],Definitions!$A$21:$A$37,0)),Table3[[#This Row],[Renewables Market Intelligence]]=0,0)} -> 0 | AR23: {=_xlfn.IFS(AND(Table3[[#This Row],[Scale]:[Scale]]="Large",Table3[[#This Row],[Renewables RTM Analysis]]=1),INDEX(Definitions!$C$21:$C$37,MATCH(Table3[[#Headers],[Renewables RTM Analysis]],Definitions!$A$21:$A$37,0)),AND(Table3[[#This Row],[Scale]:[Scale]]="Small",Table3[[#This Row],[Renewables RTM Analysis]]=1),INDEX(Definitions!$B$21:$B$37,MATCH(Table3[[#Headers],[Renewables RTM Analysis]],Definitions!$A$21:$A$37,0)),Table3[[#This Row],[Renewables RTM Analysis]]=0,0)} -> 20700 | AS23: {=_xlfn.IFS(AND(Table3[[#This Row],[Scale]:[Scale]]="Large",Table3[[#This Row],[Renewables Forecasts]]=1),INDEX(Definitions!$C$21:$C$37,MATCH(Table3[[#Headers],[Renewables Forecasts]],Definitions!$A$21:$A$37,0)),AND(Table3[[#This Row],[Scale]:[Scale]]="Small",Table3[[#This Row],[Renewables Forecasts]]=1),INDEX(Definitions!$B$21:$B$37,MATCH(Table3[[#Headers],[Renewables Forecasts]],Definitions!$A$21:$A$37,0)),Table3[[#This Row],[Renewables Forecasts]]=0,0)} -> 0 | AT23: {=_xlfn.IFS(AND(Table3[[#This Row],[Scale]:[Scale]]="Large",Table3[[#This Row],[Renewables Regulation]]=1),INDEX(Definitions!$C$21:$C$37,MATCH(Table3[[#Headers],[Renewables Regulation]],Definitions!$A$21:$A$37,0)),AND(Table3[[#This Row],[Scale]:[Scale]]="Small",Table3[[#This Row],[Renewables Regulation]]=1),INDEX(Definitions!$B$21:$B$37,MATCH(Table3[[#Headers],[Renewables Regulation]],Definitions!$A$21:$A$37,0)),Table3[[#This Row],[Renewables Regulation]]=0,0)} -> 0 | AU23: {=_xlfn.IFS(AND(Table3[[#This Row],[Scale]:[Scale]]="Large",Table3[[#This Row],[Flexibility Market Intelligence]]=1),INDEX(Definitions!$C$21:$C$37,MATCH(Table3[[#Headers],[Flexibility Market Intelligence]],Definitions!$A$21:$A$37,0)),AND(Table3[[#This Row],[Scale]:[Scale]]="Small",Table3[[#This Row],[Flexibility Market Intelligence]]=1),INDEX(Definitions!$B$21:$B$37,MATCH(Table3[[#Headers],[Flexibility Market Intelligence]],Definitions!$A$21:$A$37,0)),Table3[[#This Row],[Flexibility Market Intelligence]]=0,0)} -> 29700 | AV23: {=_xlfn.IFS(AND(Table3[[#This Row],[Scale]:[Scale]]="Large",Table3[[#This Row],[Flexibility RTM Analysis]]=1),INDEX(Definitions!$C$21:$C$37,MATCH(Table3[[#Headers],[Flexibility RTM Analysis]],Definitions!$A$21:$A$37,0)),AND(Table3[[#This Row],[Scale]:[Scale]]="Small",Table3[[#This Row],[Flexibility RTM Analysis]]=1),INDEX(Definitions!$B$21:$B$37,MATCH(Table3[[#Headers],[Flexibility RTM Analysis]],Definitions!$A$21:$A$37,0)),Table3[[#This Row],[Flexibility RTM Analysis]]=0,0)} -> 10800 | AW23: {=_xlfn.IFS(AND(Table3[[#This Row],[Scale]:[Scale]]="Large",Table3[[#This Row],[Flexibility Forecasts]]=1),INDEX(Definitions!$C$21:$C$37,MATCH(Table3[[#Headers],[Flexibility Forecasts]],Definitions!$A$21:$A$37,0)),AND(Table3[[#This Row],[Scale]:[Scale]]="Small",Table3[[#This Row],[Flexibility Forecasts]]=1),INDEX(Definitions!$B$21:$B$37,MATCH(Table3[[#Headers],[Flexibility Forecasts]],Definitions!$A$21:$A$37,0)),Table3[[#This Row],[Flexibility Forecasts]]=0,0)} -> 44100 | AX23: {=_xlfn.IFS(AND(Table3[[#This Row],[Scale]:[Scale]]="Large",Table3[[#This Row],[Flexibility Regulation]]=1),INDEX(Definitions!$C$21:$C$37,MATCH(Table3[[#Headers],[Flexibility Regulation]],Definitions!$A$21:$A$37,0)),AND(Table3[[#This Row],[Scale]:[Scale]]="Small",Table3[[#This Row],[Flexibility Regulation]]=1),INDEX(Definitions!$B$21:$B$37,MATCH(Table3[[#Headers],[Flexibility Regulation]],Definitions!$A$21:$A$37,0)),Table3[[#This Row],[Flexibility Regulation]]=0,0)} -> 0 | AY23: {=_xlfn.IFS(AND(Table3[[#This Row],[Scale]:[Scale]]="Large",Table3[[#This Row],[Business Energy Essentials]]=1),INDEX(Definitions!$C$21:$C$37,MATCH(Table3[[#Headers],[Business Energy Essentials]],Definitions!$A$21:$A$37,0)),AND(Table3[[#This Row],[Scale]:[Scale]]="Small",Table3[[#This Row],[Business Energy Essentials]]=1),INDEX(Definitions!$B$21:$B$37,MATCH(Table3[[#Headers],[Business Energy Essentials]],Definitions!$A$21:$A$37,0)),Table3[[#This Row],[Business Energy Essentials]]=0,0)} -> 0 | AZ23: {=_xlfn.IFS(AND(Table3[[#This Row],[Scale]:[Scale]]="Large",Table3[[#This Row],[Energy User RTM Analysis]]=1),INDEX(Definitions!$C$21:$C$37,MATCH(Table3[[#Headers],[Energy User RTM Analysis]],Definitions!$A$21:$A$37,0)),AND(Table3[[#This Row],[Scale]:[Scale]]="Small",Table3[[#This Row],[Energy User RTM Analysis]]=1),INDEX(Definitions!$B$21:$B$37,MATCH(Table3[[#Headers],[Energy User RTM Analysis]],Definitions!$A$21:$A$37,0)),Table3[[#This Row],[Energy User RTM Analysis]]=0,0)} -> 0 | BA23: {=_xlfn.IFS(AND(Table3[[#This Row],[Scale]:[Scale]]="Large",Table3[[#This Row],[Energy User Forecasts]]=1),INDEX(Definitions!$C$21:$C$37,MATCH(Table3[[#Headers],[Energy User Forecasts]],Definitions!$A$21:$A$37,0)),AND(Table3[[#This Row],[Scale]:[Scale]]="Small",Table3[[#This Row],[Energy User Forecasts]]=1),INDEX(Definitions!$B$21:$B$37,MATCH(Table3[[#Headers],[Energy User Forecasts]],Definitions!$A$21:$A$37,0)),Table3[[#This Row],[Energy User Forecasts]]=0,0)} -> 0 | BB23: {=_xlfn.IFS(AND(Table3[[#This Row],[Scale]:[Scale]]="Large",Table3[[#This Row],[Energy User Regulation]]=1),INDEX(Definitions!$C$21:$C$37,MATCH(Table3[[#Headers],[Energy User Regulation]],Definitions!$A$21:$A$37,0)),AND(Table3[[#This Row],[Scale]:[Scale]]="Small",Table3[[#This Row],[Energy User Regulation]]=1),INDEX(Definitions!$B$21:$B$37,MATCH(Table3[[#Headers],[Energy User Regulation]],Definitions!$A$21:$A$37,0)),Table3[[#This Row],[Energy User Regulation]]=0,0)} -> 0 | BC23: =IF(SUM(Table3[[#This Row],[Column2]:[Column18]])>Table3[[#This Row],[Column19]],Table3[[#This Row],[Column19]],SUM(Table3[[#This Row],[Column2]:[Column18]])) -> 250000 | BD23: =Table3[[#This Row],[Total Spend]]/SUM(Table3[[#This Row],[Column2]:[Column18]]) -> 0.74074074
